Workbook

Sheet Coded Passages
A1: Milei Climate Narratives — v2 Coded Passages · Data source for all summary sheets
A2: # | B2: Dimension | C2: Sub-dimension | D2: Dimension (Full) | E2: Sub-code (Full) | F2: Quoted Passage | G2: Analytical Memo | H2: Speech | I2: Date | J2: Venue / Type
A3: 1 | B3: D1.1 | C3: Anti-Casta (Elite Frame) | D3: D1.1 — State Intervention & Governance | E3: Anti-Casta (Elite Frame) | F3: Motivados por el deseo de pertenecer a una casta privilegiada, los principales líderes del mundo occidental han abandonado el modelo de la libertad. | G3: 'Casta privilegiada' extends Milei's domestic anti-elite frame to the global governance elite, targeting WEF participants. International climate institutions pre-emptively delegitimized as members of a global caste. | H3: WEF Davos 2024 | I3: 2024-01-17 | J3: Davos · Speech
A4: 2 | B4: D1.1 | C4: Anti-State / Anti-Bureaucratic | D4: D1.1 — State Intervention & Governance | E4: Anti-State / Anti-Bureaucratic | F4: Capas sobre capa de organismos, agencias y programas hasta alcanzar una hipertrofia de administraciones poco efectivas. | G4: Applies the domestic anti-bureaucratic critique at the international level, normalizing drastic reduction of the multilateral sustainability apparatus as rational efficiency reform. | H4: UN General Assembly 80th | I4: 2025-09-24 | J4: New York · Speech
A5: 3 | B5: D1.1 | C5: Anti-State / Anti-Bureaucratic | D5: D1.1 — State Intervention & Governance | E5: Anti-State / Anti-Bureaucratic | F5: La vida de todos nosotros dependa de un burócrata sentado en una oficina de lujo. | G5: 'Un burócrata sentado en una oficina de lujo' personifies the regulatory state as a rent-seeking class. Sustainability agencies, CONICET researchers, and UNFCCC secretariat staff are, by this logic, parasites. | H5: WEF Davos 2024 | I5: 2024-01-17 | J5: Davos · Speech
A6: 4 | B6: D1.1 | C6: Delegitimization of Regulation | D6: D1.1 — State Intervention & Governance | E6: Delegitimization of Regulation | F6: El marco teórico neoclásico termina siendo funcional a la intromisión del estado. El pretexto de un supuesto fallo de mercado introduce regulaciones que solo generan distorsiones en el sistema de precios. | G6: The attack on neoclassical economics demolishes the theoretical foundation of environmental regulation: mainstream climate policy derives from externality theory — precisely the 'instrumental' Milei argues serves state intrusion. | H6: WEF Davos 2024 | I6: 2024-01-17 | J6: Davos · Speech
A7: 5 | B7: D1.1 | C7: Delegitimization of Regulation | D7: D1.1 — State Intervention & Governance | E7: Delegitimization of Regulation | F7: Si las transacciones son voluntarias, el único contexto de fallo de mercado es si hay coacción. Y el único con la capacidad de coaccionar es el estado. Los fallos de mercado no existen. | G7: The inversion of causality — apparent market failures are actually state failures — performs total delegitimation of environmental regulation. Environmental regulation is recast as coercive imposition on voluntary exchange. | H7: WEF Davos 2024 | I7: 2024-01-17 | J7: Davos · Speech
A8: 6 | B8: D1.1 | C8: Delegitimization of Regulation | D8: D1.1 — State Intervention & Governance | E8: Delegitimization of Regulation | F8: Si no combatimos estas ideas, el único destino posible es que vamos a tener más estado, más regulación, más socialismo, más pobreza, menos libertad. | G8: The escalation chain — 'más estado, más regulación, más socialismo, más pobreza' — presents all regulation as steps in a deterministic descent toward poverty and unfreedom. Environmental regulation is subsumed within this chain. | H8: WEF Davos 2024 | I8: 2024-01-17 | J8: Davos · Speech
A9: 7 | B9: D1.1 | C9: Delegitimization of Regulation | D9: D1.1 — State Intervention & Governance | E9: Delegitimization of Regulation | F9: The functions of the state must once again be limited to defending the right to life, liberty and property. Any other function will inevitably lead to the 'omnipresent Leviathan' that we all suffer under today. | G9: The minimal-state principle categorically excludes environmental regulation as a legitimate state function. Climate policy falls outside life, liberty, and property — making it constitutionally illegitimate regardless of empirical merits. | H9: WEF Davos 2025 | I9: 2025-01-23 | J9: Davos · Speech
A10: 8 | B10: D1.1 | C10: Delegitimization of Regulation | D10: D1.1 — State Intervention & Governance | E10: Delegitimization of Regulation | F10: This required embracing a mathematical structure that left the door open to state intervention under the well-intentioned goal of correcting market failures, which do not really exist. The proof developed by Hans-Hermann Hoppe leaves no room for intervention. | G10: The Hoppe property-rights proof invoked to argue that the correct theoretical framework 'leaves no room for intervention.' For climate governance: the theoretical framework justifying carbon pricing and emissions regulation is replaced by one where intervention is logically prohibited. | H10: WEF Davos 2026 | I10: 2026-01-22 | J10: Davos · Speech
A11: 9 | B11: D1.1 | C11: Delegitimization of Regulation | D11: D1.1 — State Intervention & Governance | E11: Delegitimization of Regulation | F11: Intervention and regulation are dynamically inefficient because they are violent and therefore unjust. | G11: Most philosophically compressed Delegitimization_of_Regulation in the corpus. The argument flows from natural law through property rights theory to a categorical condemnation: regulation is violent AND unjust. Both dimensions — unjust and dynamically inefficient — are more comprehensive than prior formulations. | H11: WEF Davos 2026 | I11: 2026-01-22 | J11: Davos · Speech
A12: 10 | B12: D1.1 | C12: Deregulation Benefits | D12: D1.1 — State Intervention & Governance | E12: Deregulation Benefits | F12: Solo debemos apoyar iniciativas que no restrinjan la capacidad de los Estados de liberar sus fuerzas productivas, atraer inversión y fomentar el comercio. | G12: Only supporting initiatives that 'liberate productive forces, attract investment, and promote trade' frames deregulation as the poverty-reduction mechanism. Proposed as a constitutional principle for international governance. | H12: UN General Assembly 80th | I12: 2025-09-24 | J12: New York · Speech
A13: 11 | B13: D1.1 | C13: Deregulation Benefits | D13: D1.1 — State Intervention & Governance | E13: Deregulation Benefits | F13: La solución que propondrán los colectivistas no es mayor libertad sino mayor regulación, generando una espiral descendiente hasta que la vida de todos dependa de un burócrata sentado en una oficina de lujo. | G13: The positive deregulation case through intervention-spiral logic: each regulatory correction compounds the problem by distorting price signals, impairing economic calculation, reducing investment and growth. | H13: WEF Davos 2024 | I13: 2024-01-17 | J13: Davos · Speech
A14: 12 | B14: D1.1 | C14: Deregulation Benefits | D14: D1.1 — State Intervention & Governance | E14: Deregulation Benefits | F14: Such intervention achieves nothing but new distortions within the price system — such as is the case in Europe, which kills economic growth. | G14: The positive deregulation argument paired with the Europe case: removing climate regulation restores economic calculation, investment, and growth. | H14: WEF Davos 2025 | I14: 2025-01-23 | J14: Davos · Speech
... A70: 68 | B70: IND | C70: Temporal Appropriation | D70: Inductive | E70: Temporal Appropriation | F70: Incendian el futuro para mantener caliente el presente... la Argentina decidió en su momento apartarse de este proceso porque veíamos en esta agenda un mal gasto de recursos escasos. | G70: The speech's entire architecture co-opts sustainability's moral-temporal vocabulary and directs it against the 2030 Agenda. The 2030 Agenda framed as sacrificing the future for present bureaucratic comfort. Clearest and most fully developed Temporal_Appropriation instance in the corpus. | H70: UN General Assembly 80th | I70: 2025-09-24 | J70: New York · Speech

Sheet Freq — By Dimension
A1: Code Frequency by Dimension × Speech — values update automatically from 'Coded Passages'
A2: Dimension | B2: Dimension (Full) | C2: Debate Presidencial 2023 | D2: WEF Davos 2024 | E2: UN General Assembly 79th | F2: WEF Davos 2025 | G2: UN General Assembly 80th | H2: WEF Davos 2026 | I2: TOTAL | K2: Dimension | L2: Total
A3: D1.1 | B3: D1.1 — State Intervention & Governance | C3: =COUNTIFS('Coded Passages'!$B:$B,$A3,'Coded Passages'!$H:$H,C$2) -> 1 | D3: =COUNTIFS('Coded Passages'!$B:$B,$A3,'Coded Passages'!$H:$H,D$2) -> 10 | E3: =COUNTIFS('Coded Passages'!$B:$B,$A3,'Coded Passages'!$H:$H,E$2) -> 5 | F3: =COUNTIFS('Coded Passages'!$B:$B,$A3,'Coded Passages'!$H:$H,F$2) -> 7 | G3: =COUNTIFS('Coded Passages'!$B:$B,$A3,'Coded Passages'!$H:$H,G$2) -> 5 | H3: =COUNTIFS('Coded Passages'!$B:$B,$A3,'Coded Passages'!$H:$H,H$2) -> 5 | I3: =SUM(C3:H3) -> 33 | K3: D1.1 | L3: =I3 -> 33
A4: D1.2 | B4: D1.2 — Public Science & Expertise | C4: =COUNTIFS('Coded Passages'!$B:$B,$A4,'Coded Passages'!$H:$H,C$2) -> 2 | D4: =COUNTIFS('Coded Passages'!$B:$B,$A4,'Coded Passages'!$H:$H,D$2) -> 3 | E4: =COUNTIFS('Coded Passages'!$B:$B,$A4,'Coded Passages'!$H:$H,E$2) -> 1 | F4: =COUNTIFS('Coded Passages'!$B:$B,$A4,'Coded Passages'!$H:$H,F$2) -> 4 | G4: =COUNTIFS('Coded Passages'!$B:$B,$A4,'Coded Passages'!$H:$H,G$2) -> 2 | H4: =COUNTIFS('Coded Passages'!$B:$B,$A4,'Coded Passages'!$H:$H,H$2) -> 0 | I4: =SUM(C4:H4) -> 12 | K4: D1.2 | L4: =I4 -> 12
A5: D1.3 | B5: D1.3 — Cultural Backlash | C5: =COUNTIFS('Coded Passages'!$B:$B,$A5,'Coded Passages'!$H:$H,C$2) -> 0 | D5: =COUNTIFS('Coded Passages'!$B:$B,$A5,'Coded Passages'!$H:$H,D$2) -> 3 | E5: =COUNTIFS('Coded Passages'!$B:$B,$A5,'Coded Passages'!$H:$H,E$2) -> 2 | F5: =COUNTIFS('Coded Passages'!$B:$B,$A5,'Coded Passages'!$H:$H,F$2) -> 6 | G5: =COUNTIFS('Coded Passages'!$B:$B,$A5,'Coded Passages'!$H:$H,G$2) -> 1 | H5: =COUNTIFS('Coded Passages'!$B:$B,$A5,'Coded Passages'!$H:$H,H$2) -> 2 | I5: =SUM(C5:H5) -> 14 | K5: D1.3 | L5: =I5 -> 14
A6: D2.2 | B6: D2.2 — Institutional Downgrading | C6: =COUNTIFS('Coded Passages'!$B:$B,$A6,'Coded Passages'!$H:$H,C$2) -> 0 | D6: =COUNTIFS('Coded Passages'!$B:$B,$A6,'Coded Passages'!$H:$H,D$2) -> 0 | E6: =COUNTIFS('Coded Passages'!$B:$B,$A6,'Coded Passages'!$H:$H,E$2) -> 0 | F6: =COUNTIFS('Coded Passages'!$B:$B,$A6,'Coded Passages'!$H:$H,F$2) -> 0 | G6: =COUNTIFS('Coded Passages'!$B:$B,$A6,'Coded Passages'!$H:$H,G$2) -> 1 | H6: =COUNTIFS('Coded Passages'!$B:$B,$A6,'Coded Passages'!$H:$H,H$2) -> 0 | I6: =SUM(C6:H6) -> 1 | K6: D2.2 | L6: =I6 -> 1
A7: D2.3 | B7: D2.3 — Policy Dismantling | C7: =COUNTIFS('Coded Passages'!$B:$B,$A7,'Coded Passages'!$H:$H,C$2) -> 0 | D7: =COUNTIFS('Coded Passages'!$B:$B,$A7,'Coded Passages'!$H:$H,D$2) -> 0 | E7: =COUNTIFS('Coded Passages'!$B:$B,$A7,'Coded Passages'!$H:$H,E$2) -> 1 | F7: =COUNTIFS('Coded Passages'!$B:$B,$A7,'Coded Passages'!$H:$H,F$2) -> 1 | G7: =COUNTIFS('Coded Passages'!$B:$B,$A7,'Coded Passages'!$H:$H,G$2) -> 2 | H7: =COUNTIFS('Coded Passages'!$B:$B,$A7,'Coded Passages'!$H:$H,H$2) -> 0 | I7: =SUM(C7:H7) -> 4 | K7: D2.3 | L7: =I7 -> 4
A8: IND | B8: Inductive | C8: =COUNTIFS('Coded Passages'!$B:$B,$A8,'Coded Passages'!$H:$H,C$2) -> 1 | D8: =COUNTIFS('Coded Passages'!$B:$B,$A8,'Coded Passages'!$H:$H,D$2) -> 1 | E8: =COUNTIFS('Coded Passages'!$B:$B,$A8,'Coded Passages'!$H:$H,E$2) -> 0 | F8: =COUNTIFS('Coded Passages'!$B:$B,$A8,'Coded Passages'!$H:$H,F$2) -> 1 | G8: =COUNTIFS('Coded Passages'!$B:$B,$A8,'Coded Passages'!$H:$H,G$2) -> 1 | H8: =COUNTIFS('Coded Passages'!$B:$B,$A8,'Coded Passages'!$H:$H,H$2) -> 0 | I8: =SUM(C8:H8) -> 4 | K8: IND | L8: =I8 -> 4
A9: TOTAL | B9: All Dimensions | C9: =SUM(C3:C8) -> 4 | D9: =SUM(D3:D8) -> 17 | E9: =SUM(E3:E8) -> 9 | F9: =SUM(F3:F8) -> 19 | G9: =SUM(G3:G8) -> 12 | H9: =SUM(H3:H8) -> 7 | I9: =SUM(I3:I8) -> 68

Sheet Freq — By Sub-code
A1: Code Frequency by Sub-code × Speech — values update automatically from 'Coded Passages'
A2: Dim | B2: Sub-code | C2: Debate Presidencial 2023 | D2: WEF Davos 2024 | E2: UN General Assembly 79th | F2: WEF Davos 2025 | G2: UN General Assembly 80th | H2: WEF Davos 2026 | I2: TOTAL | K2: Sub-code | L2: Total
A3: D1.1 | B3: Anti-Casta (Elite Frame) | C3: =COUNTIFS('Coded Passages'!$B:$B,$A3,'Coded Passages'!$C:$C,$B3,'Coded Passages'!$H:$H,C$2) -> 0 | D3: =COUNTIFS('Coded Passages'!$B:$B,$A3,'Coded Passages'!$C:$C,$B3,'Coded Passages'!$H:$H,D$2) -> 1 | E3: =COUNTIFS('Coded Passages'!$B:$B,$A3,'Coded Passages'!$C:$C,$B3,'Coded Passages'!$H:$H,E$2) -> 0 | F3: =COUNTIFS('Coded Passages'!$B:$B,$A3,'Coded Passages'!$C:$C,$B3,'Coded Passages'!$H:$H,F$2) -> 0 | G3: =COUNTIFS('Coded Passages'!$B:$B,$A3,'Coded Passages'!$C:$C,$B3,'Coded Passages'!$H:$H,G$2) -> 0 | H3: =COUNTIFS('Coded Passages'!$B:$B,$A3,'Coded Passages'!$C:$C,$B3,'Coded Passages'!$H:$H,H$2) -> 0 | I3: =SUM(C3:H3) -> 1 | K3: D1.1·Anti-Casta (Elite Fr | L3: =I3 -> 1
A4: D1.1 | B4: Anti-State / Anti-Bureaucratic | C4: =COUNTIFS('Coded Passages'!$B:$B,$A4,'Coded Passages'!$C:$C,$B4,'Coded Passages'!$H:$H,C$2) -> 0 | D4: =COUNTIFS('Coded Passages'!$B:$B,$A4,'Coded Passages'!$C:$C,$B4,'Coded Passages'!$H:$H,D$2) -> 1 | E4: =COUNTIFS('Coded Passages'!$B:$B,$A4,'Coded Passages'!$C:$C,$B4,'Coded Passages'!$H:$H,E$2) -> 0 | F4: =COUNTIFS('Coded Passages'!$B:$B,$A4,'Coded Passages'!$C:$C,$B4,'Coded Passages'!$H:$H,F$2) -> 0 | G4: =COUNTIFS('Coded Passages'!$B:$B,$A4,'Coded Passages'!$C:$C,$B4,'Coded Passages'!$H:$H,G$2) -> 1 | H4: =COUNTIFS('Coded Passages'!$B:$B,$A4,'Coded Passages'!$C:$C,$B4,'Coded Passages'!$H:$H,H$2) -> 0 | I4: =SUM(C4:H4) -> 2 | K4: D1.1·Anti-State / Anti-Bu | L4: =I4 -> 2
A5: D1.1 | B5: Delegitimization of Regulation | C5: =COUNTIFS('Coded Passages'!$B:$B,$A5,'Coded Passages'!$C:$C,$B5,'Coded Passages'!$H:$H,C$2) -> 0 | D5: =COUNTIFS('Coded Passages'!$B:$B,$A5,'Coded Passages'!$C:$C,$B5,'Coded Passages'!$H:$H,D$2) -> 3 | E5: =COUNTIFS('Coded Passages'!$B:$B,$A5,'Coded Passages'!$C:$C,$B5,'Coded Passages'!$H:$H,E$2) -> 0 | F5: =COUNTIFS('Coded Passages'!$B:$B,$A5,'Coded Passages'!$C:$C,$B5,'Coded Passages'!$H:$H,F$2) -> 1 | G5: =COUNTIFS('Coded Passages'!$B:$B,$A5,'Coded Passages'!$C:$C,$B5,'Coded Passages'!$H:$H,G$2) -> 0 | H5: =COUNTIFS('Coded Passages'!$B:$B,$A5,'Coded Passages'!$C:$C,$B5,'Coded Passages'!$H:$H,H$2) -> 2 | I5: =SUM(C5:H5) -> 6 | K5: D1.1·Delegitimization of | L5: =I5 -> 6
A6: D1.1 | B6: Deregulation Benefits | C6: =COUNTIFS('Coded Passages'!$B:$B,$A6,'Coded Passages'!$C:$C,$B6,'Coded Passages'!$H:$H,C$2) -> 0 | D6: =COUNTIFS('Coded Passages'!$B:$B,$A6,'Coded Passages'!$C:$C,$B6,'Coded Passages'!$H:$H,D$2) -> 1 | E6: =COUNTIFS('Coded Passages'!$B:$B,$A6,'Coded Passages'!$C:$C,$B6,'Coded Passages'!$H:$H,E$2) -> 0 | F6: =COUNTIFS('Coded Passages'!$B:$B,$A6,'Coded Passages'!$C:$C,$B6,'Coded Passages'!$H:$H,F$2) -> 1 | G6: =COUNTIFS('Coded Passages'!$B:$B,$A6,'Coded Passages'!$C:$C,$B6,'Coded Passages'!$H:$H,G$2) -> 1 | H6: =COUNTIFS('Coded Passages'!$B:$B,$A6,'Coded Passages'!$C:$C,$B6,'Coded Passages'!$H:$H,H$2) -> 2 | I6: =SUM(C6:H6) -> 5 | K6: D1.1·Deregulation Benefit | L6: =I6 -> 5
A7: D1.1 | B7: Market Primacy | C7: =COUNTIFS('Coded Passages'!$B:$B,$A7,'Coded Passages'!$C:$C,$B7,'Coded Passages'!$H:$H,C$2) -> 0 | D7: =COUNTIFS('Coded Passages'!$B:$B,$A7,'Coded Passages'!$C:$C,$B7,'Coded Passages'!$H:$H,D$2) -> 3 | E7: =COUNTIFS('Coded Passages'!$B:$B,$A7,'Coded Passages'!$C:$C,$B7,'Coded Passages'!$H:$H,E$2) -> 0 | F7: =COUNTIFS('Coded Passages'!$B:$B,$A7,'Coded Passages'!$C:$C,$B7,'Coded Passages'!$H:$H,F$2) -> 1 | G7: =COUNTIFS('Coded Passages'!$B:$B,$A7,'Coded Passages'!$C:$C,$B7,'Coded Passages'!$H:$H,G$2) -> 0 | H7: =COUNTIFS('Coded Passages'!$B:$B,$A7,'Coded Passages'!$C:$C,$B7,'Coded Passages'!$H:$H,H$2) -> 1 | I7: =SUM(C7:H7) -> 5 | K7: D1.1·Market Primacy | L7: =I7 -> 5
A8: D1.1 | B8: Rejection of Multilateral Governance | C8: =COUNTIFS('Coded Passages'!$B:$B,$A8,'Coded Passages'!$C:$C,$B8,'Coded Passages'!$H:$H,C$2) -> 0 | D8: =COUNTIFS('Coded Passages'!$B:$B,$A8,'Coded Passages'!$C:$C,$B8,'Coded Passages'!$H:$H,D$2) -> 1 | E8: =COUNTIFS('Coded Passages'!$B:$B,$A8,'Coded Passages'!$C:$C,$B8,'Coded Passages'!$H:$H,E$2) -> 3 | F8: =COUNTIFS('Coded Passages'!$B:$B,$A8,'Coded Passages'!$C:$C,$B8,'Coded Passages'!$H:$H,F$2) -> 3 | G8: =COUNTIFS('Coded Passages'!$B:$B,$A8,'Coded Passages'!$C:$C,$B8,'Coded Passages'!$H:$H,G$2) -> 2 | H8: =COUNTIFS('Coded Passages'!$B:$B,$A8,'Coded Passages'!$C:$C,$B8,'Coded Passages'!$H:$H,H$2) -> 0 | I8: =SUM(C8:H8) -> 9 | K8: D1.1·Rejection of Multila | L8: =I8 -> 9
A9: D1.1 | B9: Sustainability as Ideological or Harmful | C9: =COUNTIFS('Coded Passages'!$B:$B,$A9,'Coded Passages'!$C:$C,$B9,'Coded Passages'!$H:$H,C$2) -> 1 | D9: =COUNTIFS('Coded Passages'!$B:$B,$A9,'Coded Passages'!$C:$C,$B9,'Coded Passages'!$H:$H,D$2) -> 0 | E9: =COUNTIFS('Coded Passages'!$B:$B,$A9,'Coded Passages'!$C:$C,$B9,'Coded Passages'!$H:$H,E$2) -> 2 | F9: =COUNTIFS('Coded Passages'!$B:$B,$A9,'Coded Passages'!$C:$C,$B9,'Coded Passages'!$H:$H,F$2) -> 1 | G9: =COUNTIFS('Coded Passages'!$B:$B,$A9,'Coded Passages'!$C:$C,$B9,'Coded Passages'!$H:$H,G$2) -> 1 | H9: =COUNTIFS('Coded Passages'!$B:$B,$A9,'Coded Passages'!$C:$C,$B9,'Coded Passages'!$H:$H,H$2) -> 0 | I9: =SUM(C9:H9) -> 5 | K9: D1.1·Sustainability as Id | L9: =I9 -> 5
A10: D1.2 | B10: Attack on Experts & Technocrats | C10: =COUNTIFS('Coded Passages'!$B:$B,$A10,'Coded Passages'!$C:$C,$B10,'Coded Passages'!$H:$H,C$2) -> 1 | D10: =COUNTIFS('Coded Passages'!$B:$B,$A10,'Coded Passages'!$C:$C,$B10,'Coded Passages'!$H:$H,D$2) -> 1 | E10: =COUNTIFS('Coded Passages'!$B:$B,$A10,'Coded Passages'!$C:$C,$B10,'Coded Passages'!$H:$H,E$2) -> 1 | F10: =COUNTIFS('Coded Passages'!$B:$B,$A10,'Coded Passages'!$C:$C,$B10,'Coded Passages'!$H:$H,F$2) -> 0 | G10: =COUNTIFS('Coded Passages'!$B:$B,$A10,'Coded Passages'!$C:$C,$B10,'Coded Passages'!$H:$H,G$2) -> 2 | H10: =COUNTIFS('Coded Passages'!$B:$B,$A10,'Coded Passages'!$C:$C,$B10,'Coded Passages'!$H:$H,H$2) -> 0 | I10: =SUM(C10:H10) -> 5 | K10: D1.2·Attack on Experts & | L10: =I10 -> 5
A11: D1.2 | B11: Attack on Universities | C11: =COUNTIFS('Coded Passages'!$B:$B,$A11,'Coded Passages'!$C:$C,$B11,'Coded Passages'!$H:$H,C$2) -> 0 | D11: =COUNTIFS('Coded Passages'!$B:$B,$A11,'Coded Passages'!$C:$C,$B11,'Coded Passages'!$H:$H,D$2) -> 0 | E11: =COUNTIFS('Coded Passages'!$B:$B,$A11,'Coded Passages'!$C:$C,$B11,'Coded Passages'!$H:$H,E$2) -> 0 | F11: =COUNTIFS('Coded Passages'!$B:$B,$A11,'Coded Passages'!$C:$C,$B11,'Coded Passages'!$H:$H,F$2) -> 1 | G11: =COUNTIFS('Coded Passages'!$B:$B,$A11,'Coded Passages'!$C:$C,$B11,'Coded Passages'!$H:$H,G$2) -> 0 | H11: =COUNTIFS('Coded Passages'!$B:$B,$A11,'Coded Passages'!$C:$C,$B11,'Coded Passages'!$H:$H,H$2) -> 0 | I11: =SUM(C11:H11) -> 1 | K11: D1.2·Attack on Universiti | L11: =I11 -> 1
A12: D1.2 | B12: Climate Skepticism or Dismissal | C12: =COUNTIFS('Coded Passages'!$B:$B,$A12,'Coded Passages'!$C:$C,$B12,'Coded Passages'!$H:$H,C$2) -> 1 | D12: =COUNTIFS('Coded Passages'!$B:$B,$A12,'Coded Passages'!$C:$C,$B12,'Coded Passages'!$H:$H,D$2) -> 0 | E12: =COUNTIFS('Coded Passages'!$B:$B,$A12,'Coded Passages'!$C:$C,$B12,'Coded Passages'!$H:$H,E$2) -> 0 | F12: =COUNTIFS('Coded Passages'!$B:$B,$A12,'Coded Passages'!$C:$C,$B12,'Coded Passages'!$H:$H,F$2) -> 1 | G12: =COUNTIFS('Coded Passages'!$B:$B,$A12,'Coded Passages'!$C:$C,$B12,'Coded Passages'!$H:$H,G$2) -> 0 | H12: =COUNTIFS('Coded Passages'!$B:$B,$A12,'Coded Passages'!$C:$C,$B12,'Coded Passages'!$H:$H,H$2) -> 0 | I12: =SUM(C12:H12) -> 2 | K12: D1.2·Climate Skepticism o | L12: =I12 -> 2
A13: D1.2 | B13: Pseudo-Science / Ideological Science | C13: =COUNTIFS('Coded Passages'!$B:$B,$A13,'Coded Passages'!$C:$C,$B13,'Coded Passages'!$H:$H,C$2) -> 0 | D13: =COUNTIFS('Coded Passages'!$B:$B,$A13,'Coded Passages'!$C:$C,$B13,'Coded Passages'!$H:$H,D$2) -> 2 | E13: =COUNTIFS('Coded Passages'!$B:$B,$A13,'Coded Passages'!$C:$C,$B13,'Coded Passages'!$H:$H,E$2) -> 0 | F13: =COUNTIFS('Coded Passages'!$B:$B,$A13,'Coded Passages'!$C:$C,$B13,'Coded Passages'!$H:$H,F$2) -> 1 | G13: =COUNTIFS('Coded Passages'!$B:$B,$A13,'Coded Passages'!$C:$C,$B13,'Coded Passages'!$H:$H,G$2) -> 0 | H13: =COUNTIFS('Coded Passages'!$B:$B,$A13,'Coded Passages'!$C:$C,$B13,'Coded Passages'!$H:$H,H$2) -> 0 | I13: =SUM(C13:H13) -> 3 | K13: D1.2·Pseudo-Science / Ide | L13: =I13 -> 3
A14: D1.2 | B14: Rejection of Expert Mediation | C14: =COUNTIFS('Coded Passages'!$B:$B,$A14,'Coded Passages'!$C:$C,$B14,'Coded Passages'!$H:$H,C$2) -> 0 | D14: =COUNTIFS('Coded Passages'!$B:$B,$A14,'Coded Passages'!$C:$C,$B14,'Coded Passages'!$H:$H,D$2) -> 0 | E14: =COUNTIFS('Coded Passages'!$B:$B,$A14,'Coded Passages'!$C:$C,$B14,'Coded Passages'!$H:$H,E$2) -> 0 | F14: =COUNTIFS('Coded Passages'!$B:$B,$A14,'Coded Passages'!$C:$C,$B14,'Coded Passages'!$H:$H,F$2) -> 1 | G14: =COUNTIFS('Coded Passages'!$B:$B,$A14,'Coded Passages'!$C:$C,$B14,'Coded Passages'!$H:$H,G$2) -> 0 | H14: =COUNTIFS('Coded Passages'!$B:$B,$A14,'Coded Passages'!$C:$C,$B14,'Coded Passages'!$H:$H,H$2) -> 0 | I14: =SUM(C14:H14) -> 1 | K14: D1.2·Rejection of Expert | L14: =I14 -> 1
... A22: IND | B22: Temporal Appropriation | C22: =COUNTIFS('Coded Passages'!$B:$B,$A22,'Coded Passages'!$C:$C,$B22,'Coded Passages'!$H:$H,C$2) -> 0 | D22: =COUNTIFS('Coded Passages'!$B:$B,$A22,'Coded Passages'!$C:$C,$B22,'Coded Passages'!$H:$H,D$2) -> 0 | E22: =COUNTIFS('Coded Passages'!$B:$B,$A22,'Coded Passages'!$C:$C,$B22,'Coded Passages'!$H:$H,E$2) -> 0 | F22: =COUNTIFS('Coded Passages'!$B:$B,$A22,'Coded Passages'!$C:$C,$B22,'Coded Passages'!$H:$H,F$2) -> 0 | G22: =COUNTIFS('Coded Passages'!$B:$B,$A22,'Coded Passages'!$C:$C,$B22,'Coded Passages'!$H:$H,G$2) -> 1 | H22: =COUNTIFS('Coded Passages'!$B:$B,$A22,'Coded Passages'!$C:$C,$B22,'Coded Passages'!$H:$H,H$2) -> 0 | I22: =SUM(C22:H22) -> 1 | K22: IND·Temporal Appropriati | L22: =I22 -> 1
A23: TOTAL | B23: All Sub-codes | C23: =SUM(C3:C22) -> 4 | D23: =SUM(D3:D22) -> 17 | E23: =SUM(E3:E22) -> 9 | F23: =SUM(F3:F22) -> 19 | G23: =SUM(G3:G22) -> 12 | H23: =SUM(H3:H22) -> 7 | I23: =SUM(I3:I22) -> 68

Sheet Speech Overview
A1: Speech-Level Overview — D1 / D2 / Inductive counts update automatically from 'Coded Passages'
A2: Speech | B2: Date | C2: Venue | D2: Type | E2: D1 Codes | F2: D2 Codes | G2: Inductive | H2: Total | I2: D2 Present?
A3: Debate Presidencial 2023 | B3: 2023-10-08 | C3: Buenos Aires | D3: Debate | E3: =COUNTIFS('Coded Passages'!$H:$H,$A3,'Coded Passages'!$B:$B,"D1*") -> 3 | F3: =COUNTIFS('Coded Passages'!$H:$H,$A3,'Coded Passages'!$B:$B,"D2*") -> 0 | G3: =COUNTIFS('Coded Passages'!$H:$H,$A3,'Coded Passages'!$B:$B,"IND") -> 1 | H3: =E3+F3+G3 -> 4 | I3: =IF(F3>0,"✓ YES","✗ No") -> ✗ No
A4: WEF Davos 2024 | B4: 2024-01-17 | C4: Davos | D4: Speech | E4: =COUNTIFS('Coded Passages'!$H:$H,$A4,'Coded Passages'!$B:$B,"D1*") -> 16 | F4: =COUNTIFS('Coded Passages'!$H:$H,$A4,'Coded Passages'!$B:$B,"D2*") -> 0 | G4: =COUNTIFS('Coded Passages'!$H:$H,$A4,'Coded Passages'!$B:$B,"IND") -> 1 | H4: =E4+F4+G4 -> 17 | I4: =IF(F4>0,"✓ YES","✗ No") -> ✗ No
A5: UN General Assembly 79th | B5: 2024-09-24 | C5: New York | D5: Speech | E5: =COUNTIFS('Coded Passages'!$H:$H,$A5,'Coded Passages'!$B:$B,"D1*") -> 8 | F5: =COUNTIFS('Coded Passages'!$H:$H,$A5,'Coded Passages'!$B:$B,"D2*") -> 1 | G5: =COUNTIFS('Coded Passages'!$H:$H,$A5,'Coded Passages'!$B:$B,"IND") -> 0 | H5: =E5+F5+G5 -> 9 | I5: =IF(F5>0,"✓ YES","✗ No") -> ✓ YES
A6: WEF Davos 2025 | B6: 2025-01-23 | C6: Davos | D6: Speech | E6: =COUNTIFS('Coded Passages'!$H:$H,$A6,'Coded Passages'!$B:$B,"D1*") -> 17 | F6: =COUNTIFS('Coded Passages'!$H:$H,$A6,'Coded Passages'!$B:$B,"D2*") -> 1 | G6: =COUNTIFS('Coded Passages'!$H:$H,$A6,'Coded Passages'!$B:$B,"IND") -> 1 | H6: =E6+F6+G6 -> 19 | I6: =IF(F6>0,"✓ YES","✗ No") -> ✓ YES
A7: UN General Assembly 80th | B7: 2025-09-24 | C7: New York | D7: Speech | E7: =COUNTIFS('Coded Passages'!$H:$H,$A7,'Coded Passages'!$B:$B,"D1*") -> 8 | F7: =COUNTIFS('Coded Passages'!$H:$H,$A7,'Coded Passages'!$B:$B,"D2*") -> 3 | G7: =COUNTIFS('Coded Passages'!$H:$H,$A7,'Coded Passages'!$B:$B,"IND") -> 1 | H7: =E7+F7+G7 -> 12 | I7: =IF(F7>0,"✓ YES","✗ No") -> ✓ YES
A8: WEF Davos 2026 | B8: 2026-01-22 | C8: Davos | D8: Speech | E8: =COUNTIFS('Coded Passages'!$H:$H,$A8,'Coded Passages'!$B:$B,"D1*") -> 7 | F8: =COUNTIFS('Coded Passages'!$H:$H,$A8,'Coded Passages'!$B:$B,"D2*") -> 0 | G8: =COUNTIFS('Coded Passages'!$H:$H,$A8,'Coded Passages'!$B:$B,"IND") -> 0 | H8: =E8+F8+G8 -> 7 | I8: =IF(F8>0,"✓ YES","✗ No") -> ✗ No
A9: TOTAL | E9: =SUM(E3:E8) -> 59 | F9: =SUM(F3:F8) -> 5 | G9: =SUM(G3:G8) -> 4 | H9: =SUM(H3:H8) -> 68
