Workbook

Sheet Coded Passages
A1: Milei Climate Narratives — v3 Coded Passages · Data source for all summary sheets
A2: # | B2: Dimension | C2: Sub-dimension | D2: Dimension (Full) | E2: Sub-code (Full) | F2: Quoted Passage | G2: Analytical Memo | H2: Speech | I2: Date | J2: Venue / Type
A3: 1 | B3: D1.2 | C3: Climate Skepticism or Dismissal | D3: D1.2 — Public Science & Expertise | E3: Climate Skepticism or Dismissal | F3: [MILEI — Respuesta]: A ver primero no mienta. Yo no niego el cambio climático. Lo que yo digo es que existe en la historia de la tierra un ciclo de temperaturas, es decir hay un comportamiento cíclico y este es el quinto punto del ciclo — donde la diferencia con los cuatro anteriores es que antes no estaba el ser humano. Por lo tanto todas esas políticas que culpan al ser humano del cambio climático son falsas y lo único que buscan es recaudar fondos para financiar vagos socialistas que escriben papers de cuarta. | G3: Milei performs the disclaimer-then-dismiss move: "I don't deny climate change" is immediately followed by the natural-cycles attribution, which reproduces effective denial while maintaining rhetorical deniability. The key claim — "all those policies that blame humans for climate change are false" — is a direct dismissal of the scientific basis for climate regulation, delivered as a logical conclusion from the paleoclimatic premise. This is the most compressed instance of Climate_Skepticism_or_Dismissal in the corpus: denial of anthropogenic attribution without denial of the climate phenomenon itself. | H3: Debate Presidencial 2023 | I3: 2023-10-08 | J3: Buenos Aires · Debate
A4: 2 | B4: D1.1 | C4: Sustainability as Ideological or Harmful | D4: D1.1 — State Intervention & Governance | E4: Sustainability as Ideological or Harmful | F4: [MILEI — Respuesta]: A ver primero no mienta. Yo no niego el cambio climático. Lo que yo digo es que existe en la historia de la tierra un ciclo de temperaturas, es decir hay un comportamiento cíclico y este es el quinto punto del ciclo — donde la diferencia con los cuatro anteriores es que antes no estaba el ser humano. Por lo tanto todas esas políticas que culpan al ser humano del cambio climático son falsas y lo único que buscan es recaudar fondos para financiar vagos socialistas que escriben papers de cuarta. | G4: "Recaudar fondos para financiar vagos socialistas que escriben papers de cuarta" reframes climate policy as a rent-extraction mechanism for a parasitic academic class. The claim is not that climate policy is merely wrong — it is that climate policy exists as an institutional vehicle for redistributing resources to ideologically motivated, low-quality scholarship. This is Sustainability_as_Ideological_or_Harmful at its most direct: the policy's real function is material redistribution under ideological cover, not environmental protection. | H4: Debate Presidencial 2023 | I4: 2023-10-08 | J4: Buenos Aires · Debate
A5: 3 | B5: D1.2 | C5: Attack on Experts & Technocrats | D5: D1.2 — Public Science & Expertise | E5: Attack on Experts & Technocrats | F5: [MILEI — Respuesta]: A ver primero no mienta. Yo no niego el cambio climático. Lo que yo digo es que existe en la historia de la tierra un ciclo de temperaturas, es decir hay un comportamiento cíclico y este es el quinto punto del ciclo — donde la diferencia con los cuatro anteriores es que antes no estaba el ser humano. Por lo tanto todas esas políticas que culpan al ser humano del cambio climático son falsas y lo único que buscan es recaudar fondos para financiar vagos socialistas que escriben papers de cuarta. | G5: "Vagos socialistas que escriben papers de cuarta" is the rawest expert delegitimation in the corpus — climate scientists reduced to lazy, ideologically motivated rent-seekers producing worthless work. Unlike the more sophisticated epistemological arguments deployed at Davos (which grant good intentions while invalidating the theoretical framework), here the attack is purely ad hominem and institutional, characterizing climate science as professionally worthless rather than merely theoretically flawed. | H5: Debate Presidencial 2023 | I5: 2023-10-08 | J5: Buenos Aires · Debate
A6: 4 | B6: IND | C6: Reported Denial | D6: Inductive | E6: Reported Denial | F6: [BREGMAN — Réplica]: la destrucción del Planeta es una de las muestras más claras de la irracionalidad de este sistema capitalista... pero [Milei] defiende la libertad de las empresas para contaminar hasta los ríos y llegó a decir que el cambio climático es del socialismo. | G6: Bregman's reported-speech paraphrase ("llegó a decir que el cambio climático es del socialismo") functions as inter-discursive corroboration: a nationally televised opponent accurately summarizing a Milei position confirms the claim circulates publicly and is understood as politically legible. The paraphrase maps directly onto D1.3 > Neo_Marxism — framing climate change as caused by or synonymous with socialism. Not primary Milei discourse; coded here for contextual and confirmatory purposes only. | H6: Debate Presidencial 2023 | I6: 2023-10-08 | J6: Buenos Aires · Debate
A7: 5 | B7: D1.3 | C7: Civilizational Defense | D7: D1.3 — Cultural Backlash | E7: Civilizational Defense | F7: Buenas tardes, muchas gracias: hoy estoy acá para decirles que Occidente está en peligro, está en peligro porque aquellos, que supuestamente deben defender los valores de Occidente, se encuentran cooptados por una visión del mundo que – inexorablemente – conduce al socialismo, en consecuencia a la pobreza. Lamentablemente en las últimas décadas, motivados por algunos deseos bien pensantes de querer ayudar al prójimo y otros por el deseo de querer pertenecer a una casta privilegiada, los principales líderes del mundo occidental han abandonado el modelo de la libertad, por distintas versiones, de lo que llamamos colectivismo. | G7: The opening sentences establish the master civilizational frame for the entire speech: Western civilization is under existential threat from socialism, and the WEF audience itself is identified as part of a "casta privilegiada" complicit in that decline. This frame pre-loads every subsequent critique — including of environmental policy — with civilizational stakes. Climate governance emanating from the "cooptados" Western establishment is tainted by association with civilizational threat, making engagement with it a form of civilizational capitulation. | H7: WEF Davos 2024 | I7: 2024-01-17 | J7: Davos · Speech
A8: 6 | B8: D1.1 | C8: Anti-Casta (Elite Frame) | D8: D1.1 — State Intervention & Governance | E8: Anti-Casta (Elite Frame) | F8: Buenas tardes, muchas gracias: hoy estoy acá para decirles que Occidente está en peligro, está en peligro porque aquellos, que supuestamente deben defender los valores de Occidente, se encuentran cooptados por una visión del mundo que – inexorablemente – conduce al socialismo, en consecuencia a la pobreza. Lamentablemente en las últimas décadas, motivados por algunos deseos bien pensantes de querer ayudar al prójimo y otros por el deseo de querer pertenecer a una casta privilegiada, los principales líderes del mundo occidental han abandonado el modelo de la libertad, por distintas versiones, de lo que llamamos colectivismo. | G8: "Pertenecer a una casta privilegiada" extends Milei's domestic anti-elite frame to the global governance level, targeting the WEF audience itself. International climate institutions and their leaders are pre-emptively delegitimized as members of a global caste pursuing privilege rather than planetary welfare — the same logic used domestically against environmental ministries and CONICET is applied globally to IPCC, UNEP, and multilateral climate bodies. | H8: WEF Davos 2024 | I8: 2024-01-17 | J8: Davos · Speech
A9: 7 | B9: D1.1 | C9: Market Primacy | D9: D1.1 — State Intervention & Governance | E9: Market Primacy | F9: La conclusión es obvia: lejos de ser la causa de nuestros problemas, el capitalismo de libre empresa, como sistema económico, es la única herramienta que tenemos para terminar con el hambre, la pobreza y la indigencia, a lo largo y a lo ancho de todo el planeta. La evidencia empírica es incuestionable. | G9: The hockey-stick economic history culminates in the categorical Market_Primacy claim: free-enterprise capitalism is "the only tool" for ending poverty, and the conclusion is declared empirically self-evident. For sustainability governance, the structural implication is total: if markets are the only legitimate mechanism for solving the most fundamental collective problem (poverty), they are implicitly the only legitimate mechanism for environmental problems, displacing any basis for state-led climate regulation. | H9: WEF Davos 2024 | I9: 2024-01-17 | J9: Davos · Speech
A10: 8 | B10: IND | C10: Selective Empiricism | D10: Inductive | E10: Selective Empiricism | F10: La conclusión es obvia: lejos de ser la causa de nuestros problemas, el capitalismo de libre empresa, como sistema económico, es la única herramienta que tenemos para terminar con el hambre, la pobreza y la indigencia, a lo largo y a lo ancho de todo el planeta. La evidencia empírica es incuestionable. | G10: "La evidencia empírica es incuestionable" is the canonical Selective_Empiricism instance in the corpus: Milei claims unquestionable empirical authority for the pro-market historical narrative, but later in the same speech systematically dismisses opposing academic and institutional knowledge (including climate science) as ideologically captured. The move is to appropriate the prestige of empiricism for one side while denying it to the other — crowding out rather than refuting. | H10: WEF Davos 2024 | I10: 2024-01-17 | J10: Davos · Speech
A11: 9 | B11: D1.1 | C11: Market Primacy | D11: D1.1 — State Intervention & Governance | E11: Market Primacy | F11: El colectivismo - al inhibir estos procesos de descubrimiento y al dificultar la apropiación de lo descubierto - ata al emprendedor de las manos y le imposibilita producir mejores bienes y ofrecer mejores servicios a un mejor precio. ¿Cómo puede ser, entonces, que desde la academia, los organismos internacionales, la política y la teoría económica se demonice un sistema económico que no sólo ha sacado de la pobreza más extrema, al 90 por ciento de la población mundial? | G11: The Kirznerian market-as-discovery-process argument provides theoretical grounding: environmental outcomes, like economic ones, are best achieved through decentralized market discovery rather than state planning. "Academia, los organismos internacionales, la política y la teoría económica" — the four pillars of climate governance legitimacy — are grouped as an ideological bloc irrationally hostile to the proven market mechanism. | H11: WEF Davos 2024 | I11: 2024-01-17 | J11: Davos · Speech
A12: 10 | B12: D1.2 | C12: Attack on Experts & Technocrats | D12: D1.2 — Public Science & Expertise | E12: Attack on Experts & Technocrats | F12: El colectivismo - al inhibir estos procesos de descubrimiento y al dificultar la apropiación de lo descubierto - ata al emprendedor de las manos y le imposibilita producir mejores bienes y ofrecer mejores servicios a un mejor precio. ¿Cómo puede ser, entonces, que desde la academia, los organismos internacionales, la política y la teoría económica se demonice un sistema económico que no sólo ha sacado de la pobreza más extrema, al 90 por ciento de la población mundial? | G12: The entire authority apparatus — academic, international, political, theoretical — is presented as a unified bloc that "demonizes" capitalism. For sustainability governance: IPCC, UNEP, national science ministries, and environmental economics are all expressions of the same anti-capitalist ideological formation. This is a structural delegitimation of the expert class, not a dispute with specific scientific findings. | H12: WEF Davos 2024 | I12: 2024-01-17 | J12: Davos · Speech
A13: 11 | B13: D1.2 | C13: Pseudo-Science / Ideological Science | D13: D1.2 — Public Science & Expertise | E13: Pseudo-Science / Ideological Science | F13: El problema esencial de occidente hoy es que no sólo debemos enfrentarnos a quienes siguen bregando por el socialismo empobrecedor; sino también a nuestros propios líderes, pensadores y académicos que, amparados en un marco teórico equivocado, socavan los fundamentos del sistema que nos ha dado la mayor expansión de riqueza y prosperidad de nuestra historia. | G13: "Amparados en un marco teórico equivocado" frames the entire academic and expert community as epistemically compromised: their framework is wrong, and therefore their outputs — including climate science, environmental economics, and sustainability research — are systematically distorted. The concession of good intentions ("sin quererlo," as the next paragraph notes) makes this a structurally more powerful delegitimation than the debate's ad hominem: it invalidates conclusions while preserving a veneer of charity toward the actors. | H13: WEF Davos 2024 | I13: 2024-01-17 | J13: Davos · Speech
A14: 12 | B14: D1.1 | C14: Delegitimization of Regulation | D14: D1.1 — State Intervention & Governance | E14: Delegitimization of Regulation | F14: El marco teórico al que me refiero es el de la teoría económica neoclásica, que diseña un instrumental que, sin quererlo, termina siendo funcional a la intromisión del estado. El problema de los neoclásicos es que como el modelo del que se enamoraron no mapea contra la realidad, atribuyen el error a supuestos fallos del mercado en vez de revisar las premisas de su modelo. | G14: The attack on neoclassical economics demolishes the theoretical foundation of environmental regulation. Mainstream climate policy — carbon pricing, Pigouvian taxes, cap-and-trade — derives its justification from externality theory, precisely the "instrumental" Milei argues ends up serving state intrusion. By framing neoclassical economics as the theoretical Trojan horse through which socialism enters, he delegitimizes the entire economic-theoretical basis for climate regulation at the level of first principles. | H14: WEF Davos 2024 | I14: 2024-01-17 | J14: Davos · Speech
... A100: 98 | B100: IND | C100: Temporal Appropriation | D100: Inductive | E100: Temporal Appropriation | F100: La verdadera batalla de nuestro tiempo es cultural, filosófica y moral. Es elegir el sistema que sacó de la pobreza a millones. Es para dejar de ser una Nación inmadura, que dilapida el futuro para repartir beneficios en el presente; y convertirnos en una nación madura, que planifica las reglas de juego para que haya presente y futuro; y para que cada ciudadano pueda elegir libremente su propio destino. No que se lo quiera determinar un burócrata ignorante, fatalmente arrogante. Gobernar con responsabilidad es gobernar para los argentinos de hoy, pero también gobernar para los argentinos de mañana. | G100: The contrast between a "nación inmadura que dilapida el futuro para repartir beneficios en el presente" and a "nación madura que planifica las reglas de juego para que haya presente y futuro" inverts the sustainability discourse's intergenerational frame. Climate governance's core moral claim is that present consumption sacrifices the future; here, Milei appropriates that moral structure to argue that state redistribution (including sustainability programs) is what sacrifices the future, while market freedom is what "plans for both present and future." The inversion is structurally identical to the UN 2025 passage already coded as Temporal_Appropriation — confirming the category's recurrence across the corpus. | H100: Apertura Sesiones Ordinarias 2026 (144°) | I100: 2026-03-01 | J100: Buenos Aires · Speech

Sheet Freq — By Dimension
A1: Code Frequency by Dimension × Speech — values update automatically from 'Coded Passages'
A2: Dimension | B2: Dimension (Full) | C2: Debate Presidencial 2023 | D2: WEF Davos 2024 | E2: Apertura Sesiones Ordinarias 2024 (142°) | F2: UN General Assembly 79th | G2: WEF Davos 2025 | H2: Apertura Sesiones Ordinarias 2025 (143°) | I2: UN General Assembly 80th | J2: WEF Davos 2026 | K2: Apertura Sesiones Ordinarias 2026 (144°) | L2: TOTAL | N2: Dimension | O2: Total
A3: D1.1 | B3: =COUNTIFS('Coded Passages'!$B:$B,$A3,'Coded Passages'!$H:$H,B$2) | C3: =COUNTIFS('Coded Passages'!$B:$B,$A3,'Coded Passages'!$H:$H,C$2) | D3: =COUNTIFS('Coded Passages'!$B:$B,$A3,'Coded Passages'!$H:$H,D$2) | E3: =COUNTIFS('Coded Passages'!$B:$B,$A3,'Coded Passages'!$H:$H,E$2) | F3: =COUNTIFS('Coded Passages'!$B:$B,$A3,'Coded Passages'!$H:$H,F$2) | G3: =COUNTIFS('Coded Passages'!$B:$B,$A3,'Coded Passages'!$H:$H,G$2) | H3: =COUNTIFS('Coded Passages'!$B:$B,$A3,'Coded Passages'!$H:$H,H$2) | I3: =COUNTIFS('Coded Passages'!$B:$B,$A3,'Coded Passages'!$H:$H,I$2) | J3: =COUNTIFS('Coded Passages'!$B:$B,$A3,'Coded Passages'!$H:$H,J$2) | L3: =SUM(C3:K3) | N3: D1.1 | O3: =I3
A4: D1.2 | B4: =COUNTIFS('Coded Passages'!$B:$B,$A4,'Coded Passages'!$H:$H,B$2) | C4: =COUNTIFS('Coded Passages'!$B:$B,$A4,'Coded Passages'!$H:$H,C$2) | D4: =COUNTIFS('Coded Passages'!$B:$B,$A4,'Coded Passages'!$H:$H,D$2) | E4: =COUNTIFS('Coded Passages'!$B:$B,$A4,'Coded Passages'!$H:$H,E$2) | F4: =COUNTIFS('Coded Passages'!$B:$B,$A4,'Coded Passages'!$H:$H,F$2) | G4: =COUNTIFS('Coded Passages'!$B:$B,$A4,'Coded Passages'!$H:$H,G$2) | H4: =COUNTIFS('Coded Passages'!$B:$B,$A4,'Coded Passages'!$H:$H,H$2) | I4: =COUNTIFS('Coded Passages'!$B:$B,$A4,'Coded Passages'!$H:$H,I$2) | J4: =COUNTIFS('Coded Passages'!$B:$B,$A4,'Coded Passages'!$H:$H,J$2) | L4: =SUM(C4:K4) | N4: D1.2 | O4: =I4
A5: D1.3 | B5: =COUNTIFS('Coded Passages'!$B:$B,$A5,'Coded Passages'!$H:$H,B$2) | C5: =COUNTIFS('Coded Passages'!$B:$B,$A5,'Coded Passages'!$H:$H,C$2) | D5: =COUNTIFS('Coded Passages'!$B:$B,$A5,'Coded Passages'!$H:$H,D$2) | E5: =COUNTIFS('Coded Passages'!$B:$B,$A5,'Coded Passages'!$H:$H,E$2) | F5: =COUNTIFS('Coded Passages'!$B:$B,$A5,'Coded Passages'!$H:$H,F$2) | G5: =COUNTIFS('Coded Passages'!$B:$B,$A5,'Coded Passages'!$H:$H,G$2) | H5: =COUNTIFS('Coded Passages'!$B:$B,$A5,'Coded Passages'!$H:$H,H$2) | I5: =COUNTIFS('Coded Passages'!$B:$B,$A5,'Coded Passages'!$H:$H,I$2) | J5: =COUNTIFS('Coded Passages'!$B:$B,$A5,'Coded Passages'!$H:$H,J$2) | L5: =SUM(C5:K5) | N5: D1.3 | O5: =I5
A6: IND | B6: =COUNTIFS('Coded Passages'!$B:$B,$A6,'Coded Passages'!$H:$H,B$2) | C6: =COUNTIFS('Coded Passages'!$B:$B,$A6,'Coded Passages'!$H:$H,C$2) | D6: =COUNTIFS('Coded Passages'!$B:$B,$A6,'Coded Passages'!$H:$H,D$2) | E6: =COUNTIFS('Coded Passages'!$B:$B,$A6,'Coded Passages'!$H:$H,E$2) | F6: =COUNTIFS('Coded Passages'!$B:$B,$A6,'Coded Passages'!$H:$H,F$2) | G6: =COUNTIFS('Coded Passages'!$B:$B,$A6,'Coded Passages'!$H:$H,G$2) | H6: =COUNTIFS('Coded Passages'!$B:$B,$A6,'Coded Passages'!$H:$H,H$2) | I6: =COUNTIFS('Coded Passages'!$B:$B,$A6,'Coded Passages'!$H:$H,I$2) | J6: =COUNTIFS('Coded Passages'!$B:$B,$A6,'Coded Passages'!$H:$H,J$2) | L6: =SUM(C6:K6) | N6: IND | O6: =I6
A7: TOTAL | B7: All Dimensions | C7: =SUM(C3:C6) | D7: =SUM(D3:D6) | E7: =SUM(E3:E6) | F7: =SUM(F3:F6) | G7: =SUM(G3:G6) | H7: =SUM(H3:H6) | I7: =SUM(I3:I6) | J7: =SUM(J3:J6) | ... L7: =SUM(L3:L6)

Sheet Freq — By Sub-code
A1: Code Frequency by Sub-code × Speech — values update automatically from 'Coded Passages'
A2: Dim | B2: Sub-code | C2: Debate Presidencial 2023 | D2: WEF Davos 2024 | E2: Apertura Sesiones Ordinarias 2024 (142°) | F2: UN General Assembly 79th | G2: WEF Davos 2025 | H2: Apertura Sesiones Ordinarias 2025 (143°) | I2: UN General Assembly 80th | J2: WEF Davos 2026 | K2: Apertura Sesiones Ordinarias 2026 (144°) | L2: TOTAL | N2: Sub-code | O2: Total
A3: D1.1 | B3: =COUNTIFS('Coded Passages'!$B:$B,$A3,'Coded Passages'!$C:$C,$B3,'Coded Passages'!$H:$H,B$2) | C3: =COUNTIFS('Coded Passages'!$B:$B,$A3,'Coded Passages'!$C:$C,$B3,'Coded Passages'!$H:$H,C$2) | D3: =COUNTIFS('Coded Passages'!$B:$B,$A3,'Coded Passages'!$C:$C,$B3,'Coded Passages'!$H:$H,D$2) | E3: =COUNTIFS('Coded Passages'!$B:$B,$A3,'Coded Passages'!$C:$C,$B3,'Coded Passages'!$H:$H,E$2) | F3: =COUNTIFS('Coded Passages'!$B:$B,$A3,'Coded Passages'!$C:$C,$B3,'Coded Passages'!$H:$H,F$2) | G3: =COUNTIFS('Coded Passages'!$B:$B,$A3,'Coded Passages'!$C:$C,$B3,'Coded Passages'!$H:$H,G$2) | H3: =COUNTIFS('Coded Passages'!$B:$B,$A3,'Coded Passages'!$C:$C,$B3,'Coded Passages'!$H:$H,H$2) | I3: =COUNTIFS('Coded Passages'!$B:$B,$A3,'Coded Passages'!$C:$C,$B3,'Coded Passages'!$H:$H,I$2) | J3: =COUNTIFS('Coded Passages'!$B:$B,$A3,'Coded Passages'!$C:$C,$B3,'Coded Passages'!$H:$H,J$2) | L3: =SUM(C3:K3) | N3: D1.1·Sustainability as | O3: =I3
A4: D1.1 | B4: =COUNTIFS('Coded Passages'!$B:$B,$A4,'Coded Passages'!$C:$C,$B4,'Coded Passages'!$H:$H,B$2) | C4: =COUNTIFS('Coded Passages'!$B:$B,$A4,'Coded Passages'!$C:$C,$B4,'Coded Passages'!$H:$H,C$2) | D4: =COUNTIFS('Coded Passages'!$B:$B,$A4,'Coded Passages'!$C:$C,$B4,'Coded Passages'!$H:$H,D$2) | E4: =COUNTIFS('Coded Passages'!$B:$B,$A4,'Coded Passages'!$C:$C,$B4,'Coded Passages'!$H:$H,E$2) | F4: =COUNTIFS('Coded Passages'!$B:$B,$A4,'Coded Passages'!$C:$C,$B4,'Coded Passages'!$H:$H,F$2) | G4: =COUNTIFS('Coded Passages'!$B:$B,$A4,'Coded Passages'!$C:$C,$B4,'Coded Passages'!$H:$H,G$2) | H4: =COUNTIFS('Coded Passages'!$B:$B,$A4,'Coded Passages'!$C:$C,$B4,'Coded Passages'!$H:$H,H$2) | I4: =COUNTIFS('Coded Passages'!$B:$B,$A4,'Coded Passages'!$C:$C,$B4,'Coded Passages'!$H:$H,I$2) | J4: =COUNTIFS('Coded Passages'!$B:$B,$A4,'Coded Passages'!$C:$C,$B4,'Coded Passages'!$H:$H,J$2) | L4: =SUM(C4:K4) | N4: D1.1·Anti-Casta (Elite | O4: =I4
A5: D1.1 | B5: =COUNTIFS('Coded Passages'!$B:$B,$A5,'Coded Passages'!$C:$C,$B5,'Coded Passages'!$H:$H,B$2) | C5: =COUNTIFS('Coded Passages'!$B:$B,$A5,'Coded Passages'!$C:$C,$B5,'Coded Passages'!$H:$H,C$2) | D5: =COUNTIFS('Coded Passages'!$B:$B,$A5,'Coded Passages'!$C:$C,$B5,'Coded Passages'!$H:$H,D$2) | E5: =COUNTIFS('Coded Passages'!$B:$B,$A5,'Coded Passages'!$C:$C,$B5,'Coded Passages'!$H:$H,E$2) | F5: =COUNTIFS('Coded Passages'!$B:$B,$A5,'Coded Passages'!$C:$C,$B5,'Coded Passages'!$H:$H,F$2) | G5: =COUNTIFS('Coded Passages'!$B:$B,$A5,'Coded Passages'!$C:$C,$B5,'Coded Passages'!$H:$H,G$2) | H5: =COUNTIFS('Coded Passages'!$B:$B,$A5,'Coded Passages'!$C:$C,$B5,'Coded Passages'!$H:$H,H$2) | I5: =COUNTIFS('Coded Passages'!$B:$B,$A5,'Coded Passages'!$C:$C,$B5,'Coded Passages'!$H:$H,I$2) | J5: =COUNTIFS('Coded Passages'!$B:$B,$A5,'Coded Passages'!$C:$C,$B5,'Coded Passages'!$H:$H,J$2) | L5: =SUM(C5:K5) | N5: D1.1·Market Primacy | O5: =I5
A6: D1.1 | B6: =COUNTIFS('Coded Passages'!$B:$B,$A6,'Coded Passages'!$C:$C,$B6,'Coded Passages'!$H:$H,B$2) | C6: =COUNTIFS('Coded Passages'!$B:$B,$A6,'Coded Passages'!$C:$C,$B6,'Coded Passages'!$H:$H,C$2) | D6: =COUNTIFS('Coded Passages'!$B:$B,$A6,'Coded Passages'!$C:$C,$B6,'Coded Passages'!$H:$H,D$2) | E6: =COUNTIFS('Coded Passages'!$B:$B,$A6,'Coded Passages'!$C:$C,$B6,'Coded Passages'!$H:$H,E$2) | F6: =COUNTIFS('Coded Passages'!$B:$B,$A6,'Coded Passages'!$C:$C,$B6,'Coded Passages'!$H:$H,F$2) | G6: =COUNTIFS('Coded Passages'!$B:$B,$A6,'Coded Passages'!$C:$C,$B6,'Coded Passages'!$H:$H,G$2) | H6: =COUNTIFS('Coded Passages'!$B:$B,$A6,'Coded Passages'!$C:$C,$B6,'Coded Passages'!$H:$H,H$2) | I6: =COUNTIFS('Coded Passages'!$B:$B,$A6,'Coded Passages'!$C:$C,$B6,'Coded Passages'!$H:$H,I$2) | J6: =COUNTIFS('Coded Passages'!$B:$B,$A6,'Coded Passages'!$C:$C,$B6,'Coded Passages'!$H:$H,J$2) | L6: =SUM(C6:K6) | N6: D1.1·Delegitimization o | O6: =I6
A7: D1.1 | B7: =COUNTIFS('Coded Passages'!$B:$B,$A7,'Coded Passages'!$C:$C,$B7,'Coded Passages'!$H:$H,B$2) | C7: =COUNTIFS('Coded Passages'!$B:$B,$A7,'Coded Passages'!$C:$C,$B7,'Coded Passages'!$H:$H,C$2) | D7: =COUNTIFS('Coded Passages'!$B:$B,$A7,'Coded Passages'!$C:$C,$B7,'Coded Passages'!$H:$H,D$2) | E7: =COUNTIFS('Coded Passages'!$B:$B,$A7,'Coded Passages'!$C:$C,$B7,'Coded Passages'!$H:$H,E$2) | F7: =COUNTIFS('Coded Passages'!$B:$B,$A7,'Coded Passages'!$C:$C,$B7,'Coded Passages'!$H:$H,F$2) | G7: =COUNTIFS('Coded Passages'!$B:$B,$A7,'Coded Passages'!$C:$C,$B7,'Coded Passages'!$H:$H,G$2) | H7: =COUNTIFS('Coded Passages'!$B:$B,$A7,'Coded Passages'!$C:$C,$B7,'Coded Passages'!$H:$H,H$2) | I7: =COUNTIFS('Coded Passages'!$B:$B,$A7,'Coded Passages'!$C:$C,$B7,'Coded Passages'!$H:$H,I$2) | J7: =COUNTIFS('Coded Passages'!$B:$B,$A7,'Coded Passages'!$C:$C,$B7,'Coded Passages'!$H:$H,J$2) | L7: =SUM(C7:K7) | N7: D1.1·Deregulation Benef | O7: =I7
A8: D1.1 | B8: =COUNTIFS('Coded Passages'!$B:$B,$A8,'Coded Passages'!$C:$C,$B8,'Coded Passages'!$H:$H,B$2) | C8: =COUNTIFS('Coded Passages'!$B:$B,$A8,'Coded Passages'!$C:$C,$B8,'Coded Passages'!$H:$H,C$2) | D8: =COUNTIFS('Coded Passages'!$B:$B,$A8,'Coded Passages'!$C:$C,$B8,'Coded Passages'!$H:$H,D$2) | E8: =COUNTIFS('Coded Passages'!$B:$B,$A8,'Coded Passages'!$C:$C,$B8,'Coded Passages'!$H:$H,E$2) | F8: =COUNTIFS('Coded Passages'!$B:$B,$A8,'Coded Passages'!$C:$C,$B8,'Coded Passages'!$H:$H,F$2) | G8: =COUNTIFS('Coded Passages'!$B:$B,$A8,'Coded Passages'!$C:$C,$B8,'Coded Passages'!$H:$H,G$2) | H8: =COUNTIFS('Coded Passages'!$B:$B,$A8,'Coded Passages'!$C:$C,$B8,'Coded Passages'!$H:$H,H$2) | I8: =COUNTIFS('Coded Passages'!$B:$B,$A8,'Coded Passages'!$C:$C,$B8,'Coded Passages'!$H:$H,I$2) | J8: =COUNTIFS('Coded Passages'!$B:$B,$A8,'Coded Passages'!$C:$C,$B8,'Coded Passages'!$H:$H,J$2) | L8: =SUM(C8:K8) | N8: D1.1·Anti-State / Anti- | O8: =I8
A9: D1.1 | B9: =COUNTIFS('Coded Passages'!$B:$B,$A9,'Coded Passages'!$C:$C,$B9,'Coded Passages'!$H:$H,B$2) | C9: =COUNTIFS('Coded Passages'!$B:$B,$A9,'Coded Passages'!$C:$C,$B9,'Coded Passages'!$H:$H,C$2) | D9: =COUNTIFS('Coded Passages'!$B:$B,$A9,'Coded Passages'!$C:$C,$B9,'Coded Passages'!$H:$H,D$2) | E9: =COUNTIFS('Coded Passages'!$B:$B,$A9,'Coded Passages'!$C:$C,$B9,'Coded Passages'!$H:$H,E$2) | F9: =COUNTIFS('Coded Passages'!$B:$B,$A9,'Coded Passages'!$C:$C,$B9,'Coded Passages'!$H:$H,F$2) | G9: =COUNTIFS('Coded Passages'!$B:$B,$A9,'Coded Passages'!$C:$C,$B9,'Coded Passages'!$H:$H,G$2) | H9: =COUNTIFS('Coded Passages'!$B:$B,$A9,'Coded Passages'!$C:$C,$B9,'Coded Passages'!$H:$H,H$2) | I9: =COUNTIFS('Coded Passages'!$B:$B,$A9,'Coded Passages'!$C:$C,$B9,'Coded Passages'!$H:$H,I$2) | J9: =COUNTIFS('Coded Passages'!$B:$B,$A9,'Coded Passages'!$C:$C,$B9,'Coded Passages'!$H:$H,J$2) | L9: =SUM(C9:K9) | N9: D1.1·Rejection of Multi | O9: =I9
A10: D1.2 | B10: =COUNTIFS('Coded Passages'!$B:$B,$A10,'Coded Passages'!$C:$C,$B10,'Coded Passages'!$H:$H,B$2) | C10: =COUNTIFS('Coded Passages'!$B:$B,$A10,'Coded Passages'!$C:$C,$B10,'Coded Passages'!$H:$H,C$2) | D10: =COUNTIFS('Coded Passages'!$B:$B,$A10,'Coded Passages'!$C:$C,$B10,'Coded Passages'!$H:$H,D$2) | E10: =COUNTIFS('Coded Passages'!$B:$B,$A10,'Coded Passages'!$C:$C,$B10,'Coded Passages'!$H:$H,E$2) | F10: =COUNTIFS('Coded Passages'!$B:$B,$A10,'Coded Passages'!$C:$C,$B10,'Coded Passages'!$H:$H,F$2) | G10: =COUNTIFS('Coded Passages'!$B:$B,$A10,'Coded Passages'!$C:$C,$B10,'Coded Passages'!$H:$H,G$2) | H10: =COUNTIFS('Coded Passages'!$B:$B,$A10,'Coded Passages'!$C:$C,$B10,'Coded Passages'!$H:$H,H$2) | I10: =COUNTIFS('Coded Passages'!$B:$B,$A10,'Coded Passages'!$C:$C,$B10,'Coded Passages'!$H:$H,I$2) | J10: =COUNTIFS('Coded Passages'!$B:$B,$A10,'Coded Passages'!$C:$C,$B10,'Coded Passages'!$H:$H,J$2) | L10: =SUM(C10:K10) | N10: D1.2·Climate Skepticism | O10: =I10
A11: D1.2 | B11: =COUNTIFS('Coded Passages'!$B:$B,$A11,'Coded Passages'!$C:$C,$B11,'Coded Passages'!$H:$H,B$2) | C11: =COUNTIFS('Coded Passages'!$B:$B,$A11,'Coded Passages'!$C:$C,$B11,'Coded Passages'!$H:$H,C$2) | D11: =COUNTIFS('Coded Passages'!$B:$B,$A11,'Coded Passages'!$C:$C,$B11,'Coded Passages'!$H:$H,D$2) | E11: =COUNTIFS('Coded Passages'!$B:$B,$A11,'Coded Passages'!$C:$C,$B11,'Coded Passages'!$H:$H,E$2) | F11: =COUNTIFS('Coded Passages'!$B:$B,$A11,'Coded Passages'!$C:$C,$B11,'Coded Passages'!$H:$H,F$2) | G11: =COUNTIFS('Coded Passages'!$B:$B,$A11,'Coded Passages'!$C:$C,$B11,'Coded Passages'!$H:$H,G$2) | H11: =COUNTIFS('Coded Passages'!$B:$B,$A11,'Coded Passages'!$C:$C,$B11,'Coded Passages'!$H:$H,H$2) | I11: =COUNTIFS('Coded Passages'!$B:$B,$A11,'Coded Passages'!$C:$C,$B11,'Coded Passages'!$H:$H,I$2) | J11: =COUNTIFS('Coded Passages'!$B:$B,$A11,'Coded Passages'!$C:$C,$B11,'Coded Passages'!$H:$H,J$2) | L11: =SUM(C11:K11) | N11: D1.2·Attack on Experts | O11: =I11
A12: D1.2 | B12: =COUNTIFS('Coded Passages'!$B:$B,$A12,'Coded Passages'!$C:$C,$B12,'Coded Passages'!$H:$H,B$2) | C12: =COUNTIFS('Coded Passages'!$B:$B,$A12,'Coded Passages'!$C:$C,$B12,'Coded Passages'!$H:$H,C$2) | D12: =COUNTIFS('Coded Passages'!$B:$B,$A12,'Coded Passages'!$C:$C,$B12,'Coded Passages'!$H:$H,D$2) | E12: =COUNTIFS('Coded Passages'!$B:$B,$A12,'Coded Passages'!$C:$C,$B12,'Coded Passages'!$H:$H,E$2) | F12: =COUNTIFS('Coded Passages'!$B:$B,$A12,'Coded Passages'!$C:$C,$B12,'Coded Passages'!$H:$H,F$2) | G12: =COUNTIFS('Coded Passages'!$B:$B,$A12,'Coded Passages'!$C:$C,$B12,'Coded Passages'!$H:$H,G$2) | H12: =COUNTIFS('Coded Passages'!$B:$B,$A12,'Coded Passages'!$C:$C,$B12,'Coded Passages'!$H:$H,H$2) | I12: =COUNTIFS('Coded Passages'!$B:$B,$A12,'Coded Passages'!$C:$C,$B12,'Coded Passages'!$H:$H,I$2) | J12: =COUNTIFS('Coded Passages'!$B:$B,$A12,'Coded Passages'!$C:$C,$B12,'Coded Passages'!$H:$H,J$2) | L12: =SUM(C12:K12) | N12: D1.2·Pseudo-Science / I | O12: =I12
A13: D1.2 | B13: =COUNTIFS('Coded Passages'!$B:$B,$A13,'Coded Passages'!$C:$C,$B13,'Coded Passages'!$H:$H,B$2) | C13: =COUNTIFS('Coded Passages'!$B:$B,$A13,'Coded Passages'!$C:$C,$B13,'Coded Passages'!$H:$H,C$2) | D13: =COUNTIFS('Coded Passages'!$B:$B,$A13,'Coded Passages'!$C:$C,$B13,'Coded Passages'!$H:$H,D$2) | E13: =COUNTIFS('Coded Passages'!$B:$B,$A13,'Coded Passages'!$C:$C,$B13,'Coded Passages'!$H:$H,E$2) | F13: =COUNTIFS('Coded Passages'!$B:$B,$A13,'Coded Passages'!$C:$C,$B13,'Coded Passages'!$H:$H,F$2) | G13: =COUNTIFS('Coded Passages'!$B:$B,$A13,'Coded Passages'!$C:$C,$B13,'Coded Passages'!$H:$H,G$2) | H13: =COUNTIFS('Coded Passages'!$B:$B,$A13,'Coded Passages'!$C:$C,$B13,'Coded Passages'!$H:$H,H$2) | I13: =COUNTIFS('Coded Passages'!$B:$B,$A13,'Coded Passages'!$C:$C,$B13,'Coded Passages'!$H:$H,I$2) | J13: =COUNTIFS('Coded Passages'!$B:$B,$A13,'Coded Passages'!$C:$C,$B13,'Coded Passages'!$H:$H,J$2) | L13: =SUM(C13:K13) | N13: D1.2·Attack on Universi | O13: =I13
A14: D1.2 | B14: =COUNTIFS('Coded Passages'!$B:$B,$A14,'Coded Passages'!$C:$C,$B14,'Coded Passages'!$H:$H,B$2) | C14: =COUNTIFS('Coded Passages'!$B:$B,$A14,'Coded Passages'!$C:$C,$B14,'Coded Passages'!$H:$H,C$2) | D14: =COUNTIFS('Coded Passages'!$B:$B,$A14,'Coded Passages'!$C:$C,$B14,'Coded Passages'!$H:$H,D$2) | E14: =COUNTIFS('Coded Passages'!$B:$B,$A14,'Coded Passages'!$C:$C,$B14,'Coded Passages'!$H:$H,E$2) | F14: =COUNTIFS('Coded Passages'!$B:$B,$A14,'Coded Passages'!$C:$C,$B14,'Coded Passages'!$H:$H,F$2) | G14: =COUNTIFS('Coded Passages'!$B:$B,$A14,'Coded Passages'!$C:$C,$B14,'Coded Passages'!$H:$H,G$2) | H14: =COUNTIFS('Coded Passages'!$B:$B,$A14,'Coded Passages'!$C:$C,$B14,'Coded Passages'!$H:$H,H$2) | I14: =COUNTIFS('Coded Passages'!$B:$B,$A14,'Coded Passages'!$C:$C,$B14,'Coded Passages'!$H:$H,I$2) | J14: =COUNTIFS('Coded Passages'!$B:$B,$A14,'Coded Passages'!$C:$C,$B14,'Coded Passages'!$H:$H,J$2) | L14: =SUM(C14:K14) | N14: D1.2·Rejection of Exper | O14: =I14
... A21: IND | B21: =COUNTIFS('Coded Passages'!$B:$B,$A21,'Coded Passages'!$C:$C,$B21,'Coded Passages'!$H:$H,B$2) | C21: =COUNTIFS('Coded Passages'!$B:$B,$A21,'Coded Passages'!$C:$C,$B21,'Coded Passages'!$H:$H,C$2) | D21: =COUNTIFS('Coded Passages'!$B:$B,$A21,'Coded Passages'!$C:$C,$B21,'Coded Passages'!$H:$H,D$2) | E21: =COUNTIFS('Coded Passages'!$B:$B,$A21,'Coded Passages'!$C:$C,$B21,'Coded Passages'!$H:$H,E$2) | F21: =COUNTIFS('Coded Passages'!$B:$B,$A21,'Coded Passages'!$C:$C,$B21,'Coded Passages'!$H:$H,F$2) | G21: =COUNTIFS('Coded Passages'!$B:$B,$A21,'Coded Passages'!$C:$C,$B21,'Coded Passages'!$H:$H,G$2) | H21: =COUNTIFS('Coded Passages'!$B:$B,$A21,'Coded Passages'!$C:$C,$B21,'Coded Passages'!$H:$H,H$2) | I21: =COUNTIFS('Coded Passages'!$B:$B,$A21,'Coded Passages'!$C:$C,$B21,'Coded Passages'!$H:$H,I$2) | J21: =COUNTIFS('Coded Passages'!$B:$B,$A21,'Coded Passages'!$C:$C,$B21,'Coded Passages'!$H:$H,J$2) | L21: =SUM(C21:K21) | N21: IND·Temporal Appropria | O21: =I21
A22: TOTAL | B22: All Sub-codes | C22: =SUM(C3:C21) | D22: =SUM(D3:D21) | E22: =SUM(E3:E21) | F22: =SUM(F3:F21) | G22: =SUM(G3:G21) | H22: =SUM(H3:H21) | I22: =SUM(I3:I21) | J22: =SUM(J3:J21) | ... L22: =SUM(L3:L21)

Sheet Speech Overview
A1: Speech-Level Overview — D1 / Inductive counts update automatically from 'Coded Passages' (D2 = 0 in v3)
A2: Speech | B2: Date | C2: Venue | D2: Type | E2: D1 Codes | F2: D2 Codes | G2: Inductive | H2: Total | I2: Notes
A3: Debate Presidencial 2023 | B3: 2023-10-08 | C3: Buenos Aires | D3: Debate | E3: =COUNTIFS('Coded Passages'!$H:$H,$A3,'Coded Passages'!$B:$B,"D1*") | F3: =COUNTIFS('Coded Passages'!$H:$H,$A3,'Coded Passages'!$B:$B,"D2*") | G3: =COUNTIFS('Coded Passages'!$H:$H,$A3,'Coded Passages'!$B:$B,"IND") | H3: =E3+F3+G3 | I3: D2=0 in v3 (speech corpus)
A4: WEF Davos 2024 | B4: 2024-01-17 | C4: Davos | D4: Speech | E4: =COUNTIFS('Coded Passages'!$H:$H,$A4,'Coded Passages'!$B:$B,"D1*") | F4: =COUNTIFS('Coded Passages'!$H:$H,$A4,'Coded Passages'!$B:$B,"D2*") | G4: =COUNTIFS('Coded Passages'!$H:$H,$A4,'Coded Passages'!$B:$B,"IND") | H4: =E4+F4+G4 | I4: D2=0 in v3 (speech corpus)
A5: Apertura Sesiones Ordinarias 2024 (142°) | B5: 2024-03-01 | C5: Buenos Aires | D5: Speech | E5: =COUNTIFS('Coded Passages'!$H:$H,$A5,'Coded Passages'!$B:$B,"D1*") | F5: =COUNTIFS('Coded Passages'!$H:$H,$A5,'Coded Passages'!$B:$B,"D2*") | G5: =COUNTIFS('Coded Passages'!$H:$H,$A5,'Coded Passages'!$B:$B,"IND") | H5: =E5+F5+G5 | I5: D2=0 in v3 (speech corpus)
A6: UN General Assembly 79th | B6: 2024-09-24 | C6: New York | D6: Speech | E6: =COUNTIFS('Coded Passages'!$H:$H,$A6,'Coded Passages'!$B:$B,"D1*") | F6: =COUNTIFS('Coded Passages'!$H:$H,$A6,'Coded Passages'!$B:$B,"D2*") | G6: =COUNTIFS('Coded Passages'!$H:$H,$A6,'Coded Passages'!$B:$B,"IND") | H6: =E6+F6+G6 | I6: D2=0 in v3 (speech corpus)
A7: WEF Davos 2025 | B7: 2025-01-23 | C7: Davos | D7: Speech | E7: =COUNTIFS('Coded Passages'!$H:$H,$A7,'Coded Passages'!$B:$B,"D1*") | F7: =COUNTIFS('Coded Passages'!$H:$H,$A7,'Coded Passages'!$B:$B,"D2*") | G7: =COUNTIFS('Coded Passages'!$H:$H,$A7,'Coded Passages'!$B:$B,"IND") | H7: =E7+F7+G7 | I7: D2=0 in v3 (speech corpus)
A8: Apertura Sesiones Ordinarias 2025 (143°) | B8: 2025-03-01 | C8: Buenos Aires | D8: Speech | E8: =COUNTIFS('Coded Passages'!$H:$H,$A8,'Coded Passages'!$B:$B,"D1*") | F8: =COUNTIFS('Coded Passages'!$H:$H,$A8,'Coded Passages'!$B:$B,"D2*") | G8: =COUNTIFS('Coded Passages'!$H:$H,$A8,'Coded Passages'!$B:$B,"IND") | H8: =E8+F8+G8 | I8: D2=0 in v3 (speech corpus)
A9: UN General Assembly 80th | B9: 2025-09-24 | C9: New York | D9: Speech | E9: =COUNTIFS('Coded Passages'!$H:$H,$A9,'Coded Passages'!$B:$B,"D1*") | F9: =COUNTIFS('Coded Passages'!$H:$H,$A9,'Coded Passages'!$B:$B,"D2*") | G9: =COUNTIFS('Coded Passages'!$H:$H,$A9,'Coded Passages'!$B:$B,"IND") | H9: =E9+F9+G9 | I9: D2=0 in v3 (speech corpus)
A10: WEF Davos 2026 | B10: 2026-01-22 | C10: Davos | D10: Speech | E10: =COUNTIFS('Coded Passages'!$H:$H,$A10,'Coded Passages'!$B:$B,"D1*") | F10: =COUNTIFS('Coded Passages'!$H:$H,$A10,'Coded Passages'!$B:$B,"D2*") | G10: =COUNTIFS('Coded Passages'!$H:$H,$A10,'Coded Passages'!$B:$B,"IND") | H10: =E10+F10+G10 | I10: D2=0 in v3 (speech corpus)
A11: Apertura Sesiones Ordinarias 2026 (144°) | B11: 2026-03-01 | C11: Buenos Aires | D11: Speech | E11: =COUNTIFS('Coded Passages'!$H:$H,$A11,'Coded Passages'!$B:$B,"D1*") | F11: =COUNTIFS('Coded Passages'!$H:$H,$A11,'Coded Passages'!$B:$B,"D2*") | G11: =COUNTIFS('Coded Passages'!$H:$H,$A11,'Coded Passages'!$B:$B,"IND") | H11: =E11+F11+G11 | I11: D2=0 in v3 (speech corpus)
A12: TOTAL | E12: =SUM(E3:E11) | F12: =SUM(F3:F11) | G12: =SUM(G3:G11) | H12: =SUM(H3:H11)
