Workbook

Sheet Coded Passages
F1: Milei Climate Narratives - v3 Coded Passages - Data source for all summary sheets | K1: Coded in HTML (v3) | L1: Revision & comments
A2: # | B2: Dimension | C2: Sub-dimension | D2: Dimension (Full) | E2: Sub-code (Full) | F2: Quoted Passage | G2: Analytical Memo | H2: Speech | I2: Date | J2: Venue / Type | L2: Juani | M2: Eli | N2: Germán
A3: 1 | B3: D1.2 | C3: Climate Skepticism or Dismissal | D3: D1.2 — Public Science & Expertise | E3: Climate Skepticism or Dismissal | F3: A ver primero no mienta. Yo no niego el cambio climático. Lo que yo digo es que existe en la historia de la tierra un ciclo de temperaturas, es decir hay un comportamiento cíclico y este es el quinto punto del ciclo — donde la diferencia con los cuatro anteriores es que antes no estaba el ser humano. Por lo tanto todas esas políticas que culpan al ser humano del cambio climático son falsas y lo único que buscan es recaudar fondos para financiar vagos socialistas que escriben papers de cuarta. | G3: Milei performs the disclaimer-then-dismiss move: "I don't deny climate change" is immediately followed by the natural-cycles attribution, which reproduces effective denial while maintaining rhetorical deniability. The key claim — "all those policies that blame humans for climate change are false" — is a direct dismissal of the scientific basis for climate regulation, delivered as a logical conclusion from the paleoclimatic premise. This is the most compressed instance of Climate_Skepticism_or_Dismissal in the corpus: denial of anthropogenic attribution without denial of the climate phenomenon itself. | H3: Debate Presidencial 2023 | I3: 2023-10-08 | J3: Buenos Aires · Debate | K3: TRUE | L3: ok | N3: ok
A4: 2 | B4: D1.1 | C4: Sustainability as Ideological or Harmful | D4: D1.1 — State Intervention & Governance | E4: Sustainability as Ideological or Harmful | F4: A ver primero no mienta. Yo no niego el cambio climático. Lo que yo digo es que existe en la historia de la tierra un ciclo de temperaturas, es decir hay un comportamiento cíclico y este es el quinto punto del ciclo — donde la diferencia con los cuatro anteriores es que antes no estaba el ser humano. Por lo tanto todas esas políticas que culpan al ser humano del cambio climático son falsas y lo único que buscan es recaudar fondos para financiar vagos socialistas que escriben papers de cuarta. | G4: "Recaudar fondos para financiar vagos socialistas que escriben papers de cuarta" reframes climate policy as a rent-extraction mechanism for a parasitic academic class. The claim is not that climate policy is merely wrong — it is that climate policy exists as an institutional vehicle for redistributing resources to ideologically motivated, low-quality scholarship. This is Sustainability_as_Ideological_or_Harmful at its most direct: the policy's real function is material redistribution under ideological cover, not environmental protection. | H4: Debate Presidencial 2023 | I4: 2023-10-08 | J4: Buenos Aires · Debate | K4: TRUE | L4: ok | N4: ok
A5: 3 | B5: D1.2 | C5: Attack on Experts & Technocrats | D5: D1.2 — Public Science & Expertise | E5: Attack on Experts & Technocrats | F5: A ver primero no mienta. Yo no niego el cambio climático. Lo que yo digo es que existe en la historia de la tierra un ciclo de temperaturas, es decir hay un comportamiento cíclico y este es el quinto punto del ciclo — donde la diferencia con los cuatro anteriores es que antes no estaba el ser humano. Por lo tanto todas esas políticas que culpan al ser humano del cambio climático son falsas y lo único que buscan es recaudar fondos para financiar vagos socialistas que escriben papers de cuarta. | G5: "Vagos socialistas que escriben papers de cuarta" is the rawest expert delegitimation in the corpus — climate scientists reduced to lazy, ideologically motivated rent-seekers producing worthless work. Unlike the more sophisticated epistemological arguments deployed at Davos (which grant good intentions while invalidating the theoretical framework), here the attack is purely ad hominem and institutional, characterizing climate science as professionally worthless rather than merely theoretically flawed. | H5: Debate Presidencial 2023 | I5: 2023-10-08 | J5: Buenos Aires · Debate | K5: TRUE | L5: Dimension OK. Sub-dimension alternativas podrían ser: - References to “pseudo-science” or ideological science - Delegitimization of scientific and professional institutions | N5: "ref to pesudo-science or ideological science"
A6: 4 | B6: IND | C6: Reported Denial | D6: Inductive | E6: Reported Denial | F6: la destrucción del Planeta es una de las muestras más claras de la irracionalidad de este sistema capitalista... pero [Milei] defiende la libertad de las empresas para contaminar hasta los ríos y llegó a decir que el cambio climático es del socialismo. | G6: Bregman's reported-speech paraphrase ("llegó a decir que el cambio climático es del socialismo") functions as inter-discursive corroboration: a nationally televised opponent accurately summarizing a Milei position confirms the claim circulates publicly and is understood as politically legible. The paraphrase maps directly onto D1.3 > Neo_Marxism — framing climate change as caused by or synonymous with socialism. Not primary Milei discourse; coded here for contextual and confirmatory purposes only. | H6: Debate Presidencial 2023 | I6: 2023-10-08 | J6: Buenos Aires · Debate | K6: TRUE | L6: N/A (no es dicho por él mismo en este momento, es más bien una referencia de dichos previos en entrevistas)
A7: 5 | B7: D1.3 | C7: Civilizational Defense | D7: D1.3 — Cultural Backlash | E7: Civilizational Defense | F7: Buenas tardes, muchas gracias: hoy estoy acá para decirles que Occidente está en peligro, está en peligro porque aquellos, que supuestamente deben defender los valores de Occidente, se encuentran cooptados por una visión del mundo que – inexorablemente – conduce al socialismo, en consecuencia a la pobreza. Lamentablemente en las últimas décadas, motivados por algunos deseos bien pensantes de querer ayudar al prójimo y otros por el deseo de querer pertenecer a una casta privilegiada, los principales líderes del mundo occidental han abandonado el modelo de la libertad, por distintas versiones, de lo que llamamos colectivismo. | G7: The opening sentences establish the master civilizational frame for the entire speech: Western civilization is under existential threat from socialism, and the WEF audience itself is identified as part of a "casta privilegiada" complicit in that decline. This frame pre-loads every subsequent critique — including of environmental policy — with civilizational stakes. Climate governance emanating from the "cooptados" Western establishment is tainted by association with civilizational threat, making engagement with it a form of civilizational capitulation. | H7: WEF Davos 2024 | I7: 2024-01-17 | J7: Davos · Speech | K7: TRUE | L7: D1 es Dimensión correcta. Parte central de la "Batalla cultural". La sub-dimensión VER. Podría ser parte de 'Neo-marxismo'. | N7: Subdimension: anti-socialismo (or anti-colectivismo)
A8: 6 | B8: D1.1 | C8: Anti-Casta (Elite Frame) | D8: D1.1 — State Intervention & Governance | E8: Anti-Casta (Elite Frame) | F8: Buenas tardes, muchas gracias: hoy estoy acá para decirles que Occidente está en peligro, está en peligro porque aquellos, que supuestamente deben defender los valores de Occidente, se encuentran cooptados por una visión del mundo que – inexorablemente – conduce al socialismo, en consecuencia a la pobreza. Lamentablemente en las últimas décadas, motivados por algunos deseos bien pensantes de querer ayudar al prójimo y otros por el deseo de querer pertenecer a una casta privilegiada, los principales líderes del mundo occidental han abandonado el modelo de la libertad, por distintas versiones, de lo que llamamos colectivismo. | G8: "Pertenecer a una casta privilegiada" extends Milei's domestic anti-elite frame to the global governance level, targeting the WEF audience itself. International climate institutions and their leaders are pre-emptively delegitimized as members of a global caste pursuing privilege rather than planetary welfare — the same logic used domestically against environmental ministries and CONICET is applied globally to IPCC, UNEP, and multilateral climate bodies. | H8: WEF Davos 2024 | I8: 2024-01-17 | J8: Davos · Speech | K8: TRUE | L8: ok | N8: ok
A9: 7 | B9: D1.1 | C9: Market Primacy | D9: D1.1 — State Intervention & Governance | E9: Market Primacy | F9: La conclusión es obvia: lejos de ser la causa de nuestros problemas, el capitalismo de libre empresa, como sistema económico, es la única herramienta que tenemos para terminar con el hambre, la pobreza y la indigencia, a lo largo y a lo ancho de todo el planeta. La evidencia empírica es incuestionable. | G9: The hockey-stick economic history culminates in the categorical Market_Primacy claim: free-enterprise capitalism is "the only tool" for ending poverty, and the conclusion is declared empirically self-evident. For sustainability governance, the structural implication is total: if markets are the only legitimate mechanism for solving the most fundamental collective problem (poverty), they are implicitly the only legitimate mechanism for environmental problems, displacing any basis for state-led climate regulation. | H9: WEF Davos 2024 | I9: 2024-01-17 | J9: Davos · Speech | K9: TRUE | L9: ok | N9: ok
A10: 8 | B10: IND | C10: Selective Empiricism | D10: Inductive | E10: Selective Empiricism | F10: La conclusión es obvia: lejos de ser la causa de nuestros problemas, el capitalismo de libre empresa, como sistema económico, es la única herramienta que tenemos para terminar con el hambre, la pobreza y la indigencia, a lo largo y a lo ancho de todo el planeta. La evidencia empírica es incuestionable. | G10: "La evidencia empírica es incuestionable" is the canonical Selective_Empiricism instance in the corpus: Milei claims unquestionable empirical authority for the pro-market historical narrative, but later in the same speech systematically dismisses opposing academic and institutional knowledge (including climate science) as ideologically captured. The move is to appropriate the prestige of empiricism for one side while denying it to the other — crowding out rather than refuting. | H10: WEF Davos 2024 | I10: 2024-01-17 | J10: Davos · Speech | K10: TRUE | L10: VER | N10: Puede ser una subcategoria dentro de "Science and expertice", podria llamarse: Selective scientific empirism
A11: 9 | B11: D1.1 | C11: Market Primacy | D11: D1.1 — State Intervention & Governance | E11: Market Primacy | F11: El colectivismo - al inhibir estos procesos de descubrimiento y al dificultar la apropiación de lo descubierto - ata al emprendedor de las manos y le imposibilita producir mejores bienes y ofrecer mejores servicios a un mejor precio. ¿Cómo puede ser, entonces, que desde la academia, los organismos internacionales, la política y la teoría económica se demonice un sistema económico que no sólo ha sacado de la pobreza más extrema, al 90 por ciento de la población mundial? | G11: The Kirznerian market-as-discovery-process argument provides theoretical grounding: environmental outcomes, like economic ones, are best achieved through decentralized market discovery rather than state planning. "Academia, los organismos internacionales, la política y la teoría económica" — the four pillars of climate governance legitimacy — are grouped as an ideological bloc irrationally hostile to the proven market mechanism. | H11: WEF Davos 2024 | I11: 2024-01-17 | J11: Davos · Speech | K11: TRUE | L11: ok | N11: Subdimension: anti-socialismo (or anti-colectivismo)
A12: 10 | B12: D1.2 | C12: Attack on Experts & Technocrats | D12: D1.2 — Public Science & Expertise | E12: Attack on Experts & Technocrats | F12: El colectivismo - al inhibir estos procesos de descubrimiento y al dificultar la apropiación de lo descubierto - ata al emprendedor de las manos y le imposibilita producir mejores bienes y ofrecer mejores servicios a un mejor precio. ¿Cómo puede ser, entonces, que desde la academia, los organismos internacionales, la política y la teoría económica se demonice un sistema económico que no sólo ha sacado de la pobreza más extrema, al 90 por ciento de la población mundial? | G12: The entire authority apparatus — academic, international, political, theoretical — is presented as a unified bloc that "demonizes" capitalism. For sustainability governance: IPCC, UNEP, national science ministries, and environmental economics are all expressions of the same anti-capitalist ideological formation. This is a structural delegitimation of the expert class, not a dispute with specific scientific findings. | H12: WEF Davos 2024 | I12: 2024-01-17 | J12: Davos · Speech | K12: TRUE | L12: ok | N12: ok
A13: 11 | B13: D1.2 | C13: Pseudo-Science / Ideological Science | D13: D1.2 — Public Science & Expertise | E13: Pseudo-Science / Ideological Science | F13: El problema esencial de occidente hoy es que no sólo debemos enfrentarnos a quienes siguen bregando por el socialismo empobrecedor; sino también a nuestros propios líderes, pensadores y académicos que, amparados en un marco teórico equivocado, socavan los fundamentos del sistema que nos ha dado la mayor expansión de riqueza y prosperidad de nuestra historia. | G13: "Amparados en un marco teórico equivocado" frames the entire academic and expert community as epistemically compromised: their framework is wrong, and therefore their outputs — including climate science, environmental economics, and sustainability research — are systematically distorted. The concession of good intentions ("sin quererlo," as the next paragraph notes) makes this a structurally more powerful delegitimation than the debate's ad hominem: it invalidates conclusions while preserving a veneer of charity toward the actors. | H13: WEF Davos 2024 | I13: 2024-01-17 | J13: Davos · Speech | K13: TRUE | L13: VER. Deberíamos definir si la sub-dimensión 'Pseudo-science' sólo aplica a sustainability science o más amplia. | N13: ok but also "attacks on experts and technocratics elites"
A14: 12 | B14: D1.1 | C14: Delegitimization of Regulation | D14: D1.1 — State Intervention & Governance | E14: Delegitimization of Regulation | F14: El marco teórico al que me refiero es el de la teoría económica neoclásica, que diseña un instrumental que, sin quererlo, termina siendo funcional a la intromisión del estado. El problema de los neoclásicos es que como el modelo del que se enamoraron no mapea contra la realidad, atribuyen el error a supuestos fallos del mercado en vez de revisar las premisas de su modelo. | G14: The attack on neoclassical economics demolishes the theoretical foundation of environmental regulation. Mainstream climate policy — carbon pricing, Pigouvian taxes, cap-and-trade — derives its justification from externality theory, precisely the "instrumental" Milei argues ends up serving state intrusion. By framing neoclassical economics as the theoretical Trojan horse through which socialism enters, he delegitimizes the entire economic-theoretical basis for climate regulation at the level of first principles. | H14: WEF Davos 2024 | I14: 2024-01-17 | J14: Davos · Speech | K14: TRUE | L14: ok | N14: Ok, but it would also be "selective scientific evidence (or similar)"
A15: 13 | B15: D1.1 | C15: Deregulation Benefits | D15: D1.1 — State Intervention & Governance | E15: Deregulation Benefits | F15: El pretexto de un supuesto fallo de mercado se introducen regulaciones que lo único que generan es distorsiones en el sistema de precios, que impiden el cálculo económico, y en consecuencia el ahorro, la inversión y el crecimiento. | G15: The positive deregulation case through intervention-spiral logic: each regulatory "correction" of a supposed market failure compounds the problem by distorting price signals, impairing economic calculation, reducing saving, investment, and growth. Applied to climate policy: carbon taxes, emissions standards, and green industrial mandates suppress economic activity rather than solving an environmental problem. | H15: WEF Davos 2024 | I15: 2024-01-17 | J15: Davos · Speech | K15: TRUE | L15: ok | N15: ok, aunque "bemefits of deregulation" es practicamente igual que "deligitimization of regulation" talvez podemos combinar las dos en una
A16: 14 | B16: D1.1 | C16: Market Primacy | D16: D1.1 — State Intervention & Governance | E16: Market Primacy | F16: Si las transacciones son voluntarias, el único contexto en el que puede haber un fallo de mercado es si hay coacción. Y el único con la capacidad de coaccionar de manera generalizada es el estado que tiene el monopolio de la violencia. Los fallos de mercado no existen. | G16: "El fallo del mercado es un oxímoron. No existe fallo de mercado." This is the most consequential passage in the speech for sustainability governance. Environmental externalities — greenhouse gas emissions, pollution, deforestation — are the paradigmatic market failures in environmental economics; the entire justification for climate regulation rests on this concept. By declaring market failures logically impossible (not empirically absent, but conceptually self-contradictory), Milei eliminates the theoretical ground for any climate policy whatsoever. | H16: WEF Davos 2024 | I16: 2024-01-17 | J16: Davos · Speech | K16: TRUE | L16: ok | N16: ok
A17: 15 | B17: D1.1 | C17: Delegitimization of Regulation | D17: D1.1 — State Intervention & Governance | E17: Delegitimization of Regulation | F17: Si las transacciones son voluntarias, el único contexto en el que puede haber un fallo de mercado es si hay coacción. Y el único con la capacidad de coaccionar de manera generalizada es el estado que tiene el monopolio de la violencia. Los fallos de mercado no existen. | G17: The inversion of causality — apparent market failures are actually state failures — performs total delegitimation of environmental regulation: if every environmental harm traces to prior state intervention rather than market dynamics, the correct response to environmental problems is always less regulation, never more. The "monopolio de la violencia" framing additionally casts environmental regulation as coercive imposition on voluntary exchange, not corrective policy. | H17: WEF Davos 2024 | I17: 2024-01-17 | J17: Davos · Speech | K17: TRUE | L17: OJO con codear de más y sobredimensionar la frecuencia de la categoría. Podría unificarse con #14. | N17: sub categoria puede ser tamb "anti state" ya que aca formula una critica directa al rol del Estado
A18: 16 | B18: D1.1 | C18: Anti-State / Anti-Bureaucratic | D18: D1.1 — State Intervention & Governance | E18: Anti-State / Anti-Bureaucratic | F18: Sin embargo, frente a la demostración teórica de que la intervención del estado es perjudicial, y la evidencia empírica de que fracasó, la solución que propondrán los colectivistas no es mayor libertad sino que es mayor regulación, generando una espiral descendiente de regulaciones hasta que todos seamos más pobres, y la vida de todos nosotros dependa de un burócrata sentado en una oficina de lujo. | G18: "Un burócrata sentado en una oficina de lujo" personifies the regulatory state as a rent-seeking class who live off others' productivity. Sustainability agencies, CONICET researchers, and UNFCCC secretariat staff are implicitly "parasites" in this framing. The "espiral descendiente de regulaciones" presents regulatory accumulation as inherently self-reinforcing and catastrophic — every incremental climate regulation is a step toward total bureaucratic control. | H18: WEF Davos 2024 | I18: 2024-01-17 | J18: Davos · Speech | K18: TRUE | L18: ok | N18: ok, puede ser tamb "anti casta"
... A33: 31 | B33: D1.1 | C33: Sustainability as Ideological or Harmful | D33: D1.1 — State Intervention & Governance | E33: Sustainability as Ideological or Harmful | F33: Nor has the tutelage of the World Economic Forum helped, where ridiculous policies are promoted with Malthusian blinders on — such as "Zero Emission" policies — which harm poor countries in particular. To policies linked to sexual and reproductive rights, when the birth rate in Western countries is plummeting, heralding a bleak future for all. | G33: "Zero Emission" policies are named explicitly and characterized as "ridiculous" and "Malthusian," harmful especially to poor countries. This is the most direct attack on net-zero climate policy as policy in the UN corpus: the agenda is framed as ideologically driven (Malthusian) and materially harmful (to the poor), deploying both the sustainability-as-harmful and the broader Malthusian anti-humanist framing simultaneously. | H33: UN General Assembly 79th | I33: 2024-09-24 | J33: New York · Speech | K33: TRUE | L33: ok. Me parece de las destacables | N33: ok
A34: 32 | B34: D1.3 | C34: Woke Bundling | D34: D1.3 — Cultural Backlash | E34: Woke Bundling | F34: Nor has the tutelage of the World Economic Forum helped, where ridiculous policies are promoted with Malthusian blinders on — such as "Zero Emission" policies — which harm poor countries in particular. To policies linked to sexual and reproductive rights, when the birth rate in Western countries is plummeting, heralding a bleak future for all. | G34: "Zero Emission" policies are listed in the same breath as "policies linked to sexual and reproductive rights" — climate policy bundled with population/reproductive policy via the Malthusian linkage. At the General Assembly, where many member states are deeply conservative on reproductive rights, this bundling maximizes delegitimization of climate governance among the audience most capable of blocking multilateral sustainability commitments. | H34: UN General Assembly 79th | I34: 2024-09-24 | J34: New York · Speech | K34: TRUE | L34: ok
A35: 33 | B35: D1.1 | C35: Rejection of Multilateral Governance | D35: D1.1 — State Intervention & Governance | E35: Rejection of Multilateral Governance | F35: An organization that, instead of confronting real global conflicts, invests time and effort in imposing on poor countries what, how and what they should produce, with whom they should associate, what they should eat and what they should believe in, as the present Pact for the Future intends to dictate. | G35: The list — what to produce, with whom to associate, what to eat, what to believe — encompasses climate-related production constraints (fossil fuel restrictions), trade conditionalities (Paris-Agreement-linked), dietary sustainability guidelines (meat consumption), and scientific orthodoxy (climate consensus). Framing these as illegitimate impositions on sovereignty and self-determination performs a comprehensive delegitimation covering the full scope of the sustainable development agenda. | H35: UN General Assembly 79th | I35: 2024-09-24 | J35: New York · Speech | K35: TRUE | L35: ok | N35: ok
A36: 34 | B36: D1.3 | C36: Woke Bundling | D36: D1.3 — Cultural Backlash | E36: Woke Bundling | F36: Therefore, I would like to issue a warning: we are at the end of a cycle. Collectivism and moral posturing, of the woke agenda, have collided with reality and no longer have credible solutions to offer to the world's real problems. | G36: "Collectivism and moral posturing, of the woke agenda" — the UN sustainability agenda is absorbed into the "woke agenda" at the General Assembly, delivering the same cultural-war framing to the world's premier diplomatic institution. "Has collided with reality and no longer has credible solutions" performs a temporal delegitimation: the entire 30-year history of sustainable development (from Rio 1992 to the 2030 Agenda) is retroactively framed as a project that never worked and has now conclusively failed. | H36: UN General Assembly 79th | I36: 2024-09-24 | J36: New York · Speech | K36: TRUE | L36: ok | N36: ok
A37: 35 | B37: D1.1 | C37: Rejection of Multilateral Governance | D37: D1.1 — State Intervention & Governance | E37: Rejection of Multilateral Governance | F37: I want to be clear about something: Argentina will not support any policy that implies the restriction of individual freedoms, of trade, or the violation of the natural rights of individuals, no matter who promotes it or how much consensus that institution has. For this reason, we wish to express — officially — our dissent on the Pact of the Future, signed on Sunday, and we invite all the nations of the free world to join us, not only in dissenting from this pact, but also in the creation of a new agenda for this noble institution: the agenda of freedom. | G37: [V3 re-code — was D2.3 in v2] The formal announcement of dissent from the Pact for the Future is here coded as D1.1 > Rejection_of_Multilateral_Governance because this passage is a rhetorical act: Milei is legitimizing and framing the exit, not performing the institutional act itself. The phrase "no matter who promotes it or how much consensus that institution has" directly applies the Fallacy_of_Authority logic to formal multilateral commitments — scientific and institutional consensus is explicitly declared non-binding. The invitation to form a counter-coalition extends the rhetorical delegitimation to a geopolitical project. The actual formal institutional act (official communication, voting record, decree) belongs in the D2 formal documentation corpus. | H37: UN General Assembly 79th | I37: 2024-09-24 | J37: New York · Speech | K37: TRUE | L37: ok. Es un anuncio. Trackear efecto en formalidad | N37: Not sure he reject here multilateral governance, he propose an alternative agenda for such governance, focusing on his interpretation of freedom as the central pilar. I would say it is part of Cultural backlash, with a subcategory of "freedom" or similar
A38: 36 | B38: D1.1 | C38: Rejection of Multilateral Governance | D38: D1.1 — State Intervention & Governance | E38: Rejection of Multilateral Governance | F38: From this day on, know that the Argentine Republic will abandon the position of historical neutrality and will be at the forefront of the struggle in defense of freedom. | G38: Argentina's declaration of a new activist foreign policy stance "in defense of freedom" — framed against the multilateral collectivist governance architecture — establishes a discursive commitment to sustained opposition to the international sustainability governance system. The rhetorical register is civilizational mobilization: Argentina is not a passive defector but a vanguard actor in a freedom-versus-collectivism conflict. | H38: UN General Assembly 79th | I38: 2024-09-24 | J38: New York · Speech | K38: TRUE | L38: VER. Este pasaje es fuerte pero más que un rechazo a la gobernanza multilateral es un posicionamiento dentro de sus reglas. Quizás englobar en ID #37 dentro de D1.3 | N38: Idem anterior; freedom as key moral principle
A39: 37 | B39: D1.3 | C39: Civilizational Defense | D39: D1.3 — Cultural Backlash | E39: Civilizational Defense | F39: From this day on, know that the Argentine Republic will abandon the position of historical neutrality and will be at the forefront of the struggle in defense of freedom. | G39: "La lucha en defensa de la libertad" against multilateral collectivism is the Civilizational_Defense frame applied as foreign policy commitment. Western civilization's survival requires active opposition to the institutions (UN, WEF, 2030 Agenda) that Milei has spent the speech identifying as the agents of civilizational decline. | H39: UN General Assembly 79th | I39: 2024-09-24 | J39: New York · Speech | K39: TRUE | L39: ok. Quizás esto englobe ID #36 | N39: ok for the dimension, see for the sub-dimension
A40: 38 | B40: D1.1 | C40: Rejection of Multilateral Governance | D40: D1.1 — State Intervention & Governance | E40: Rejection of Multilateral Governance | F40: Because I must say that forums like this one have been protagonists and promoters of the sinister agenda of wokeism that is doing so much damage to the Western world. | G40: WEF is named a "protagonist and promoter" of a "sinister agenda" — the institution that convenes global climate governance (the Davos Consensus, net-zero pledges, green capitalism frameworks) is delegitimized as ideologically captured before any specific climate argument is made. This is meta-level Rejection_of_Multilateral_Governance: not objecting to a specific commitment but delegitimizing the entire governance institution, meaning everything it produces — climate targets, ESG standards, green investment pledges — is tainted at source. | H40: WEF Davos 2025 | I40: 2025-01-23 | J40: Davos · Speech | K40: TRUE | L40: VER. Podría ir dentro de D1.3 cultural | N40: ok
A41: 39 | B41: D1.2 | C41: Attack on Universities | D41: D1.2 — Public Science & Expertise | E41: Attack on Universities | F41: This is the great epidemic of our time that must be cured. This is the cancer we need to get rid of. This ideology has colonized the world's most important institutions — from the political parties and governments of leading Western nations to global governance organizations, even NGOs, universities and media outlets. | G41: Universities appear in the list of colonized institutions alongside global governance organizations and media. Universities are the primary sites where climate scientists are trained, climate research is produced, and the expert community underpinning IPCC assessment reports is formed. By framing universities as ideologically colonized, Milei delegitimizes the climate knowledge-production chain at its origin point. | H41: WEF Davos 2025 | I41: 2025-01-23 | J41: Davos · Speech | K41: TRUE | L41: NO. Para mi es: D1.2. References to “pseudo-science” or ideological science | N41: ok
A42: 40 | B42: D1.2 | C42: Rejection of Expert Mediation | D42: D1.2 — Public Science & Expertise | E42: Rejection of Expert Mediation | F42: This is the great epidemic of our time that must be cured. This is the cancer we need to get rid of. This ideology has colonized the world's most important institutions — from the political parties and governments of leading Western nations to global governance organizations, even NGOs, universities and media outlets. | G42: The enumeration of captured institutions — political parties, global governance organizations, NGOs, universities, media — covers the entire infrastructure of expert mediation in public policy: the channels through which scientific knowledge reaches and legitimizes policy decisions. Claiming all are colonized by a single ideology denies any possibility of legitimate expert mediation in climate governance. | H42: WEF Davos 2025 | I42: 2025-01-23 | J42: Davos · Speech | K42: TRUE | L42: UNIFICAR CON ATTACKS ON EXPERTS AND TECHNOCRATIC ELITES | N42: ok
A43: 41 | B43: D1.3 | C43: Neo-Marxism | D43: D1.3 — Cultural Backlash | E43: Neo-Marxism | F43: These are all various heads of the same beast aimed at justifying the state's expansion through the appropriation and distortion of noble causes. | G43: Environmentalism is listed (alongside feminism, gender ideology, and immigration) as one of several "heads of the same beast aimed at justifying the state's expansion." Neo_Marxism's core formulation: these causes are strategic tools for state expansion, not genuine moral concerns. Carbon taxes, green industrial policy, and emissions regulation are Trojan horses for socialist state growth — not environmental management. | H43: WEF Davos 2025 | I43: 2025-01-23 | J43: Davos · Speech | K43: TRUE | L43: ok con D1.3. | N43: Ver. Si es cultural, entonces diria Woke Bundling; or anti socialisism
A44: 42 | B44: D1.3 | C44: Woke Bundling | D44: D1.3 — Cultural Backlash | E44: Woke Bundling | F44: But once again, wokeism has managed to pervert this fundamental idea. From preserving the environment for human enjoyment, we have shifted to a fanatical environmentalism, where we humans are seen as a cancer that must be eradicated and economic development is considered little more than a crime against nature. | G44: The pivot from feminism to environmentalism using "Wokism also manifests in..." is the formal Woke_Bundling move: climate governance is positioned as another chapter in the same ideological story, governed by the same analytical template applied to feminism. The concession-then-perversion structure ("a matter of common sense" → "perverted") is more sophisticated than Davos 2024 — acknowledging legitimacy before delegitimizing, making the attack harder to characterize as reactionary denial. | H44: WEF Davos 2025 | I44: 2025-01-23 | J44: Davos · Speech | K44: TRUE | L44: ok. Destacable | N44: ok
A45: 43 | B45: D1.3 | C45: Neo-Marxism | D45: D1.3 — Cultural Backlash | E45: Neo-Marxism | F45: But once again, wokeism has managed to pervert this fundamental idea. From preserving the environment for human enjoyment, we have shifted to a fanatical environmentalism, where we humans are seen as a cancer that must be eradicated and economic development is considered little more than a crime against nature. | G45: "Economic development is considered little more than a crime against nature" frames climate regulation as anti-civilization and anti-progress ideology. The "cancer" metaphor is analytically notable: Milei applies "cancer" both to woke ideology (which must be cured) and to how environmentalists supposedly view humanity — a double inversion equating climate advocates with those who dehumanize people. | H45: WEF Davos 2025 | I45: 2025-01-23 | J45: Davos · Speech | K45: TRUE | L45: ok. Quizás unificaría con #42 | N45: no, overcoding
A46: 44 | B46: D1.1 | C46: Sustainability as Ideological or Harmful | D46: D1.1 — State Intervention & Governance | E46: Sustainability as Ideological or Harmful | F46: But once again, wokeism has managed to pervert this fundamental idea. From preserving the environment for human enjoyment, we have shifted to a fanatical environmentalism, where we humans are seen as a cancer that must be eradicated and economic development is considered little more than a crime against nature. | G46: "Economic development is considered a crime against nature" reframes climate regulation as anti-development ideology. Particularly effective for the Global South dimension: if climate governance criminalizes development, it condemns poor countries to permanent underdevelopment in the name of ideology. | H46: WEF Davos 2025 | I46: 2025-01-23 | J46: Davos · Speech | K46: TRUE | L46: ok | N46: ok
... A54: 52 | B54: D1.3 | C54: Civilizational Defense | D54: D1.3 — Cultural Backlash | E54: Civilizational Defense | F54: And this organization, along with the most influential supranational bodies, have been the ideologues of this barbarity. Multilateral lending organizations have been instruments of extortion, while many national governments, and especially the European Union, have acted as their armed wing. | G54: "Worship of a sinister and murderous ideology, as if it were a golden calf" elevates the stakes to civilizational-religious dimensions. The WEF-led governance consensus — including its climate architecture — is not an error but an idolatry that must be dismantled to save Western civilization. Civilizational_Defense at maximum intensity. | H54: WEF Davos 2025 | I54: 2025-01-23 | J54: Davos · Speech | K54: TRUE | L54: Dimensión D1.3 OK. VER sub-dimensión. Similar a ID #27 | N54: Ver subdimension
A55: 53 | B55: D1.1 | C55: Market Primacy | D55: D1.1 — State Intervention & Governance | E55: Market Primacy | F55: The only thing such intervention achieves is the creation of new distortions within the price system, which in turn hinders economic calculation, savings and investment — ultimately leading to even more poverty in its wake or a mesh of abhorrent regulations, such as is the case in Europe, which kills economic growth. | G55: The denial of market failures restated verbatim from Davos 2024, now anchored to European climate regulation as the exemplary case of "abhorrent regulations that kill economic growth." The EU's climate regulatory architecture (ETS, CBAM, Fit for 55) is the world's most ambitious; naming it as evidence for the No_Market_Failures thesis directly targets the leading model of climate governance as proof that climate regulation causes poverty. | H55: WEF Davos 2025 | I55: 2025-01-23 | J55: Davos · Speech | K55: TRUE | L55: ok
A56: 54 | B56: D1.1 | C56: Deregulation Benefits | D56: D1.1 — State Intervention & Governance | E56: Deregulation Benefits | F56: The only thing such intervention achieves is the creation of new distortions within the price system, which in turn hinders economic calculation, savings and investment — ultimately leading to even more poverty in its wake or a mesh of abhorrent regulations, such as is the case in Europe, which kills economic growth. | G56: The positive deregulation argument paired with the Europe case: removing climate regulation restores economic calculation, investment, and growth. "Such as is the case in Europe, which kills economic growth" — Deregulation_Benefits applied to climate regulation specifically, with the EU's climate architecture as empirical evidence. | H56: WEF Davos 2025 | I56: 2025-01-23 | J56: Davos · Speech | K56: TRUE | L56: ok
A57: 55 | B57: D1.1 | C57: Rejection of Multilateral Governance | D57: D1.1 — State Intervention & Governance | E57: Rejection of Multilateral Governance | F57: Not only in each of our countries, but also the drastic reduction of all supranational organizations, as this is the only way to root out this perverse system, draining its resources in order to give back to taxpayers what belongs to them, and to put an end to the sale of favours. | G57: [V3 re-code — was D2.3 in v2] "Drastic reduction of all supranational organizations" and "draining its resources" — this passage is here coded D1.1 > Rejection_of_Multilateral_Governance because the speech is performing a rhetorical act: declaring a policy prescription and framing it as ideologically necessary. The actual institutional actions (funding reductions, withdrawal from bodies, defunding climate funds) are D2 evidence to be found in Corpus B. The prescriptive force of the passage does not change its discursive nature. | H57: WEF Davos 2025 | I57: 2025-01-23 | J57: Davos · Speech | K57: TRUE | L57: ok. Destacable
A58: 56 | B58: D1.3 | C58: Neo-Marxism | D58: D1.3 — Cultural Backlash | E58: Neo-Marxism | F58: Not only in each of our countries, but also the drastic reduction of all supranational organizations, as this is the only way to root out this perverse system, draining its resources in order to give back to taxpayers what belongs to them, and to put an end to the sale of favours. | G58: "Wokism is nothing more than a systematic plan by the party of the state to justify state intervention" explicitly articulates the Neo_Marxism thesis for the entire woke project — including its environmental dimension: the climate agenda is a state-expansion pretext. The logical consequent is direct: drastic state reduction (including of climate institutions) is the necessary response. | H58: WEF Davos 2025 | I58: 2025-01-23 | J58: Davos · Speech | K58: TRUE | L58: ok
A59: 57 | B59: D1.1 | C59: Delegitimization of Regulation | D59: D1.1 — State Intervention & Governance | E59: Delegitimization of Regulation | F59: The functions of the state must once again be limited to defending the right to life, liberty and property. Any other function the state assumes will come at the expense of its fundamental role and will inevitably lead to the 'omnipresent Leviathan' that we all suffer under today. | G59: The minimal-state prescriptive principle categorically excludes environmental regulation as a legitimate state function. Climate policy in all its forms — carbon pricing, emissions regulation, environmental ministries, adaptation planning, clean energy mandates — falls outside life, liberty, and property, making it constitutionally illegitimate regardless of empirical merits. This is Delegitimization_of_Regulation stated as a first-principles categorical exclusion. | H59: WEF Davos 2025 | I59: 2025-01-23 | J59: Davos · Speech | K59: TRUE | L59: ok
A60: 58 | B60: D1.1 | C60: Rejection of Multilateral Governance | D60: D1.1 — State Intervention & Governance | E60: Rejection of Multilateral Governance | F60: Sin embargo, advertí que la ONU se había alejado de su norte en las últimas décadas. El exitoso modelo de Naciones Unidas que hablaba de la necesidad de paz sin victoria y que se fundaba en la cooperación de los Estados-Nación se vio reemplazado por un modelo de gobierno supranacional de burócratas internacionales que buscan imponerles a los ciudadanos del mundo un modo de vivir determinado. Así es como pasamos de una organización que pretendía mediar la paz entre pares a una organización que pretende decidir no solo qué debe hacer cada Estado o Nación, sino también cada uno de los individuos en las distintas latitudes del planeta. | G60: The critique of the UN's transformation from a peace-mediation body to a "supranational government of international bureaucrats" directly targets the institutional architecture through which climate governance operates. UNFCCC, SDG framework, and Paris Agreement all require exactly the kind of normative prescription ("what each state must do, what each individual must do") that Milei characterizes as illegitimate overreach. "Modo de vivir determinado" positions climate NDCs and energy transition requirements as externally imposed lifestyle dictates rather than voluntary multilateral cooperation. | H60: UN General Assembly 80th | I60: 2025-09-24 | J60: New York · Speech | K60: TRUE
A61: 59 | B61: D1.2 | C61: Attack on Experts & Technocrats | D61: D1.2 — Public Science & Expertise | E61: Attack on Experts & Technocrats | F61: Sin embargo, advertí que la ONU se había alejado de su norte en las últimas décadas. El exitoso modelo de Naciones Unidas que hablaba de la necesidad de paz sin victoria y que se fundaba en la cooperación de los Estados-Nación se vio reemplazado por un modelo de gobierno supranacional de burócratas internacionales que buscan imponerles a los ciudadanos del mundo un modo de vivir determinado. Así es como pasamos de una organización que pretendía mediar la paz entre pares a una organización que pretende decidir no solo qué debe hacer cada Estado o Nación, sino también cada uno de los individuos en las distintas latitudes del planeta. | G61: "Burócratas internacionales" is the recurring personification of international governance expertise: UN climate secretariat staff, IPCC working group members, and sustainability agency personnel are "bureaucrats who impose rather than advise," denied legitimacy as technical mediators and recast as political actors pursuing their own agenda. | H61: UN General Assembly 80th | I61: 2025-09-24 | J61: New York · Speech | K61: TRUE
A62: 60 | B62: D1.1 | C62: Rejection of Multilateral Governance | D62: D1.1 — State Intervention & Governance | E62: Rejection of Multilateral Governance | F62: Nosotros creemos en el fin original de este organismo. Creemos que existen problemas globales que requieren del diálogo y la cooperación internacional para ser resueltos. Pero para eso debemos rechazar estas extralimitaciones que a menudo acompañan a las agendas nobles. Como sostuvimos el año pasado, no acompañaremos nunca el cercenamiento de libertades individuales, comerciales, ni la violación de los derechos naturales de los ciudadanos de los Estados miembros; y, durante el último año y medio, hemos votado en consecuencia. | G62: [V3 re-code — was D2.3 in v2] "Durante el último año y medio, hemos votado en consecuencia" is here coded as D1.1 > Rejection_of_Multilateral_Governance because this is a rhetorical act — Milei is legitimizing and affirming Argentina's principled opposition to multilateral governance overreach. The statement performs the discursive work of framing Argentina's voting behavior as ideologically consistent and morally obligatory. The voting record itself (actual votes cast at UN bodies) is the D2 institutional evidence in Corpus B. Note that the concession opening ("We believe in the original purpose of this organization") is an inoculation move — acknowledging legitimate multilateral cooperation before rejecting its current form. | H62: UN General Assembly 80th | I62: 2025-09-24 | J62: New York · Speech | K62: TRUE
A63: 61 | B63: IND | C63: Temporal Appropriation | D63: Inductive | E63: Temporal Appropriation | F63: Así, los Estados contemporáneos han entrado en una dinámica donde el interés del político siempre será sacrificar el futuro en el altar del presente porque consumir el capital acumulado genera bienestar momentáneo y ese bienestar momentáneo genera votos. | G63: "Incendian el futuro para mantener caliente el presente" is the central rhetorical move of the entire speech: intergenerational responsibility language — the moral foundation of sustainability discourse — is co-opted and directed against the 2030 Agenda and the multilateral governance apparatus. Milei appropriates the sustainability regime's own vocabulary (futurity, sacrifice-of-present, protecting future generations) and turns it against sustainability governance itself: the bureaucrats and agencies of the 2030 Agenda are the ones sacrificing the future for present bureaucratic comfort. This is the clearest and most fully developed Temporal_Appropriation instance in the corpus. | H63: UN General Assembly 80th | I63: 2025-09-24 | J63: New York · Speech | K63: TRUE | L63: I will change it to D1.1. "Anti-State / Anti-Bureaucratic"or D1.2. "Attacks on experts and technocratic elites" as is a direct attack on politicians' capability to coordinate
A64: 62 | B64: D1.2 | C64: Attack on Experts & Technocrats | D64: D1.2 — Public Science & Expertise | E64: Attack on Experts & Technocrats | F64: Con el correr de los años esta organización ha ido adquiriendo funciones ajenas a su espíritu fundacional. Ha ido creando capas sobre capa de organismos, agencias y programas hasta alcanzar una hipertrofia de administraciones que son poco efectivas a la hora de resolver los problemas para los cuales fueron creadas. Así se engrosan las responsabilidades de la ONU, se engrosan los aportes recibidos por parte de las Naciones miembro y se redujeron los resultados palpables que esta organización tenía para ofrecerle al mundo. | G64: "Hipertrofia de administraciones que son poco efectivas" characterizes the proliferation of UN agencies and programs as bureaucratic bloat producing poor results. UNEP, UNFCCC secretariat, IPCC, and SDG-linked programs are implicitly included in the indictment. If the agencies fail despite growing resources, the experts guiding them are not competent. | H64: UN General Assembly 80th | I64: 2025-09-24 | J64: New York · Speech | K64: TRUE | L64: NO. I will go either with ID #63 "Anti-state / anti-bureaucratic" or D1.1. "Rejection of multilateral governance.". No hace un ataque ni mención directas a sustainability institutions
A65: 63 | B65: D1.1 | C65: Anti-State / Anti-Bureaucratic | D65: D1.1 — State Intervention & Governance | E65: Anti-State / Anti-Bureaucratic | F65: Con el correr de los años esta organización ha ido adquiriendo funciones ajenas a su espíritu fundacional. Ha ido creando capas sobre capa de organismos, agencias y programas hasta alcanzar una hipertrofia de administraciones que son poco efectivas a la hora de resolver los problemas para los cuales fueron creadas. Así se engrosan las responsabilidades de la ONU, se engrosan los aportes recibidos por parte de las Naciones miembro y se redujeron los resultados palpables que esta organización tenía para ofrecerle al mundo. | G65: "Capas sobre capa de organismos, agencias y programas" applies the domestic anti-bureaucratic critique at the international level: the UN sustainability architecture is presented as the supranational equivalent of the Argentine administrative bloat Milei is dismantling domestically. This normalizes drastic reduction of the multilateral sustainability apparatus as rational efficiency reform — not political hostility to climate governance but consistent application of anti-bureaucratic logic. | H65: UN General Assembly 80th | I65: 2025-09-24 | J65: New York · Speech | K65: TRUE | L65: OK. ver #62
A66: 64 | B66: D1.1 | C66: Sustainability as Ideological or Harmful | D66: D1.1 — State Intervention & Governance | E66: Sustainability as Ideological or Harmful | F66: A este cóctel de incentivos cruzados se le suma que, a diferencia de los primeros mandatarios nacionales, las organizaciones internacionales nadie rinde verdaderamente cuentas por fallar en la resolución de un problema. Sin ir más lejos, los malos resultados de la Agenda 2030 dan testimonio de esto que describo. Lo que persiste en la práctica es un ciclo de estructuras que se reciclan, recursos que se multiplican y metas que se reprograman. Por esta razón, la Argentina decidió en su momento apartarse de este proceso porque veíamos en esta agenda un mal gasto de recursos escasos, con fines que no compartíamos y con el efecto de distraer la atención de las dificultades reales de un mundo encaminado al estancamiento. | G66: "Malos resultados de la Agenda 2030" performs a consequentialist delegitimation: the sustainability framework has failed its own stated objectives. "Estructuras que se reciclan, recursos que se multiplican y metas que se reprograman" is a devastating characterization of SDG governance as self-perpetuating institutional inertia. "Distraer la atención de las dificultades reales" frames sustainability governance as an opportunity cost — absorbing scarce resources from pressing problems. This is Sustainability_as_Ideological_or_Harmful in its consequentialist register: not that the agenda is socialist per se, but that it wastes resources and obscures real needs. | H66: UN General Assembly 80th | I66: 2025-09-24 | J66: New York · Speech | K66: TRUE | L66: ok
A67: 65 | B67: D1.1 | C67: Rejection of Multilateral Governance | D67: D1.1 — State Intervention & Governance | E67: Rejection of Multilateral Governance | F67: A este cóctel de incentivos cruzados se le suma que, a diferencia de los primeros mandatarios nacionales, las organizaciones internacionales nadie rinde verdaderamente cuentas por fallar en la resolución de un problema. Sin ir más lejos, los malos resultados de la Agenda 2030 dan testimonio de esto que describo. Lo que persiste en la práctica es un ciclo de estructuras que se reciclan, recursos que se multiplican y metas que se reprograman. Por esta razón, la Argentina decidió en su momento apartarse de este proceso porque veíamos en esta agenda un mal gasto de recursos escasos, con fines que no compartíamos y con el efecto de distraer la atención de las dificultades reales de un mundo encaminado al estancamiento. | G67: [V3 re-code — was D2.3 in v2] "La Argentina decidió en su momento apartarse de este proceso" is here coded D1.1 > Rejection_of_Multilateral_Governance. The speech is performing the discursive work of justifying and legitimizing Argentina's exit from the 2030 Agenda process — framing it as principled, rational, and sovereign. The rhetorical rationale (bad results, wrong goals, opportunity cost) is the D1 content. The formal institutional act (official communication to UN bodies, executive decree if any) is the D2 evidence to be sought in Corpus B. | H67: UN General Assembly 80th | I67: 2025-09-24 | J67: New York · Speech | K67: TRUE | L67: ok. Opcional
A68: 66 | B68: IND | C68: Temporal Appropriation | D68: Inductive | E68: Temporal Appropriation | F68: A este cóctel de incentivos cruzados se le suma que, a diferencia de los primeros mandatarios nacionales, las organizaciones internacionales nadie rinde verdaderamente cuentas por fallar en la resolución de un problema. Sin ir más lejos, los malos resultados de la Agenda 2030 dan testimonio de esto que describo. Lo que persiste en la práctica es un ciclo de estructuras que se reciclan, recursos que se multiplican y metas que se reprograman. Por esta razón, la Argentina decidió en su momento apartarse de este proceso porque veíamos en esta agenda un mal gasto de recursos escasos, con fines que no compartíamos y con el efecto de distraer la atención de las dificultades reales de un mundo encaminado al estancamiento. | G68: "Un mal gasto de recursos escasos" used to justify exiting the 2030 Agenda completes the Temporal_Appropriation move: the framework tasked with protecting future generations is reframed as the actor wasting the scarce resources that future generations will need. The same intergenerational moral vocabulary that launched the speech ("incendian el futuro") is now applied to delegitimize the 2030 Agenda as itself guilty of sacrificing future welfare. | H68: UN General Assembly 80th | I68: 2025-09-24 | J68: New York · Speech | K68: TRUE | L68: NO. Eliminar.
A69: 67 | B69: D1.3 | C69: Civilizational Defense | D69: D1.3 — Cultural Backlash | E69: Civilizational Defense | F69: No somos, sin embargo, los únicos que estamos tomando las decisiones difíciles que este momento histórico demanda. El Presidente Trump, en Estados Unidos, también entiende que es el momento de revertir una dinámica que estaba llevando a Estados Unidos a una catástrofe. Entiende que debe hacer lo necesario, aunque a muchos no les guste. | G69: The invocation of Trump as co-protagonist in "the decisions this historical moment demands" elevates the obstruction of multilateral sustainability governance to a coordinated civilizational project. The U.S.-Argentina alignment — both having defected from or undermined multilateral climate commitments — is framed as a deliberate civilizational intervention against a catastrophic trajectory, not bilateral political alignment. | H69: UN General Assembly 80th | I69: 2025-09-24 | J69: New York · Speech | K69: TRUE | L69: VER. Parte de D1.3 seguro
A70: 68 | B70: D1.1 | C70: Rejection of Multilateral Governance | D70: D1.1 — State Intervention & Governance | E70: Rejection of Multilateral Governance | F70: 1. Principio del mandato esencial. La misión central de la ONU es preservar la paz y la seguridad internacional, todo lo demás debe concebirse como complementario a ese fin. 2. Principio de subsidiariedad internacional. La ONU debería intervenir sobre un tema únicamente cuando sea evidente que el problema excede de manera demostrable las capacidades de acción nacional; en todos los demás casos corresponde devolver la iniciativa a los Estados. 3. Principio de diligencia institucional. Eso implica la realización de auditorías confiables, el cierre de programas ineficaces, la consolidación de agencias únicas y un financiamiento condicionado a resultados verificables. 4. Principio de simplificación y racionalización normativa. Solo debemos apoyar iniciativas que no restrinjan la capacidad de los Estados de liberar sus fuerzas productivas, atraer inversión y fomentar el comercio. | G70: [V3 re-code — was split D2.2 + D1.1 in v2] The four principles constitute a comprehensive institutional redesign proposal that strips the UN of its sustainability governance function: Principle 1 (peace/security only) excludes SDGs and climate action from legitimate UN mandates; Principle 2 (subsidiarity) removes the binding character of international climate commitments by making all sustainability governance contingent on national voluntary adoption; Principle 4 (no restrictions on productive forces) would prohibit carbon pricing and emissions regulation categorically. This is coded entirely as D1.1 > Rejection_of_Multilateral_Governance in v3 because the speech is making a rhetorical proposal — arguing for an institutional redesign. The actual institutional acts required to implement these principles (treaty amendments, funding reductions, agency closures) belong in Corpus B. | H70: UN General Assembly 80th | I70: 2025-09-24 | J70: New York · Speech | K70: TRUE | L70: VER. Eliminar o integrar con #70
A71: 69 | B71: D1.1 | C71: Deregulation Benefits | D71: D1.1 — State Intervention & Governance | E71: Deregulation Benefits | F71: 1. Principio del mandato esencial. La misión central de la ONU es preservar la paz y la seguridad internacional, todo lo demás debe concebirse como complementario a ese fin. 2. Principio de subsidiariedad internacional. La ONU debería intervenir sobre un tema únicamente cuando sea evidente que el problema excede de manera demostrable las capacidades de acción nacional; en todos los demás casos corresponde devolver la iniciativa a los Estados. 3. Principio de diligencia institucional. Eso implica la realización de auditorías confiables, el cierre de programas ineficaces, la consolidación de agencias únicas y un financiamiento condicionado a resultados verificables. 4. Principio de simplificación y racionalización normativa. Solo debemos apoyar iniciativas que no restrinjan la capacidad de los Estados de liberar sus fuerzas productivas, atraer inversión y fomentar el comercio. | G71: Principle 4 — "solo debemos apoyar iniciativas que no restrinjan la capacidad de los Estados de liberar sus fuerzas productivas, atraer inversión y fomentar el comercio" — frames deregulation as the positive prescription for international governance. Removing environmental and social standards from trade and investment conditions is framed as generating growth more effectively than climate programs. Proposed as a constitutional principle for international governance. | H71: UN General Assembly 80th | I71: 2025-09-24 | J71: New York · Speech | K71: TRUE | L71: ok
A72: 70 | B72: D1.1 | C72: Anti-State / Anti-Bureaucratic | D72: D1.1 — State Intervention & Governance | E72: Anti-State / Anti-Bureaucratic | F72: 1. Principio del mandato esencial. La misión central de la ONU es preservar la paz y la seguridad internacional, todo lo demás debe concebirse como complementario a ese fin. 2. Principio de subsidiariedad internacional. La ONU debería intervenir sobre un tema únicamente cuando sea evidente que el problema excede de manera demostrable las capacidades de acción nacional; en todos los demás casos corresponde devolver la iniciativa a los Estados. 3. Principio de diligencia institucional. Eso implica la realización de auditorías confiables, el cierre de programas ineficaces, la consolidación de agencias únicas y un financiamiento condicionado a resultados verificables. 4. Principio de simplificación y racionalización normativa. Solo debemos apoyar iniciativas que no restrinjan la capacidad de los Estados de liberar sus fuerzas productivas, atraer inversión y fomentar el comercio. | G72: Principle 3 — "cierre de programas ineficaces, consolidación de agencias únicas" — is the anti-bureaucratic argument applied at the international institutional level. Milei explicitly parallels this to his domestic restructuring, framing international agency consolidation as the same rational efficiency logic: wasteful bureaucracy must be eliminated wherever it exists, domestic or international. | H72: UN General Assembly 80th | I72: 2025-09-24 | J72: New York · Speech | K72: TRUE | L72: ok
A73: 71 | B73: D1.1 | C73: Market Primacy | D73: D1.1 — State Intervention & Governance | E73: Market Primacy | F73: Therefore, the opposition between the dimensions of efficiency and justice is false and erroneous. That is to say, what is just can't be inefficient, nor can what is efficient be unjust. Actually, from the standpoint of dynamic analysis, justice and efficiency are two sides of the same coin. | G73: The Huerta de Soto dynamic efficiency argument performs a foundational move for Market_Primacy: it collapses the efficiency-justice distinction that underpins much environmental economics. In standard welfare economics, a carbon tax may be efficient (correcting an externality) while raising distributional concerns (justice). Milei's framework eliminates this tradeoff by definitional fiat: what is just (private property, voluntary exchange) is by definition efficient, and what is efficient cannot be unjust. This forecloses the standard case for environmental regulation — that a market failure produces an outcome both inefficient and unjust that state intervention can improve. | H73: WEF Davos 2026 | I73: 2026-01-22 | J73: Davos · Speech | K73: TRUE | L73: OK. Opcional. Podría ser eliminado para no sobrecodear.
A74: 72 | B74: D1.1 | C74: Delegitimization of Regulation | D74: D1.1 — State Intervention & Governance | E74: Delegitimization of Regulation | F74: However, this required embracing a mathematical structure that left the door open to state intervention under the well-intentioned goal of correcting market failures, which, from my perspective, do not really exist. To address this, the proof developed by Hans-Hermann Hoppe, based on property rights in line with Locke's principle of original appropriation together with the non-aggression principle, not only proves satisfactory in establishing optimality, but also leaves no room for intervention. | G74: The Hoppe property-rights proof is invoked to argue that the neoclassical framework "leaves the door open to state intervention" through the market failure concept, and that the correct theoretical framework (Lockean property rights + non-aggression principle) "leaves no room for intervention." For climate governance, this is the most philosophically grounded version of the Delegitimization_of_Regulation argument: the entire framework justifying carbon pricing and emissions regulation is replaced by a rival framework in which intervention is not merely inadvisable but logically prohibited by natural law. | H74: WEF Davos 2026 | I74: 2026-01-22 | J74: Davos · Speech | K74: TRUE | L74: ok. Podría ser destacable (por ser foundational)
... A78: 76 | B78: D1.1 | C78: Deregulation Benefits | D78: D1.1 — State Intervention & Governance | E78: Deregulation Benefits | F78: Note that along the same lines, we can also address the issue of artificial intelligence. Therefore, the most responsible thing states can do regarding this issue is to stop pestering those who are creating a better world. | G78: "The most responsible thing states can do is to stop pestering those who are creating a better world" — deregulation prescription applied to AI, but the logic is explicitly general and applies identically to climate technology (clean energy, carbon capture, EVs). The "pestering" metaphor diminishes regulatory intervention as petty harassment of innovators rather than legitimate public policy, pre-empting any case for green industrial mandates, technology standards, or innovation requirements. | H78: WEF Davos 2026 | I78: 2026-01-22 | J78: Davos · Speech | K78: TRUE | L78: ok
A79: 77 | B79: D1.3 | C79: Civilizational Defense | D79: D1.3 — Cultural Backlash | E79: Civilizational Defense | F79: However, 2026 is the year in which I bring you good news. The world has begun to awaken. The best proof of this is what is happening in the Americas with the rebirth of the ideas of liberty. Therefore, the Americas will be the beacon of light that will once again illuminate the entire West, thereby repaying the civilizational debt with expressions of gratitude towards the foundations in Greek philosophy, Roman law and Judeo-Christian values. | G79: The three-year Davos arc (2024: West in danger; 2025: battle not yet won; 2026: world awakening) is consolidated into a progressive civilizational recovery narrative. Climate governance — previously identified with "wokeism in its most hypocritical form" — is implicitly receding along with the broader woke project. The "Americas as beacon of light" framing positions the U.S.-Argentina axis (both having defected from multilateral climate commitments) as the civilizational vanguard, normalizing climate obstruction as the leading edge of Western renewal. The Judeo-Christian values reference grounds the civilization in religious tradition, raising the moral stakes beyond policy disagreement. | H79: WEF Davos 2026 | I79: 2026-01-22 | J79: Davos · Speech | K79: TRUE
A80: 78 | B80: D1.2 | C80: Attack on Universities | D80: D1.2 — Public Science & Expertise | E80: Attack on Universities | F80: En el plano de la Educación Superior, la creación de universidades se ha convertido en un negocio más de la política y en los profesorados e institutos de formación inicial de docentes se imparte, cada vez más, adoctrinamiento político, en lugar de educación. | G80: Milei frames teacher-training colleges and universities as sites of "political indoctrination" rather than education, attacking the epistemic infrastructure that produces Argentina's scientific and professional classes. This delegitimizes the knowledge-producing institutions most responsible for environmental and sustainability expertise, positioning academic education as a captured ideological project rather than a reliable source of expertise for policymaking. The move is structural rather than specific: it does not name individual environmental scholars but pathologizes the institutional culture from which climate-relevant expertise emerges. | H80: Apertura 142 (2024) | I80: 2024-03-01 | J80: Buenos Aires · Apertura | K80: TRUE | L80: ok
A81: 79 | B81: D1.1 | C81: Anti-Casta (Elite Frame) | D81: D1.1 — State Intervention & Governance | E81: Anti-Casta (Elite Frame) | F81: Tras haber visto con mis propios ojos y en detalle la vulgaridad del despilfarro con el que la política se acostumbró a vivir, ratifico una vez más que la casta política es lo peor que le puede pasar a un país como el nuestro. | G81: Milei confirms and intensifies the "la casta" frame as the foundational political category of his governing project. This is the first explicit formalization of the casta indictment in a presidential address, establishing the frame that will subsequently be applied to environmental agencies, sustainability technocrats, and international governance bodies. When this same anti-casta rhetoric is deployed later against CONICET, the Ministry of Environment, or multilateral climate bodies, its legitimating logic has been institutionalized here in the opening address of his presidency. | H81: Apertura 142 (2024) | I81: 2024-03-01 | J81: Buenos Aires · Apertura | K81: TRUE | L81: ok
A82: 80 | B82: D1.1 | C82: Deregulation Benefits | D82: D1.1 — State Intervention & Governance | E82: Deregulation Benefits | F82: Por último, también firmamos un mega Decreto de Necesidad y Urgencia para, por primera vez en décadas, devolverles la libertad a los argentinos en vez de quitárselas con regulaciones sin sentido. | G82: The DNU 70/23 -- framed here as "returning freedom" to Argentines -- included the derogation of dozens of environmental and land-use regulations, alongside broader economic deregulation. By presenting the entire deregulatory package as "freedom from senseless regulations," Milei establishes the foundational rhetorical move that makes environmental regulation categorically illegitimate: not harmful to growth per se, but a deprivation of liberty. The positive framing ("returning freedom") is analytically central -- it does not argue against regulations on techno-economic grounds but on moral-liberty grounds. | H82: Apertura 142 (2024) | I82: 2024-03-01 | J82: Buenos Aires · Apertura | K82: TRUE | L82: lo eliminaría
A83: 81 | B83: D1.1 | C83: Delegitimization of Regulation | D83: D1.1 — State Intervention & Governance | E83: Delegitimization of Regulation | F83: Por último, también firmamos un mega Decreto de Necesidad y Urgencia para, por primera vez en décadas, devolverles la libertad a los argentinos en vez de quitárselas con regulaciones sin sentido. | G83: The phrase "regulaciones sin sentido" does categorical ideological work: it asserts that regulations as a class are senseless, without needing to evaluate any specific regulation's rationale. This is not a technocratic critique but an a priori dismissal -- the state's power to regulate is itself illegitimate. Environmental and sustainability regulations, which depend on public justification of market failures and externalities, are pre-emptively categorized as "senseless" by this framing, before any specific environmental case can be made. | H83: Apertura 142 (2024) | I83: 2024-03-01 | J83: Buenos Aires · Apertura | K83: TRUE | L83: ok
A84: 82 | B84: D1.1 | C84: Anti-State / Anti-Bureaucratic | D84: D1.1 — State Intervention & Governance | E84: Anti-State / Anti-Bureaucratic | F84: Eliminamos cajas de militancia como el INCAA, el INADI, el Ministerio de la Mujer y Télam y volvimos superavitarias empresas emblemáticas de la militancia deficitaria, como Aerolíneas Argentinas, AySA, Intercargo y ENARSA. (...) mientras empezamos a dar los primeros pasos para la privatización de todas las empresas públicas, porque entendemos que el Estado no está para reemplazar al empresario. | G84: The explicit grouping of INCAA, INADI, and the Ministerio de la Mujer as "cajas de militancia" establishes the rhetorical pattern of labeling progressive-adjacent state institutions as corrupt political patronage rather than legitimate public functions. INADI and the women's ministry represent precisely the kind of social-regulatory institutions that also administer environmental and sustainability policy -- agencies whose authority rests on normative social science rather than market metrics. Categorizing them as inherently militant/patronage-driven pre-emptively applies the same frame to environmental agencies. | H84: Apertura 143 (2025) | I84: 2025-03-01 | J84: Buenos Aires · Apertura | K84: TRUE | L84: lo eliminaría
A85: 83 | B85: D1.1 | C85: Market Primacy | D85: D1.1 — State Intervention & Governance | E85: Market Primacy | F85: Además, eliminamos la obra pública --que era uno de los curros más grandes de la política--. [...] la obra pública no genera trabajo, la obra pública genera impuestos. | G85: The sustained argument that public works are a net economic negative because they crowd out private spending is a classic market-primacy move with direct implications for climate governance. Climate transition policy relies substantially on public investment -- green infrastructure, renewable energy buildout, adaptation works. By asserting categorically that public investment destroys value rather than creating it, this passage delegitimizes the economic logic of public climate investment before any specific environmental case can be made. The framing also pathologizes public expenditure on infrastructure as inherently corrupt ("curro de la política"), making it politically toxic for future governments to justify green public investment. | H85: Apertura 143 (2025) | I85: 2025-03-01 | J85: Buenos Aires · Apertura | K85: TRUE | L85: ok categoría D1.1. También puede ser "delegitimation of regulation"
A86: 84 | B86: D1.1 | C86: Deregulation Benefits | D86: D1.1 — State Intervention & Governance | E86: Deregulation Benefits | F86: hemos concentrado alrededor y concretado 1700 reformas estructurales, eliminando regulaciones que cercenaban libertades comerciales y económicas y le ponían palos en la rueda al gran motor productivo de nuestro país, que es el sector privado. | G86: The "1700 structural reforms" figure is presented as the central achievement of the first year, with deregulation framed as "removing sticks from the wheels" of the productive sector. The institutionalization of a dedicated "Ministro de Desregulación" makes deregulation a permanent administrative function of the state, not a one-time corrective. This is significant for climate governance because environmental regulations constitute a substantial portion of the regulatory corpus being dismantled; the weight-of-paper metaphor trivializes regulatory content by reducing regulations to their bureaucratic bulk rather than their protective function. | H86: Apertura 143 (2025) | I86: 2025-03-01 | J86: Buenos Aires · Apertura | K86: TRUE | L86: ok
A87: 85 | B87: D1.1 | C87: Deregulation Benefits | D87: D1.1 — State Intervention & Governance | E87: Deregulation Benefits | F87: No es menor lo de Elon con la motosierra. La motosierra, hoy, es un símbolo de cambio de época y el inicio de una nueva era dorada para la humanidad, pero esta vez, en vez de ir a contramano del mundo, Argentina está a la vanguardia del mundo. | G87: The explicit alignment of Milei's chainsaw symbol with Elon Musk's DOGE deregulatory operation is a transnational validation move: it frames the anti-regulatory revolution as a global historical trend ("a new golden era for humanity") in which Argentina is the vanguard. This is significant for climate governance because both DOGE and Milei's deregulatory agenda specifically targeted environmental agencies and regulations. The "new golden era" framing positions environmental deregulation not as a contested political choice but as the natural direction of history -- a form of temporal determinism that makes resistance to deregulation appear backward. | H87: Apertura 143 (2025) | I87: 2025-03-01 | J87: Buenos Aires · Apertura | K87: TRUE | L87: ok
A88: 86 | B88: D1.1 | C88: Rejection of Multilateral Governance | D88: D1.1 — State Intervention & Governance | E88: Rejection of Multilateral Governance | F88: es necesario estar dispuesto a flexibilizar o, incluso, llegado el caso, a salir del Mercosur, que lo único que logró desde su creación es enriquecer a los grandes industriales brasileros a costa de empobrecer a los argentinos. | G88: The willingness to exit Mercosur -- a major regional multilateral governance framework -- is framed as a necessary condition for national prosperity. Mercosur's institutional architecture includes environmental and sustainability chapters, and its relationship with the EU (being negotiated at this time) involved environmental conditionality. By treating Mercosur exit as a legitimate policy option and framing multilateral economic integration as inherently enriching other countries at Argentina's expense, Milei extends the rejection-of-multilateral-governance logic from the climate domain (2030 Agenda, IPCC) to the broader institutional architecture of regional governance. | H88: Apertura 143 (2025) | I88: 2025-03-01 | J88: Buenos Aires · Apertura | K88: TRUE | L88: puede ser
A89: 87 | B89: D1.3 | C89: Woke Bundling | D89: D1.3 — Cultural Backlash | E89: Woke Bundling | F89: tenemos que recuperar el imperio de la igualdad ante la ley, terminando con este sistema de cupos de distinto tipo que impone desde a quién emplear hasta a quién votar. Hemos llegado al punto en el que hay cupos hasta para emplear gente en medios de comunicación o para la programación de artistas en un festival. | G89: The grouping of employment quotas (gender, diversity), media programming quotas, and electoral quotas under a single "equality-before-the-law" critique performs ideological bundling: it treats affirmative representation mechanisms as a unified progressive excess. The phrase "ciertos grupos percibidos como oprimidos" explicitly frames identity-based policy as based on perception rather than material reality -- the same epistemic move used to frame climate science as perception-based rather than empirically grounded. The anti-quota framing extends the anti-"woke" frame into public institutions, preparing the terrain for applying the same logic to environmental quotas, emissions targets, and international reporting obligations. | H89: Apertura 143 (2025) | I89: 2025-03-01 | J89: Buenos Aires · Apertura | K89: TRUE | L89: NO. Eliminar. A lo sumo como algo más genérico tipo cultural battle
A90: 88 | B90: D1.3 | C90: Civilizational Defense | D90: D1.3 — Cultural Backlash | E90: Civilizational Defense | F90: en nuestra visión existe un claro orden de mérito. En primer lugar, están la ética y la moral en base a los valores de Occidente. Esto es, la filosofía griega, el derecho romano, la rectitud de los estoicos y los valores judeocristianos. En segundo lugar, ubicamos la eficiencia económica. Y, por último, en tercer lugar, el utilitarismo político. | G90: The explicit ordering of moral values -- Western ethics/morality first, economic efficiency second, political utilitarianism third -- establishes a normative hierarchy in which "Occidente" (Greek philosophy, Roman law, Judeo-Christian values) is the foundational reference for all legitimate policy. Sustainability governance and environmental science, which invoke collective/intergenerational obligations that cut across individual rights, are implicitly subordinate to this Western-individual-rights framework. Climate policy that invokes the 2030 Agenda or IPCC consensus falls outside the "moral" primary category by definition -- it would be classified as "utilitarismo político" at best. | H90: Apertura 144 (2026) | I90: 2026-03-01 | J90: Buenos Aires · Apertura | K90: TRUE | L90: NO. Muy rebuscado. Eliminaría o dejaría general como d1.3. Cultural battle
A91: 89 | B91: D1.1 | C91: Deregulation Benefits | D91: D1.1 — State Intervention & Governance | E91: Deregulation Benefits | F91: El primer pilar es la desregulación de la economía. Esta política de exterminar regulaciones no solo es una forma de restaurar el derecho de propiedad, sino que además libera rendimientos crecientes, los cuales son la base del crecimiento económico. Si no asimilamos este punto, todo lo demás será en vano. | G91: The framing of deregulation as "exterminar regulaciones" -- exterminating rather than reforming regulations -- uses maximalist language that positions the regulatory corpus itself as a hostile entity to be eliminated rather than a governance tool to be calibrated. The positive theoretical claim -- deregulation "liberates increasing returns," which is the basis for economic growth -- forecloses the case for environmental regulation before it can be made: if regulations by definition suppress increasing returns and therefore growth, then environmental regulations are anti-growth by definition, and any empirical case for environmental regulation would be dismissed as theoretically unfounded. | H91: Apertura 144 (2026) | I91: 2026-03-01 | J91: Buenos Aires · Apertura | K91: TRUE | L91: ok
... A100: 98 | B100: D1.1 | C100: Anti-State / Anti-Bureaucratic | D100: D1.1 — State Intervention & Governance | E100: Anti-State / Anti-Bureaucratic | F100: El Estado presente, que pretende hacerse cargo de todos los órdenes de la vida, fracasó. Por eso necesitamos un Estado ágil, abocado a unas pocas funciones esenciales, sintetizadas en la defensa de la vida, la libertad y la propiedad privada, amparado en lo que definimos, como decía Ayn Rand, la ética de la emergencia. | G100: The invocation of Ayn Rand's "ethics of emergency" to justify a minimal state, combined with the claim that any state "that pretends to take care of all dimensions of life" has failed, is a direct repudiation of the regulatory state's legitimacy in the domain of climate governance. Climate governance requires precisely the kind of state that "pretends to take care" of long-range collective problems that markets do not spontaneously resolve. By framing state scope as the cause of failure (rather than specific bad policies), Milei pre-emptively delegitimizes any future government's attempt to use state capacity for environmental management. | H100: Apertura 144 (2026) | I100: 2026-03-01 | J100: Buenos Aires · Apertura | K100: TRUE | L100: OK
A101: SEE | B101: D1.1 | C101: Anti-Casta (Elite Frame) | D101: D1.1 — State Intervention & Governance | F101: Para tener una idea, desde la década del 70 hasta acá el mundo bajó la pobreza del 50% al 10%; y nosotros del 5 la llevamos al 50, una verdadera aberración fruto de la casta política. | G101: The casta is blamed for the past 70 years of economic failures | H101: Apertura 143 (2025) | I101: 2025-03-01 | J101: Buenos Aires · Apertura | K101: FALSE | L101: propuesta
A102: SEE | B102: D1.1 | C102: Anti-State / Anti-Bureaucratic | D102: D1.1 — State Intervention & Governance | F102: Y por qué fallaron todos nuestros intentos de salir. La respuesta es simple: porque siempre se partió desde un diagnóstico equivocado. Nadie nunca cuestionó el eje sobre el que giraba la calesita: la mano negra del Estado omnipresente. Todas las falsas dicotomías de nuestra historia, campo o industria, dólar barato o caro, peronismo o antiperonismo, escondieron atrás la misma constante; y la política siempre defendió al Estado con uñas y dientes, viendo la administración pública como un botín a ser conquistado. Eso es el verdadero modelo de la casta. | G102: The foundational reason why every policy failed was because of the persistent role played by the State | H102: Apertura 143 (2025) | I102: 2025-03-01 | J102: Buenos Aires · Apertura | K102: FALSE | L102: propuesta

Sheet Freq — By Dimension
A1: Code Frequency by Dimension × Speech — values update automatically from 'Coded Passages'
A2: Dimension | B2: Dimension (Full) | C2: Debate Presidencial 2023 | D2: WEF Davos 2024 | E2: UN General Assembly 79th | F2: WEF Davos 2025 | G2: UN General Assembly 80th | H2: WEF Davos 2026 | I2: ='Coded Passages'!H80 -> Apertura 142 (2024) | J2: ='Coded Passages'!H84 -> Apertura 143 (2025) | K2: ='Coded Passages'!H90 -> Apertura 144 (2026) | L2: TOTAL | O2: Dimension | P2: Total
A3: D1.1 | B3: D1.1 — State Intervention & Governance | C3: =COUNTIFS('Coded Passages'!$B:$B,$A3,'Coded Passages'!$H:$H,C$2) -> 1 | D3: =COUNTIFS('Coded Passages'!$B:$B,$A3,'Coded Passages'!$H:$H,D$2) -> 13 | E3: =COUNTIFS('Coded Passages'!$B:$B,$A3,'Coded Passages'!$H:$H,E$2) -> 8 | F3: =COUNTIFS('Coded Passages'!$B:$B,$A3,'Coded Passages'!$H:$H,F$2) -> 7 | G3: =COUNTIFS('Coded Passages'!$B:$B,$A3,'Coded Passages'!$H:$H,G$2) -> 8 | H3: =COUNTIFS('Coded Passages'!$B:$B,$A3,'Coded Passages'!$H:$H,H$2) -> 5 | I3: =COUNTIFS('Coded Passages'!$B:$B,$A3,'Coded Passages'!$H:$H,I$2) -> 3 | J3: =COUNTIFS('Coded Passages'!$B:$B,$A3,'Coded Passages'!$H:$H,J$2) -> 7 | K3: =COUNTIFS('Coded Passages'!$B:$B,$A3,'Coded Passages'!$H:$H,K$2) -> 7 | L3: =SUM(C3:K3) -> 59 | O3: D1.1 | P3: =L3 -> 59 | Q3: =P3/$P$8 -> 0.59
A4: D1.2 | B4: D1.2 — Public Science & Expertise | C4: =COUNTIFS('Coded Passages'!$B:$B,$A4,'Coded Passages'!$H:$H,C$2) -> 2 | D4: =COUNTIFS('Coded Passages'!$B:$B,$A4,'Coded Passages'!$H:$H,D$2) -> 3 | E4: =COUNTIFS('Coded Passages'!$B:$B,$A4,'Coded Passages'!$H:$H,E$2) -> 1 | F4: =COUNTIFS('Coded Passages'!$B:$B,$A4,'Coded Passages'!$H:$H,F$2) -> 5 | G4: =COUNTIFS('Coded Passages'!$B:$B,$A4,'Coded Passages'!$H:$H,G$2) -> 2 | H4: =COUNTIFS('Coded Passages'!$B:$B,$A4,'Coded Passages'!$H:$H,H$2) -> 0 | I4: =COUNTIFS('Coded Passages'!$B:$B,$A4,'Coded Passages'!$H:$H,I$2) -> 1 | J4: =COUNTIFS('Coded Passages'!$B:$B,$A4,'Coded Passages'!$H:$H,J$2) -> 0 | K4: =COUNTIFS('Coded Passages'!$B:$B,$A4,'Coded Passages'!$H:$H,K$2) -> 0 | L4: =SUM(C4:K4) -> 14 | O4: D1.2 | P4: =L4 -> 14 | Q4: =P4/$P$8 -> 0.14
A5: D1.3 | B5: D1.3 — Cultural Backlash | C5: =COUNTIFS('Coded Passages'!$B:$B,$A5,'Coded Passages'!$H:$H,C$2) -> 0 | D5: =COUNTIFS('Coded Passages'!$B:$B,$A5,'Coded Passages'!$H:$H,D$2) -> 3 | E5: =COUNTIFS('Coded Passages'!$B:$B,$A5,'Coded Passages'!$H:$H,E$2) -> 4 | F5: =COUNTIFS('Coded Passages'!$B:$B,$A5,'Coded Passages'!$H:$H,F$2) -> 7 | G5: =COUNTIFS('Coded Passages'!$B:$B,$A5,'Coded Passages'!$H:$H,G$2) -> 1 | H5: =COUNTIFS('Coded Passages'!$B:$B,$A5,'Coded Passages'!$H:$H,H$2) -> 2 | I5: =COUNTIFS('Coded Passages'!$B:$B,$A5,'Coded Passages'!$H:$H,I$2) -> 0 | J5: =COUNTIFS('Coded Passages'!$B:$B,$A5,'Coded Passages'!$H:$H,J$2) -> 1 | K5: =COUNTIFS('Coded Passages'!$B:$B,$A5,'Coded Passages'!$H:$H,K$2) -> 3 | L5: =SUM(C5:K5) -> 21 | O5: D1.3 | P5: =L5 -> 21 | Q5: =P5/$P$8 -> 0.21
A6: IND | B6: Inductive | C6: =COUNTIFS('Coded Passages'!$B:$B,$A6,'Coded Passages'!$H:$H,C$2) -> 1 | D6: =COUNTIFS('Coded Passages'!$B:$B,$A6,'Coded Passages'!$H:$H,D$2) -> 1 | E6: =COUNTIFS('Coded Passages'!$B:$B,$A6,'Coded Passages'!$H:$H,E$2) -> 0 | F6: =COUNTIFS('Coded Passages'!$B:$B,$A6,'Coded Passages'!$H:$H,F$2) -> 1 | G6: =COUNTIFS('Coded Passages'!$B:$B,$A6,'Coded Passages'!$H:$H,G$2) -> 2 | H6: =COUNTIFS('Coded Passages'!$B:$B,$A6,'Coded Passages'!$H:$H,H$2) -> 0 | I6: =COUNTIFS('Coded Passages'!$B:$B,$A6,'Coded Passages'!$H:$H,I$2) -> 0 | J6: =COUNTIFS('Coded Passages'!$B:$B,$A6,'Coded Passages'!$H:$H,J$2) -> 0 | K6: =COUNTIFS('Coded Passages'!$B:$B,$A6,'Coded Passages'!$H:$H,K$2) -> 1 | L6: =SUM(C6:K6) -> 6 | O6: IND | P6: =L6 -> 6 | Q6: =P6/$P$8 -> 0.06
A7: TOTAL | B7: All Dimensions | C7: =SUM(C3:C6) -> 4 | D7: =SUM(D3:D6) -> 20 | E7: =SUM(E3:E6) -> 13 | F7: =SUM(F3:F6) -> 20 | G7: =SUM(G3:G6) -> 13 | H7: =SUM(H3:H6) -> 7 | I7: =SUM(I3:I6) -> 4 | J7: =SUM(J3:J6) -> 8 | ... L7: =SUM(L3:L6) -> 100
O8: TOT | P8: =SUM(P3:P6) -> 100

Sheet Freq — By Sub-code
A1: Code Frequency by Sub-code × Speech — values update automatically from 'Coded Passages'
A2: Dim | B2: Sub-code | C2: Debate Presidencial 2023 | D2: WEF Davos 2024 | E2: UN General Assembly 79th | F2: WEF Davos 2025 | G2: UN General Assembly 80th | H2: WEF Davos 2026 | I2: ='Coded Passages'!H80 -> Apertura 142 (2024) | J2: ='Coded Passages'!H84 -> Apertura 143 (2025) | K2: ='Coded Passages'!H90 -> Apertura 144 (2026) | L2: TOTAL | N2: Sub-code | O2: Total
A3: D1.1 | B3: Anti-Casta (Elite Frame) | C3: =COUNTIFS('Coded Passages'!$B:$B,$A3,'Coded Passages'!$C:$C,$B3,'Coded Passages'!$H:$H,C$2) -> 0 | D3: =COUNTIFS('Coded Passages'!$B:$B,$A3,'Coded Passages'!$C:$C,$B3,'Coded Passages'!$H:$H,D$2) -> 2 | E3: =COUNTIFS('Coded Passages'!$B:$B,$A3,'Coded Passages'!$C:$C,$B3,'Coded Passages'!$H:$H,E$2) -> 0 | F3: =COUNTIFS('Coded Passages'!$B:$B,$A3,'Coded Passages'!$C:$C,$B3,'Coded Passages'!$H:$H,F$2) -> 0 | G3: =COUNTIFS('Coded Passages'!$B:$B,$A3,'Coded Passages'!$C:$C,$B3,'Coded Passages'!$H:$H,G$2) -> 0 | H3: =COUNTIFS('Coded Passages'!$B:$B,$A3,'Coded Passages'!$C:$C,$B3,'Coded Passages'!$H:$H,H$2) -> 0 | I3: =COUNTIFS('Coded Passages'!$B:$B,$A3,'Coded Passages'!$C:$C,$B3,'Coded Passages'!$H:$H,I$2) -> 1 | J3: =COUNTIFS('Coded Passages'!$B:$B,$A3,'Coded Passages'!$C:$C,$B3,'Coded Passages'!$H:$H,J$2) -> 1 | K3: =COUNTIFS('Coded Passages'!$B:$B,$A3,'Coded Passages'!$C:$C,$B3,'Coded Passages'!$H:$H,K$2) -> 1 | L3: =SUM(C3:K3) -> 5 | N3: D1.1·Anti-Casta (Eli | O3: =L3 -> 5
A4: D1.1 | B4: Anti-State / Anti-Bureaucratic | C4: =COUNTIFS('Coded Passages'!$B:$B,$A4,'Coded Passages'!$C:$C,$B4,'Coded Passages'!$H:$H,C$2) -> 0 | D4: =COUNTIFS('Coded Passages'!$B:$B,$A4,'Coded Passages'!$C:$C,$B4,'Coded Passages'!$H:$H,D$2) -> 1 | E4: =COUNTIFS('Coded Passages'!$B:$B,$A4,'Coded Passages'!$C:$C,$B4,'Coded Passages'!$H:$H,E$2) -> 0 | F4: =COUNTIFS('Coded Passages'!$B:$B,$A4,'Coded Passages'!$C:$C,$B4,'Coded Passages'!$H:$H,F$2) -> 0 | G4: =COUNTIFS('Coded Passages'!$B:$B,$A4,'Coded Passages'!$C:$C,$B4,'Coded Passages'!$H:$H,G$2) -> 2 | H4: =COUNTIFS('Coded Passages'!$B:$B,$A4,'Coded Passages'!$C:$C,$B4,'Coded Passages'!$H:$H,H$2) -> 0 | I4: =COUNTIFS('Coded Passages'!$B:$B,$A4,'Coded Passages'!$C:$C,$B4,'Coded Passages'!$H:$H,I$2) -> 0 | J4: =COUNTIFS('Coded Passages'!$B:$B,$A4,'Coded Passages'!$C:$C,$B4,'Coded Passages'!$H:$H,J$2) -> 2 | K4: =COUNTIFS('Coded Passages'!$B:$B,$A4,'Coded Passages'!$C:$C,$B4,'Coded Passages'!$H:$H,K$2) -> 1 | L4: =SUM(C4:K4) -> 6 | N4: D1.1·Anti-State / An | O4: =L4 -> 6
A5: D1.1 | B5: Delegitimization of Regulation | C5: =COUNTIFS('Coded Passages'!$B:$B,$A5,'Coded Passages'!$C:$C,$B5,'Coded Passages'!$H:$H,C$2) -> 0 | D5: =COUNTIFS('Coded Passages'!$B:$B,$A5,'Coded Passages'!$C:$C,$B5,'Coded Passages'!$H:$H,D$2) -> 4 | E5: =COUNTIFS('Coded Passages'!$B:$B,$A5,'Coded Passages'!$C:$C,$B5,'Coded Passages'!$H:$H,E$2) -> 0 | F5: =COUNTIFS('Coded Passages'!$B:$B,$A5,'Coded Passages'!$C:$C,$B5,'Coded Passages'!$H:$H,F$2) -> 1 | G5: =COUNTIFS('Coded Passages'!$B:$B,$A5,'Coded Passages'!$C:$C,$B5,'Coded Passages'!$H:$H,G$2) -> 0 | H5: =COUNTIFS('Coded Passages'!$B:$B,$A5,'Coded Passages'!$C:$C,$B5,'Coded Passages'!$H:$H,H$2) -> 2 | I5: =COUNTIFS('Coded Passages'!$B:$B,$A5,'Coded Passages'!$C:$C,$B5,'Coded Passages'!$H:$H,I$2) -> 1 | J5: =COUNTIFS('Coded Passages'!$B:$B,$A5,'Coded Passages'!$C:$C,$B5,'Coded Passages'!$H:$H,J$2) -> 0 | K5: =COUNTIFS('Coded Passages'!$B:$B,$A5,'Coded Passages'!$C:$C,$B5,'Coded Passages'!$H:$H,K$2) -> 1 | L5: =SUM(C5:K5) -> 9 | N5: D1.1·Delegitimizatio | O5: =L5 -> 9
A6: D1.1 | B6: Deregulation Benefits | C6: =COUNTIFS('Coded Passages'!$B:$B,$A6,'Coded Passages'!$C:$C,$B6,'Coded Passages'!$H:$H,C$2) -> 0 | D6: =COUNTIFS('Coded Passages'!$B:$B,$A6,'Coded Passages'!$C:$C,$B6,'Coded Passages'!$H:$H,D$2) -> 2 | E6: =COUNTIFS('Coded Passages'!$B:$B,$A6,'Coded Passages'!$C:$C,$B6,'Coded Passages'!$H:$H,E$2) -> 0 | F6: =COUNTIFS('Coded Passages'!$B:$B,$A6,'Coded Passages'!$C:$C,$B6,'Coded Passages'!$H:$H,F$2) -> 1 | G6: =COUNTIFS('Coded Passages'!$B:$B,$A6,'Coded Passages'!$C:$C,$B6,'Coded Passages'!$H:$H,G$2) -> 1 | H6: =COUNTIFS('Coded Passages'!$B:$B,$A6,'Coded Passages'!$C:$C,$B6,'Coded Passages'!$H:$H,H$2) -> 2 | I6: =COUNTIFS('Coded Passages'!$B:$B,$A6,'Coded Passages'!$C:$C,$B6,'Coded Passages'!$H:$H,I$2) -> 1 | J6: =COUNTIFS('Coded Passages'!$B:$B,$A6,'Coded Passages'!$C:$C,$B6,'Coded Passages'!$H:$H,J$2) -> 2 | K6: =COUNTIFS('Coded Passages'!$B:$B,$A6,'Coded Passages'!$C:$C,$B6,'Coded Passages'!$H:$H,K$2) -> 1 | L6: =SUM(C6:K6) -> 10 | N6: D1.1·Deregulation Be | O6: =L6 -> 10
A7: D1.1 | B7: Market Primacy | C7: =COUNTIFS('Coded Passages'!$B:$B,$A7,'Coded Passages'!$C:$C,$B7,'Coded Passages'!$H:$H,C$2) -> 0 | D7: =COUNTIFS('Coded Passages'!$B:$B,$A7,'Coded Passages'!$C:$C,$B7,'Coded Passages'!$H:$H,D$2) -> 3 | E7: =COUNTIFS('Coded Passages'!$B:$B,$A7,'Coded Passages'!$C:$C,$B7,'Coded Passages'!$H:$H,E$2) -> 0 | F7: =COUNTIFS('Coded Passages'!$B:$B,$A7,'Coded Passages'!$C:$C,$B7,'Coded Passages'!$H:$H,F$2) -> 1 | G7: =COUNTIFS('Coded Passages'!$B:$B,$A7,'Coded Passages'!$C:$C,$B7,'Coded Passages'!$H:$H,G$2) -> 0 | H7: =COUNTIFS('Coded Passages'!$B:$B,$A7,'Coded Passages'!$C:$C,$B7,'Coded Passages'!$H:$H,H$2) -> 1 | I7: =COUNTIFS('Coded Passages'!$B:$B,$A7,'Coded Passages'!$C:$C,$B7,'Coded Passages'!$H:$H,I$2) -> 0 | J7: =COUNTIFS('Coded Passages'!$B:$B,$A7,'Coded Passages'!$C:$C,$B7,'Coded Passages'!$H:$H,J$2) -> 1 | K7: =COUNTIFS('Coded Passages'!$B:$B,$A7,'Coded Passages'!$C:$C,$B7,'Coded Passages'!$H:$H,K$2) -> 1 | L7: =SUM(C7:K7) -> 7 | N7: D1.1·Market Primacy | O7: =L7 -> 7
A8: D1.1 | B8: Rejection of Multilateral Governance | C8: =COUNTIFS('Coded Passages'!$B:$B,$A8,'Coded Passages'!$C:$C,$B8,'Coded Passages'!$H:$H,C$2) -> 0 | D8: =COUNTIFS('Coded Passages'!$B:$B,$A8,'Coded Passages'!$C:$C,$B8,'Coded Passages'!$H:$H,D$2) -> 1 | E8: =COUNTIFS('Coded Passages'!$B:$B,$A8,'Coded Passages'!$C:$C,$B8,'Coded Passages'!$H:$H,E$2) -> 5 | F8: =COUNTIFS('Coded Passages'!$B:$B,$A8,'Coded Passages'!$C:$C,$B8,'Coded Passages'!$H:$H,F$2) -> 3 | G8: =COUNTIFS('Coded Passages'!$B:$B,$A8,'Coded Passages'!$C:$C,$B8,'Coded Passages'!$H:$H,G$2) -> 4 | H8: =COUNTIFS('Coded Passages'!$B:$B,$A8,'Coded Passages'!$C:$C,$B8,'Coded Passages'!$H:$H,H$2) -> 0 | I8: =COUNTIFS('Coded Passages'!$B:$B,$A8,'Coded Passages'!$C:$C,$B8,'Coded Passages'!$H:$H,I$2) -> 0 | J8: =COUNTIFS('Coded Passages'!$B:$B,$A8,'Coded Passages'!$C:$C,$B8,'Coded Passages'!$H:$H,J$2) -> 1 | K8: =COUNTIFS('Coded Passages'!$B:$B,$A8,'Coded Passages'!$C:$C,$B8,'Coded Passages'!$H:$H,K$2) -> 1 | L8: =SUM(C8:K8) -> 15 | N8: D1.1·Rejection of Mu | O8: =L8 -> 15
A9: D1.1 | B9: Sustainability as Ideological or Harmful | C9: =COUNTIFS('Coded Passages'!$B:$B,$A9,'Coded Passages'!$C:$C,$B9,'Coded Passages'!$H:$H,C$2) -> 1 | D9: =COUNTIFS('Coded Passages'!$B:$B,$A9,'Coded Passages'!$C:$C,$B9,'Coded Passages'!$H:$H,D$2) -> 0 | E9: =COUNTIFS('Coded Passages'!$B:$B,$A9,'Coded Passages'!$C:$C,$B9,'Coded Passages'!$H:$H,E$2) -> 3 | F9: =COUNTIFS('Coded Passages'!$B:$B,$A9,'Coded Passages'!$C:$C,$B9,'Coded Passages'!$H:$H,F$2) -> 1 | G9: =COUNTIFS('Coded Passages'!$B:$B,$A9,'Coded Passages'!$C:$C,$B9,'Coded Passages'!$H:$H,G$2) -> 1 | H9: =COUNTIFS('Coded Passages'!$B:$B,$A9,'Coded Passages'!$C:$C,$B9,'Coded Passages'!$H:$H,H$2) -> 0 | I9: =COUNTIFS('Coded Passages'!$B:$B,$A9,'Coded Passages'!$C:$C,$B9,'Coded Passages'!$H:$H,I$2) -> 0 | J9: =COUNTIFS('Coded Passages'!$B:$B,$A9,'Coded Passages'!$C:$C,$B9,'Coded Passages'!$H:$H,J$2) -> 0 | K9: =COUNTIFS('Coded Passages'!$B:$B,$A9,'Coded Passages'!$C:$C,$B9,'Coded Passages'!$H:$H,K$2) -> 1 | L9: =SUM(C9:K9) -> 7 | N9: D1.1·Sustainability | O9: =L9 -> 7
A10: D1.2 | B10: Attack on Experts & Technocrats | C10: =COUNTIFS('Coded Passages'!$B:$B,$A10,'Coded Passages'!$C:$C,$B10,'Coded Passages'!$H:$H,C$2) -> 1 | D10: =COUNTIFS('Coded Passages'!$B:$B,$A10,'Coded Passages'!$C:$C,$B10,'Coded Passages'!$H:$H,D$2) -> 1 | E10: =COUNTIFS('Coded Passages'!$B:$B,$A10,'Coded Passages'!$C:$C,$B10,'Coded Passages'!$H:$H,E$2) -> 1 | F10: =COUNTIFS('Coded Passages'!$B:$B,$A10,'Coded Passages'!$C:$C,$B10,'Coded Passages'!$H:$H,F$2) -> 0 | G10: =COUNTIFS('Coded Passages'!$B:$B,$A10,'Coded Passages'!$C:$C,$B10,'Coded Passages'!$H:$H,G$2) -> 2 | H10: =COUNTIFS('Coded Passages'!$B:$B,$A10,'Coded Passages'!$C:$C,$B10,'Coded Passages'!$H:$H,H$2) -> 0 | I10: =COUNTIFS('Coded Passages'!$B:$B,$A10,'Coded Passages'!$C:$C,$B10,'Coded Passages'!$H:$H,I$2) -> 0 | J10: =COUNTIFS('Coded Passages'!$B:$B,$A10,'Coded Passages'!$C:$C,$B10,'Coded Passages'!$H:$H,J$2) -> 0 | K10: =COUNTIFS('Coded Passages'!$B:$B,$A10,'Coded Passages'!$C:$C,$B10,'Coded Passages'!$H:$H,K$2) -> 0 | L10: =SUM(C10:K10) -> 5 | N10: D1.2·Attack on Exper | O10: =L10 -> 5
A11: D1.2 | B11: Attack on Universities | C11: =COUNTIFS('Coded Passages'!$B:$B,$A11,'Coded Passages'!$C:$C,$B11,'Coded Passages'!$H:$H,C$2) -> 0 | D11: =COUNTIFS('Coded Passages'!$B:$B,$A11,'Coded Passages'!$C:$C,$B11,'Coded Passages'!$H:$H,D$2) -> 0 | E11: =COUNTIFS('Coded Passages'!$B:$B,$A11,'Coded Passages'!$C:$C,$B11,'Coded Passages'!$H:$H,E$2) -> 0 | F11: =COUNTIFS('Coded Passages'!$B:$B,$A11,'Coded Passages'!$C:$C,$B11,'Coded Passages'!$H:$H,F$2) -> 2 | G11: =COUNTIFS('Coded Passages'!$B:$B,$A11,'Coded Passages'!$C:$C,$B11,'Coded Passages'!$H:$H,G$2) -> 0 | H11: =COUNTIFS('Coded Passages'!$B:$B,$A11,'Coded Passages'!$C:$C,$B11,'Coded Passages'!$H:$H,H$2) -> 0 | I11: =COUNTIFS('Coded Passages'!$B:$B,$A11,'Coded Passages'!$C:$C,$B11,'Coded Passages'!$H:$H,I$2) -> 1 | J11: =COUNTIFS('Coded Passages'!$B:$B,$A11,'Coded Passages'!$C:$C,$B11,'Coded Passages'!$H:$H,J$2) -> 0 | K11: =COUNTIFS('Coded Passages'!$B:$B,$A11,'Coded Passages'!$C:$C,$B11,'Coded Passages'!$H:$H,K$2) -> 0 | L11: =SUM(C11:K11) -> 3 | N11: D1.2·Attack on Unive | O11: =L11 -> 3
A12: D1.2 | B12: Climate Skepticism or Dismissal | C12: =COUNTIFS('Coded Passages'!$B:$B,$A12,'Coded Passages'!$C:$C,$B12,'Coded Passages'!$H:$H,C$2) -> 1 | D12: =COUNTIFS('Coded Passages'!$B:$B,$A12,'Coded Passages'!$C:$C,$B12,'Coded Passages'!$H:$H,D$2) -> 0 | E12: =COUNTIFS('Coded Passages'!$B:$B,$A12,'Coded Passages'!$C:$C,$B12,'Coded Passages'!$H:$H,E$2) -> 0 | F12: =COUNTIFS('Coded Passages'!$B:$B,$A12,'Coded Passages'!$C:$C,$B12,'Coded Passages'!$H:$H,F$2) -> 1 | G12: =COUNTIFS('Coded Passages'!$B:$B,$A12,'Coded Passages'!$C:$C,$B12,'Coded Passages'!$H:$H,G$2) -> 0 | H12: =COUNTIFS('Coded Passages'!$B:$B,$A12,'Coded Passages'!$C:$C,$B12,'Coded Passages'!$H:$H,H$2) -> 0 | I12: =COUNTIFS('Coded Passages'!$B:$B,$A12,'Coded Passages'!$C:$C,$B12,'Coded Passages'!$H:$H,I$2) -> 0 | J12: =COUNTIFS('Coded Passages'!$B:$B,$A12,'Coded Passages'!$C:$C,$B12,'Coded Passages'!$H:$H,J$2) -> 0 | K12: =COUNTIFS('Coded Passages'!$B:$B,$A12,'Coded Passages'!$C:$C,$B12,'Coded Passages'!$H:$H,K$2) -> 0 | L12: =SUM(C12:K12) -> 2 | N12: D1.2·Climate Skeptic | O12: =L12 -> 2
A13: D1.2 | B13: Pseudo-Science / Ideological Science | C13: =COUNTIFS('Coded Passages'!$B:$B,$A13,'Coded Passages'!$C:$C,$B13,'Coded Passages'!$H:$H,C$2) -> 0 | D13: =COUNTIFS('Coded Passages'!$B:$B,$A13,'Coded Passages'!$C:$C,$B13,'Coded Passages'!$H:$H,D$2) -> 2 | E13: =COUNTIFS('Coded Passages'!$B:$B,$A13,'Coded Passages'!$C:$C,$B13,'Coded Passages'!$H:$H,E$2) -> 0 | F13: =COUNTIFS('Coded Passages'!$B:$B,$A13,'Coded Passages'!$C:$C,$B13,'Coded Passages'!$H:$H,F$2) -> 1 | G13: =COUNTIFS('Coded Passages'!$B:$B,$A13,'Coded Passages'!$C:$C,$B13,'Coded Passages'!$H:$H,G$2) -> 0 | H13: =COUNTIFS('Coded Passages'!$B:$B,$A13,'Coded Passages'!$C:$C,$B13,'Coded Passages'!$H:$H,H$2) -> 0 | I13: =COUNTIFS('Coded Passages'!$B:$B,$A13,'Coded Passages'!$C:$C,$B13,'Coded Passages'!$H:$H,I$2) -> 0 | J13: =COUNTIFS('Coded Passages'!$B:$B,$A13,'Coded Passages'!$C:$C,$B13,'Coded Passages'!$H:$H,J$2) -> 0 | K13: =COUNTIFS('Coded Passages'!$B:$B,$A13,'Coded Passages'!$C:$C,$B13,'Coded Passages'!$H:$H,K$2) -> 0 | L13: =SUM(C13:K13) -> 3 | N13: D1.2·Pseudo-Science | O13: =L13 -> 3
A14: D1.2 | B14: Rejection of Expert Mediation | C14: =COUNTIFS('Coded Passages'!$B:$B,$A14,'Coded Passages'!$C:$C,$B14,'Coded Passages'!$H:$H,C$2) -> 0 | D14: =COUNTIFS('Coded Passages'!$B:$B,$A14,'Coded Passages'!$C:$C,$B14,'Coded Passages'!$H:$H,D$2) -> 0 | E14: =COUNTIFS('Coded Passages'!$B:$B,$A14,'Coded Passages'!$C:$C,$B14,'Coded Passages'!$H:$H,E$2) -> 0 | F14: =COUNTIFS('Coded Passages'!$B:$B,$A14,'Coded Passages'!$C:$C,$B14,'Coded Passages'!$H:$H,F$2) -> 1 | G14: =COUNTIFS('Coded Passages'!$B:$B,$A14,'Coded Passages'!$C:$C,$B14,'Coded Passages'!$H:$H,G$2) -> 0 | H14: =COUNTIFS('Coded Passages'!$B:$B,$A14,'Coded Passages'!$C:$C,$B14,'Coded Passages'!$H:$H,H$2) -> 0 | I14: =COUNTIFS('Coded Passages'!$B:$B,$A14,'Coded Passages'!$C:$C,$B14,'Coded Passages'!$H:$H,I$2) -> 0 | J14: =COUNTIFS('Coded Passages'!$B:$B,$A14,'Coded Passages'!$C:$C,$B14,'Coded Passages'!$H:$H,J$2) -> 0 | K14: =COUNTIFS('Coded Passages'!$B:$B,$A14,'Coded Passages'!$C:$C,$B14,'Coded Passages'!$H:$H,K$2) -> 0 | L14: =SUM(C14:K14) -> 1 | N14: D1.2·Rejection of Ex | O14: =L14 -> 1
... A20: IND | B20: Temporal Appropriation | C20: =COUNTIFS('Coded Passages'!$B:$B,$A20,'Coded Passages'!$C:$C,$B20,'Coded Passages'!$H:$H,C$2) -> 0 | D20: =COUNTIFS('Coded Passages'!$B:$B,$A20,'Coded Passages'!$C:$C,$B20,'Coded Passages'!$H:$H,D$2) -> 0 | E20: =COUNTIFS('Coded Passages'!$B:$B,$A20,'Coded Passages'!$C:$C,$B20,'Coded Passages'!$H:$H,E$2) -> 0 | F20: =COUNTIFS('Coded Passages'!$B:$B,$A20,'Coded Passages'!$C:$C,$B20,'Coded Passages'!$H:$H,F$2) -> 0 | G20: =COUNTIFS('Coded Passages'!$B:$B,$A20,'Coded Passages'!$C:$C,$B20,'Coded Passages'!$H:$H,G$2) -> 2 | H20: =COUNTIFS('Coded Passages'!$B:$B,$A20,'Coded Passages'!$C:$C,$B20,'Coded Passages'!$H:$H,H$2) -> 0 | I20: =COUNTIFS('Coded Passages'!$B:$B,$A20,'Coded Passages'!$C:$C,$B20,'Coded Passages'!$H:$H,I$2) -> 0 | J20: =COUNTIFS('Coded Passages'!$B:$B,$A20,'Coded Passages'!$C:$C,$B20,'Coded Passages'!$H:$H,J$2) -> 0 | K20: =COUNTIFS('Coded Passages'!$B:$B,$A20,'Coded Passages'!$C:$C,$B20,'Coded Passages'!$H:$H,K$2) -> 1 | L20: =SUM(C20:K20) -> 3 | N20: IND·Temporal Approp | O20: =L20 -> 3
A21: TOTAL | B21: All Sub-codes | C21: =SUM(C3:C20) -> 4 | D21: =SUM(D3:D20) -> 20 | E21: =SUM(E3:E20) -> 13 | F21: =SUM(F3:F20) -> 20 | G21: =SUM(G3:G20) -> 13 | H21: =SUM(H3:H20) -> 7 | I21: =SUM(I3:I20) -> 4 | J21: =SUM(J3:J20) -> 8 | ... L21: =SUM(L3:L20) -> 100

Sheet Analysis of categories
B1: Original | C1: New | D1: Comments
A2: D1.1. Delegitimization of state intervention and sustainability governance | B2: Market primacy and free-market solutions | C2: Market primacy and free-market solutions
B3: Anti-state and anti-bureaucratic rhetoric | C3: Anti-state and anti-bureaucratic rhetoric
B4: Anti-elite narratives (“la casta”) | C4: Anti-elite narratives (“la casta”)
B5: Delegitimization of regulation | C5: Delegitimization of regulation / benefits of deregulation | D5: to bundle benefits of deregulation with delegitimization of regulation
B6: benefits of deregulation
B7: Sustainability as Ideological or Harmful
B8: Rejection of multilateral environmental governance. | D8: To consider a broad definition of rejection of multilateral governance in general not only environmental
A9: D1.2 Delegitimization of science and expertise | B9: Attack on Universities | C9: Attack on Universities and Research Institutions | D9: To bundle research institutions and universities, each time it is found Delegitimization of scientific and professional institutions
B10: Attack on Experts & Technocrats | C10: Attack on Experts & Technocrats | D10: Bundled with rejection of expert mediation (rarely found)
B11: Climate Skepticism or Dismissal of Environmental Science | C11: Climate Skepticism or Dismissal of Environmental Science
B12: Pseudo-Science / Ideological Science | C12: Pseudo-Science / Ideological Science | D12: Sometimes is bundled with dimension 3
C13: Selective empiricism
A14: D1.3 Cultural backlash (wokeism, neo-marxism) | B14: neo-marxism | C14: Anti-socialism or anti neo-marxism | D14: Look for a definition of this concept (cultural backlash / cultural battle)
B15: Woke bundling | C15: Woke bundling
B16: Civilizational defense | C16: Civilizational defense
