Workbook

Sheet Coded Passages
A1: Milei Climate Narratives — v4 Coded Passages · Data source for all summary sheets
A2: # | B2: Dimension | C2: Sub-dimension | D2: Dimension (Full) | E2: Sub-code (Full) | F2: Quoted Passage | G2: Analytical Memo | H2: Speech | I2: Date | J2: Venue | K2: Type | L2: Scope
A3: 1 | B3: D1.2 | C3: Climate Skepticism or Dismissal | D3: D1.2 — Public Science & Expertise | E3: Climate Skepticism or Dismissal | F3: [MILEI — Respuesta]: A ver primero no mienta. Yo no niego el cambio climático. Lo que yo digo es que existe en la historia de la tierra un ciclo de temperaturas, es decir hay un comportamiento cíclico y este es el quinto punto del ciclo — donde la diferencia con los cuatro anteriores es que antes no estaba el ser humano. Por lo tanto todas esas políticas que culpan al ser humano del cambio climático son falsas y lo único que buscan es recaudar fondos para financiar vagos socialistas que escriben papers de cuarta. | G3: Milei performs the disclaimer-then-dismiss move: "I don't deny climate change" is immediately followed by the natural-cycles attribution, which reproduces effective denial while maintaining rhetorical deniability. The key claim — "all those policies that blame humans for climate change are false" — is a direct dismissal of the scientific basis for climate regulation, delivered as a logical conclusion from the paleoclimatic premise. This is the most compressed instance of Climate_Skepticism_or_Dismissal in the corpus: denial of anthropogenic attribution without denial of the climate phenomenon itself. | H3: Debate Presidencial 2023 | I3: 2023-10-08 | J3: Buenos Aires | K3: Debate presidencial | L3: National
A4: 2 | B4: D1.1 | C4: Sustainability as Ideological or Harmful | D4: D1.1 — State Intervention & Governance | E4: Sustainability as Ideological or Harmful | F4: [MILEI — Respuesta]: A ver primero no mienta. Yo no niego el cambio climático. Lo que yo digo es que existe en la historia de la tierra un ciclo de temperaturas, es decir hay un comportamiento cíclico y este es el quinto punto del ciclo — donde la diferencia con los cuatro anteriores es que antes no estaba el ser humano. Por lo tanto todas esas políticas que culpan al ser humano del cambio climático son falsas y lo único que buscan es recaudar fondos para financiar vagos socialistas que escriben papers de cuarta. | G4: "Recaudar fondos para financiar vagos socialistas que escriben papers de cuarta" reframes climate policy as a rent-extraction mechanism for a parasitic academic class. The claim is not that climate policy is merely wrong — it is that climate policy exists as an institutional vehicle for redistributing resources to ideologically motivated, low-quality scholarship. This is Sustainability_as_Ideological_or_Harmful at its most direct: the policy's real function is material redistribution under ideological cover, not environmental protection. | H4: Debate Presidencial 2023 | I4: 2023-10-08 | J4: Buenos Aires | K4: Debate presidencial | L4: National
A5: 3 | B5: D1.2 | C5: Attack on Experts & Technocrats | D5: D1.2 — Public Science & Expertise | E5: Attack on Experts & Technocrats | F5: [MILEI — Respuesta]: A ver primero no mienta. Yo no niego el cambio climático. Lo que yo digo es que existe en la historia de la tierra un ciclo de temperaturas, es decir hay un comportamiento cíclico y este es el quinto punto del ciclo — donde la diferencia con los cuatro anteriores es que antes no estaba el ser humano. Por lo tanto todas esas políticas que culpan al ser humano del cambio climático son falsas y lo único que buscan es recaudar fondos para financiar vagos socialistas que escriben papers de cuarta. | G5: "Vagos socialistas que escriben papers de cuarta" is the rawest expert delegitimation in the corpus — climate scientists reduced to lazy, ideologically motivated rent-seekers producing worthless work. Unlike the more sophisticated epistemological arguments deployed at Davos (which grant good intentions while invalidating the theoretical framework), here the attack is purely ad hominem and institutional, characterizing climate science as professionally worthless rather than merely theoretically flawed. | H5: Debate Presidencial 2023 | I5: 2023-10-08 | J5: Buenos Aires | K5: Debate presidencial | L5: National
A6: 4 | B6: D1.3 | C6: Civilizational Defense | D6: D1.3 — Cultural Backlash | E6: Civilizational Defense | F6: Buenas tardes, muchas gracias: hoy estoy acá para decirles que Occidente está en peligro, está en peligro porque aquellos, que supuestamente deben defender los valores de Occidente, se encuentran cooptados por una visión del mundo que – inexorablemente – conduce al socialismo, en consecuencia a la pobreza. Lamentablemente en las últimas décadas, motivados por algunos deseos bien pensantes de querer ayudar al prójimo y otros por el deseo de querer pertenecer a una casta privilegiada, los principales líderes del mundo occidental han abandonado el modelo de la libertad, por distintas versiones, de lo que llamamos colectivismo. | G6: The opening sentences establish the master civilizational frame for the entire speech: Western civilization is under existential threat from socialism, and the WEF audience itself is identified as part of a "casta privilegiada" complicit in that decline. This frame pre-loads every subsequent critique — including of environmental policy — with civilizational stakes. Climate governance emanating from the "cooptados" Western establishment is tainted by association with civilizational threat, making engagement with it a form of civilizational capitulation. | H6: WEF Davos 2024 | I6: 2024-01-17 | J6: Davos, Suiza | K6: Foro económico internacional | L6: International
A7: 5 | B7: D1.1 | C7: Anti-Casta (Elite Frame) | D7: D1.1 — State Intervention & Governance | E7: Anti-Casta (Elite Frame) | F7: Buenas tardes, muchas gracias: hoy estoy acá para decirles que Occidente está en peligro, está en peligro porque aquellos, que supuestamente deben defender los valores de Occidente, se encuentran cooptados por una visión del mundo que – inexorablemente – conduce al socialismo, en consecuencia a la pobreza. Lamentablemente en las últimas décadas, motivados por algunos deseos bien pensantes de querer ayudar al prójimo y otros por el deseo de querer pertenecer a una casta privilegiada, los principales líderes del mundo occidental han abandonado el modelo de la libertad, por distintas versiones, de lo que llamamos colectivismo. | G7: "Pertenecer a una casta privilegiada" extends Milei's domestic anti-elite frame to the global governance level, targeting the WEF audience itself. International climate institutions and their leaders are pre-emptively delegitimized as members of a global caste pursuing privilege rather than planetary welfare — the same logic used domestically against environmental ministries and CONICET is applied globally to IPCC, UNEP, and multilateral climate bodies. | H7: WEF Davos 2024 | I7: 2024-01-17 | J7: Davos, Suiza | K7: Foro económico internacional | L7: International
A8: 6 | B8: D1.1 | C8: Market Primacy | D8: D1.1 — State Intervention & Governance | E8: Market Primacy | F8: La conclusión es obvia: lejos de ser la causa de nuestros problemas, el capitalismo de libre empresa, como sistema económico, es la única herramienta que tenemos para terminar con el hambre, la pobreza y la indigencia, a lo largo y a lo ancho de todo el planeta. La evidencia empírica es incuestionable. | G8: The hockey-stick economic history culminates in the categorical Market_Primacy claim: free-enterprise capitalism is "the only tool" for ending poverty, and the conclusion is declared empirically self-evident. For sustainability governance, the structural implication is total: if markets are the only legitimate mechanism for solving the most fundamental collective problem (poverty), they are implicitly the only legitimate mechanism for environmental problems, displacing any basis for state-led climate regulation. | H8: WEF Davos 2024 | I8: 2024-01-17 | J8: Davos, Suiza | K8: Foro económico internacional | L8: International
A9: 7 | B9: D1.2 | C9: Selective Empiricism | D9: D1.2 — Public Science & Expertise | E9: Selective Empiricism | F9: La conclusión es obvia: lejos de ser la causa de nuestros problemas, el capitalismo de libre empresa, como sistema económico, es la única herramienta que tenemos para terminar con el hambre, la pobreza y la indigencia, a lo largo y a lo ancho de todo el planeta. La evidencia empírica es incuestionable. | G9: "La evidencia empírica es incuestionable" is the canonical Selective_Empiricism instance in the corpus: Milei claims unquestionable empirical authority for the pro-market historical narrative, but later in the same speech systematically dismisses opposing academic and institutional knowledge (including climate science) as ideologically captured. The move is to appropriate the prestige of empiricism for one side while denying it to the other — crowding out rather than refuting. | H9: WEF Davos 2024 | I9: 2024-01-17 | J9: Davos, Suiza | K9: Foro económico internacional | L9: International
A10: 8 | B10: D1.1 | C10: Market Primacy | D10: D1.1 — State Intervention & Governance | E10: Market Primacy | F10: El colectivismo - al inhibir estos procesos de descubrimiento y al dificultar la apropiación de lo descubierto - ata al emprendedor de las manos y le imposibilita producir mejores bienes y ofrecer mejores servicios a un mejor precio. ¿Cómo puede ser, entonces, que desde la academia, los organismos internacionales, la política y la teoría económica se demonice un sistema económico que no sólo ha sacado de la pobreza más extrema, al 90 por ciento de la población mundial? | G10: The Kirznerian market-as-discovery-process argument provides theoretical grounding: environmental outcomes, like economic ones, are best achieved through decentralized market discovery rather than state planning. "Academia, los organismos internacionales, la política y la teoría económica" — the four pillars of climate governance legitimacy — are grouped as an ideological bloc irrationally hostile to the proven market mechanism. | H10: WEF Davos 2024 | I10: 2024-01-17 | J10: Davos, Suiza | K10: Foro económico internacional | L10: International
A11: 9 | B11: D1.2 | C11: Attack on Experts & Technocrats | D11: D1.2 — Public Science & Expertise | E11: Attack on Experts & Technocrats | F11: El colectivismo - al inhibir estos procesos de descubrimiento y al dificultar la apropiación de lo descubierto - ata al emprendedor de las manos y le imposibilita producir mejores bienes y ofrecer mejores servicios a un mejor precio. ¿Cómo puede ser, entonces, que desde la academia, los organismos internacionales, la política y la teoría económica se demonice un sistema económico que no sólo ha sacado de la pobreza más extrema, al 90 por ciento de la población mundial? | G11: The entire authority apparatus — academic, international, political, theoretical — is presented as a unified bloc that "demonizes" capitalism. For sustainability governance: IPCC, UNEP, national science ministries, and environmental economics are all expressions of the same anti-capitalist ideological formation. This is a structural delegitimation of the expert class, not a dispute with specific scientific findings. | H11: WEF Davos 2024 | I11: 2024-01-17 | J11: Davos, Suiza | K11: Foro económico internacional | L11: International
A12: 10 | B12: D1.2 | C12: Pseudo-Science / Ideological Science | D12: D1.2 — Public Science & Expertise | E12: Pseudo-Science / Ideological Science | F12: El problema esencial de occidente hoy es que no sólo debemos enfrentarnos a quienes siguen bregando por el socialismo empobrecedor; sino también a nuestros propios líderes, pensadores y académicos que, amparados en un marco teórico equivocado, socavan los fundamentos del sistema que nos ha dado la mayor expansión de riqueza y prosperidad de nuestra historia. | G12: "Amparados en un marco teórico equivocado" frames the entire academic and expert community as epistemically compromised: their framework is wrong, and therefore their outputs — including climate science, environmental economics, and sustainability research — are systematically distorted. The concession of good intentions ("sin quererlo," as the next paragraph notes) makes this a structurally more powerful delegitimation than the debate's ad hominem: it invalidates conclusions while preserving a veneer of charity toward the actors. | H12: WEF Davos 2024 | I12: 2024-01-17 | J12: Davos, Suiza | K12: Foro económico internacional | L12: International
A13: 11 | B13: D1.1 | C13: Delegitimization of Regulation | D13: D1.1 — State Intervention & Governance | E13: Delegitimization of Regulation | F13: El marco teórico al que me refiero es el de la teoría económica neoclásica, que diseña un instrumental que, sin quererlo, termina siendo funcional a la intromisión del estado. El problema de los neoclásicos es que como el modelo del que se enamoraron no mapea contra la realidad, atribuyen el error a supuestos fallos del mercado en vez de revisar las premisas de su modelo. | G13: The attack on neoclassical economics demolishes the theoretical foundation of environmental regulation. Mainstream climate policy — carbon pricing, Pigouvian taxes, cap-and-trade — derives its justification from externality theory, precisely the "instrumental" Milei argues ends up serving state intrusion. By framing neoclassical economics as the theoretical Trojan horse through which socialism enters, he delegitimizes the entire economic-theoretical basis for climate regulation at the level of first principles. | H13: WEF Davos 2024 | I13: 2024-01-17 | J13: Davos, Suiza | K13: Foro económico internacional | L13: International
A14: 12 | B14: D1.1 | C14: Delegitimization of Regulation | D14: D1.1 — State Intervention & Governance | E14: Delegitimization of Regulation | F14: El pretexto de un supuesto fallo de mercado se introducen regulaciones que lo único que generan es distorsiones en el sistema de precios, que impiden el cálculo económico, y en consecuencia el ahorro, la inversión y el crecimiento. | G14: The positive deregulation case through intervention-spiral logic: each regulatory "correction" of a supposed market failure compounds the problem by distorting price signals, impairing economic calculation, reducing saving, investment, and growth. Applied to climate policy: carbon taxes, emissions standards, and green industrial mandates suppress economic activity rather than solving an environmental problem. | H14: WEF Davos 2024 | I14: 2024-01-17 | J14: Davos, Suiza | K14: Foro económico internacional | L14: International
... A90: 88 | B90: D1.3 | C90: Anti-Socialism / Anti-Collectivism | D90: D1.3 — Cultural Backlash | E90: Anti-Socialism / Anti-Collectivism | F90: La verdadera batalla de nuestro tiempo es cultural, filosófica y moral. Es elegir el sistema que sacó de la pobreza a millones. Es para dejar de ser una Nación inmadura, que dilapida el futuro para repartir beneficios en el presente; y convertirnos en una nación madura, que planifica las reglas de juego para que haya presente y futuro; y para que cada ciudadano pueda elegir libremente su propio destino. No que se lo quiera determinar un burócrata ignorante, fatalmente arrogante. Gobernar con responsabilidad es gobernar para los argentinos de hoy, pero también gobernar para los argentinos de mañana. | G90: The framing of "la verdadera batalla de nuestro tiempo" as cultural, philosophical, and moral — a battle between the "system that lifted millions from poverty" (capitalism/market freedom) and an unnamed adversary — is the neo-Marxism code at its most developed. The adversary is implicitly socialism/collectivism, and the climate governance regime is implicitly on the collectivist side: it involves state planning, expert mediation, and redistribution of present consumption toward future generations. The closing formulation — "gobernar para los argentinos de mañana" — is analytically notable because it appropriates the intergenerational responsibility language of sustainability (governing for future generations) while deploying it against climate policy (which in this framing dilapidates the future by redistributing in the present). This is a sophisticated version of the Temporal_Appropriation inductive category. | H90: Apertura Sesiones Ordinarias 2026 (144°) | I90: 2026-03-01 | J90: Buenos Aires (Congreso) | K90: Acto institucional | L90: National

Sheet Freq — By Dimension
A1: Code Frequency by Dimension × Speech — values update automatically from 'Coded Passages'
A2: Dimension | B2: Dimension (Full) | C2: Debate Presidencial 2023 | D2: WEF Davos 2024 | E2: Apertura Sesiones Ordinarias 2024 (142°) | F2: UN General Assembly 79th | G2: WEF Davos 2025 | H2: Apertura Sesiones Ordinarias 2025 (143°) | I2: UN General Assembly 80th | J2: WEF Davos 2026 | K2: Apertura Sesiones Ordinarias 2026 (144°) | L2: TOTAL | N2: Dimension | O2: Total
A3: D1.1 | B3: =COUNTIFS('Coded Passages'!$B:$B,$A3,'Coded Passages'!$H:$H,B$2) -> 0 | C3: =COUNTIFS('Coded Passages'!$B:$B,$A3,'Coded Passages'!$H:$H,C$2) -> 1 | D3: =COUNTIFS('Coded Passages'!$B:$B,$A3,'Coded Passages'!$H:$H,D$2) -> 13 | E3: =COUNTIFS('Coded Passages'!$B:$B,$A3,'Coded Passages'!$H:$H,E$2) -> 2 | F3: =COUNTIFS('Coded Passages'!$B:$B,$A3,'Coded Passages'!$H:$H,F$2) -> 8 | G3: =COUNTIFS('Coded Passages'!$B:$B,$A3,'Coded Passages'!$H:$H,G$2) -> 7 | H3: =COUNTIFS('Coded Passages'!$B:$B,$A3,'Coded Passages'!$H:$H,H$2) -> 4 | I3: =COUNTIFS('Coded Passages'!$B:$B,$A3,'Coded Passages'!$H:$H,I$2) -> 9 | J3: =COUNTIFS('Coded Passages'!$B:$B,$A3,'Coded Passages'!$H:$H,J$2) -> 5 | L3: =SUM(C3:K3) -> 49 | N3: D1.1 | O3: =L3 -> 49
A4: D1.2 | B4: =COUNTIFS('Coded Passages'!$B:$B,$A4,'Coded Passages'!$H:$H,B$2) -> 0 | C4: =COUNTIFS('Coded Passages'!$B:$B,$A4,'Coded Passages'!$H:$H,C$2) -> 2 | D4: =COUNTIFS('Coded Passages'!$B:$B,$A4,'Coded Passages'!$H:$H,D$2) -> 4 | E4: =COUNTIFS('Coded Passages'!$B:$B,$A4,'Coded Passages'!$H:$H,E$2) -> 1 | F4: =COUNTIFS('Coded Passages'!$B:$B,$A4,'Coded Passages'!$H:$H,F$2) -> 1 | G4: =COUNTIFS('Coded Passages'!$B:$B,$A4,'Coded Passages'!$H:$H,G$2) -> 6 | H4: =COUNTIFS('Coded Passages'!$B:$B,$A4,'Coded Passages'!$H:$H,H$2) -> 0 | I4: =COUNTIFS('Coded Passages'!$B:$B,$A4,'Coded Passages'!$H:$H,I$2) -> 2 | J4: =COUNTIFS('Coded Passages'!$B:$B,$A4,'Coded Passages'!$H:$H,J$2) -> 0 | L4: =SUM(C4:K4) -> 16 | N4: D1.2 | O4: =L4 -> 16
A5: D1.3 | B5: =COUNTIFS('Coded Passages'!$B:$B,$A5,'Coded Passages'!$H:$H,B$2) -> 0 | C5: =COUNTIFS('Coded Passages'!$B:$B,$A5,'Coded Passages'!$H:$H,C$2) -> 0 | D5: =COUNTIFS('Coded Passages'!$B:$B,$A5,'Coded Passages'!$H:$H,D$2) -> 2 | E5: =COUNTIFS('Coded Passages'!$B:$B,$A5,'Coded Passages'!$H:$H,E$2) -> 0 | F5: =COUNTIFS('Coded Passages'!$B:$B,$A5,'Coded Passages'!$H:$H,F$2) -> 4 | G5: =COUNTIFS('Coded Passages'!$B:$B,$A5,'Coded Passages'!$H:$H,G$2) -> 6 | H5: =COUNTIFS('Coded Passages'!$B:$B,$A5,'Coded Passages'!$H:$H,H$2) -> 0 | I5: =COUNTIFS('Coded Passages'!$B:$B,$A5,'Coded Passages'!$H:$H,I$2) -> 1 | J5: =COUNTIFS('Coded Passages'!$B:$B,$A5,'Coded Passages'!$H:$H,J$2) -> 2 | L5: =SUM(C5:K5) -> 15 | N5: D1.3 | O5: =L5 -> 15
A6: IND | B6: =COUNTIFS('Coded Passages'!$B:$B,$A6,'Coded Passages'!$H:$H,B$2) -> 0 | C6: =COUNTIFS('Coded Passages'!$B:$B,$A6,'Coded Passages'!$H:$H,C$2) -> 0 | D6: =COUNTIFS('Coded Passages'!$B:$B,$A6,'Coded Passages'!$H:$H,D$2) -> 0 | E6: =COUNTIFS('Coded Passages'!$B:$B,$A6,'Coded Passages'!$H:$H,E$2) -> 0 | F6: =COUNTIFS('Coded Passages'!$B:$B,$A6,'Coded Passages'!$H:$H,F$2) -> 0 | G6: =COUNTIFS('Coded Passages'!$B:$B,$A6,'Coded Passages'!$H:$H,G$2) -> 0 | H6: =COUNTIFS('Coded Passages'!$B:$B,$A6,'Coded Passages'!$H:$H,H$2) -> 0 | I6: =COUNTIFS('Coded Passages'!$B:$B,$A6,'Coded Passages'!$H:$H,I$2) -> 0 | J6: =COUNTIFS('Coded Passages'!$B:$B,$A6,'Coded Passages'!$H:$H,J$2) -> 0 | L6: =SUM(C6:K6) -> 0 | N6: IND | O6: =L6 -> 0
A7: TOTAL | B7: All Dimensions | C7: =SUM(C3:C6) -> 3 | D7: =SUM(D3:D6) -> 19 | E7: =SUM(E3:E6) -> 3 | F7: =SUM(F3:F6) -> 13 | G7: =SUM(G3:G6) -> 19 | H7: =SUM(H3:H6) -> 4 | I7: =SUM(I3:I6) -> 12 | J7: =SUM(J3:J6) -> 7 | ... L7: =SUM(L3:L6) -> 80

Sheet Freq — By Sub-code
A1: Code Frequency by Sub-code × Speech — values update automatically from 'Coded Passages'
A2: Dim | B2: Sub-code | C2: Debate Presidencial 2023 | D2: WEF Davos 2024 | E2: Apertura Sesiones Ordinarias 2024 (142°) | F2: UN General Assembly 79th | G2: WEF Davos 2025 | H2: Apertura Sesiones Ordinarias 2025 (143°) | I2: UN General Assembly 80th | J2: WEF Davos 2026 | K2: Apertura Sesiones Ordinarias 2026 (144°) | L2: TOTAL | N2: Sub-code | O2: Total
A3: D1.1 | B3: =COUNTIFS('Coded Passages'!$B:$B,$A3,'Coded Passages'!$C:$C,$B3,'Coded Passages'!$H:$H,B$2) | C3: =COUNTIFS('Coded Passages'!$B:$B,$A3,'Coded Passages'!$C:$C,$B3,'Coded Passages'!$H:$H,C$2) | D3: =COUNTIFS('Coded Passages'!$B:$B,$A3,'Coded Passages'!$C:$C,$B3,'Coded Passages'!$H:$H,D$2) | E3: =COUNTIFS('Coded Passages'!$B:$B,$A3,'Coded Passages'!$C:$C,$B3,'Coded Passages'!$H:$H,E$2) | F3: =COUNTIFS('Coded Passages'!$B:$B,$A3,'Coded Passages'!$C:$C,$B3,'Coded Passages'!$H:$H,F$2) | G3: =COUNTIFS('Coded Passages'!$B:$B,$A3,'Coded Passages'!$C:$C,$B3,'Coded Passages'!$H:$H,G$2) | H3: =COUNTIFS('Coded Passages'!$B:$B,$A3,'Coded Passages'!$C:$C,$B3,'Coded Passages'!$H:$H,H$2) | I3: =COUNTIFS('Coded Passages'!$B:$B,$A3,'Coded Passages'!$C:$C,$B3,'Coded Passages'!$H:$H,I$2) | J3: =COUNTIFS('Coded Passages'!$B:$B,$A3,'Coded Passages'!$C:$C,$B3,'Coded Passages'!$H:$H,J$2) | L3: =SUM(C3:K3) | N3: D1.1·Sustainability as | O3: =L3
A4: D1.1 | B4: =COUNTIFS('Coded Passages'!$B:$B,$A4,'Coded Passages'!$C:$C,$B4,'Coded Passages'!$H:$H,B$2) | C4: =COUNTIFS('Coded Passages'!$B:$B,$A4,'Coded Passages'!$C:$C,$B4,'Coded Passages'!$H:$H,C$2) | D4: =COUNTIFS('Coded Passages'!$B:$B,$A4,'Coded Passages'!$C:$C,$B4,'Coded Passages'!$H:$H,D$2) | E4: =COUNTIFS('Coded Passages'!$B:$B,$A4,'Coded Passages'!$C:$C,$B4,'Coded Passages'!$H:$H,E$2) | F4: =COUNTIFS('Coded Passages'!$B:$B,$A4,'Coded Passages'!$C:$C,$B4,'Coded Passages'!$H:$H,F$2) | G4: =COUNTIFS('Coded Passages'!$B:$B,$A4,'Coded Passages'!$C:$C,$B4,'Coded Passages'!$H:$H,G$2) | H4: =COUNTIFS('Coded Passages'!$B:$B,$A4,'Coded Passages'!$C:$C,$B4,'Coded Passages'!$H:$H,H$2) | I4: =COUNTIFS('Coded Passages'!$B:$B,$A4,'Coded Passages'!$C:$C,$B4,'Coded Passages'!$H:$H,I$2) | J4: =COUNTIFS('Coded Passages'!$B:$B,$A4,'Coded Passages'!$C:$C,$B4,'Coded Passages'!$H:$H,J$2) | L4: =SUM(C4:K4) | N4: D1.1·Anti-Casta (Elite | O4: =L4
A5: D1.1 | B5: =COUNTIFS('Coded Passages'!$B:$B,$A5,'Coded Passages'!$C:$C,$B5,'Coded Passages'!$H:$H,B$2) | C5: =COUNTIFS('Coded Passages'!$B:$B,$A5,'Coded Passages'!$C:$C,$B5,'Coded Passages'!$H:$H,C$2) | D5: =COUNTIFS('Coded Passages'!$B:$B,$A5,'Coded Passages'!$C:$C,$B5,'Coded Passages'!$H:$H,D$2) | E5: =COUNTIFS('Coded Passages'!$B:$B,$A5,'Coded Passages'!$C:$C,$B5,'Coded Passages'!$H:$H,E$2) | F5: =COUNTIFS('Coded Passages'!$B:$B,$A5,'Coded Passages'!$C:$C,$B5,'Coded Passages'!$H:$H,F$2) | G5: =COUNTIFS('Coded Passages'!$B:$B,$A5,'Coded Passages'!$C:$C,$B5,'Coded Passages'!$H:$H,G$2) | H5: =COUNTIFS('Coded Passages'!$B:$B,$A5,'Coded Passages'!$C:$C,$B5,'Coded Passages'!$H:$H,H$2) | I5: =COUNTIFS('Coded Passages'!$B:$B,$A5,'Coded Passages'!$C:$C,$B5,'Coded Passages'!$H:$H,I$2) | J5: =COUNTIFS('Coded Passages'!$B:$B,$A5,'Coded Passages'!$C:$C,$B5,'Coded Passages'!$H:$H,J$2) | L5: =SUM(C5:K5) | N5: D1.1·Market Primacy | O5: =L5
A6: D1.1 | B6: =COUNTIFS('Coded Passages'!$B:$B,$A6,'Coded Passages'!$C:$C,$B6,'Coded Passages'!$H:$H,B$2) | C6: =COUNTIFS('Coded Passages'!$B:$B,$A6,'Coded Passages'!$C:$C,$B6,'Coded Passages'!$H:$H,C$2) | D6: =COUNTIFS('Coded Passages'!$B:$B,$A6,'Coded Passages'!$C:$C,$B6,'Coded Passages'!$H:$H,D$2) | E6: =COUNTIFS('Coded Passages'!$B:$B,$A6,'Coded Passages'!$C:$C,$B6,'Coded Passages'!$H:$H,E$2) | F6: =COUNTIFS('Coded Passages'!$B:$B,$A6,'Coded Passages'!$C:$C,$B6,'Coded Passages'!$H:$H,F$2) | G6: =COUNTIFS('Coded Passages'!$B:$B,$A6,'Coded Passages'!$C:$C,$B6,'Coded Passages'!$H:$H,G$2) | H6: =COUNTIFS('Coded Passages'!$B:$B,$A6,'Coded Passages'!$C:$C,$B6,'Coded Passages'!$H:$H,H$2) | I6: =COUNTIFS('Coded Passages'!$B:$B,$A6,'Coded Passages'!$C:$C,$B6,'Coded Passages'!$H:$H,I$2) | J6: =COUNTIFS('Coded Passages'!$B:$B,$A6,'Coded Passages'!$C:$C,$B6,'Coded Passages'!$H:$H,J$2) | L6: =SUM(C6:K6) | N6: D1.1·Delegitimization o | O6: =L6
A7: D1.1 | B7: =COUNTIFS('Coded Passages'!$B:$B,$A7,'Coded Passages'!$C:$C,$B7,'Coded Passages'!$H:$H,B$2) | C7: =COUNTIFS('Coded Passages'!$B:$B,$A7,'Coded Passages'!$C:$C,$B7,'Coded Passages'!$H:$H,C$2) | D7: =COUNTIFS('Coded Passages'!$B:$B,$A7,'Coded Passages'!$C:$C,$B7,'Coded Passages'!$H:$H,D$2) | E7: =COUNTIFS('Coded Passages'!$B:$B,$A7,'Coded Passages'!$C:$C,$B7,'Coded Passages'!$H:$H,E$2) | F7: =COUNTIFS('Coded Passages'!$B:$B,$A7,'Coded Passages'!$C:$C,$B7,'Coded Passages'!$H:$H,F$2) | G7: =COUNTIFS('Coded Passages'!$B:$B,$A7,'Coded Passages'!$C:$C,$B7,'Coded Passages'!$H:$H,G$2) | H7: =COUNTIFS('Coded Passages'!$B:$B,$A7,'Coded Passages'!$C:$C,$B7,'Coded Passages'!$H:$H,H$2) | I7: =COUNTIFS('Coded Passages'!$B:$B,$A7,'Coded Passages'!$C:$C,$B7,'Coded Passages'!$H:$H,I$2) | J7: =COUNTIFS('Coded Passages'!$B:$B,$A7,'Coded Passages'!$C:$C,$B7,'Coded Passages'!$H:$H,J$2) | L7: =SUM(C7:K7) | N7: D1.1·Anti-State / Anti- | O7: =L7
A8: D1.1 | B8: =COUNTIFS('Coded Passages'!$B:$B,$A8,'Coded Passages'!$C:$C,$B8,'Coded Passages'!$H:$H,B$2) | C8: =COUNTIFS('Coded Passages'!$B:$B,$A8,'Coded Passages'!$C:$C,$B8,'Coded Passages'!$H:$H,C$2) | D8: =COUNTIFS('Coded Passages'!$B:$B,$A8,'Coded Passages'!$C:$C,$B8,'Coded Passages'!$H:$H,D$2) | E8: =COUNTIFS('Coded Passages'!$B:$B,$A8,'Coded Passages'!$C:$C,$B8,'Coded Passages'!$H:$H,E$2) | F8: =COUNTIFS('Coded Passages'!$B:$B,$A8,'Coded Passages'!$C:$C,$B8,'Coded Passages'!$H:$H,F$2) | G8: =COUNTIFS('Coded Passages'!$B:$B,$A8,'Coded Passages'!$C:$C,$B8,'Coded Passages'!$H:$H,G$2) | H8: =COUNTIFS('Coded Passages'!$B:$B,$A8,'Coded Passages'!$C:$C,$B8,'Coded Passages'!$H:$H,H$2) | I8: =COUNTIFS('Coded Passages'!$B:$B,$A8,'Coded Passages'!$C:$C,$B8,'Coded Passages'!$H:$H,I$2) | J8: =COUNTIFS('Coded Passages'!$B:$B,$A8,'Coded Passages'!$C:$C,$B8,'Coded Passages'!$H:$H,J$2) | L8: =SUM(C8:K8) | N8: D1.1·Rejection of Multi | O8: =L8
A9: D1.2 | B9: =COUNTIFS('Coded Passages'!$B:$B,$A9,'Coded Passages'!$C:$C,$B9,'Coded Passages'!$H:$H,B$2) | C9: =COUNTIFS('Coded Passages'!$B:$B,$A9,'Coded Passages'!$C:$C,$B9,'Coded Passages'!$H:$H,C$2) | D9: =COUNTIFS('Coded Passages'!$B:$B,$A9,'Coded Passages'!$C:$C,$B9,'Coded Passages'!$H:$H,D$2) | E9: =COUNTIFS('Coded Passages'!$B:$B,$A9,'Coded Passages'!$C:$C,$B9,'Coded Passages'!$H:$H,E$2) | F9: =COUNTIFS('Coded Passages'!$B:$B,$A9,'Coded Passages'!$C:$C,$B9,'Coded Passages'!$H:$H,F$2) | G9: =COUNTIFS('Coded Passages'!$B:$B,$A9,'Coded Passages'!$C:$C,$B9,'Coded Passages'!$H:$H,G$2) | H9: =COUNTIFS('Coded Passages'!$B:$B,$A9,'Coded Passages'!$C:$C,$B9,'Coded Passages'!$H:$H,H$2) | I9: =COUNTIFS('Coded Passages'!$B:$B,$A9,'Coded Passages'!$C:$C,$B9,'Coded Passages'!$H:$H,I$2) | J9: =COUNTIFS('Coded Passages'!$B:$B,$A9,'Coded Passages'!$C:$C,$B9,'Coded Passages'!$H:$H,J$2) | L9: =SUM(C9:K9) | N9: D1.2·Climate Skepticism | O9: =L9
A10: D1.2 | B10: =COUNTIFS('Coded Passages'!$B:$B,$A10,'Coded Passages'!$C:$C,$B10,'Coded Passages'!$H:$H,B$2) | C10: =COUNTIFS('Coded Passages'!$B:$B,$A10,'Coded Passages'!$C:$C,$B10,'Coded Passages'!$H:$H,C$2) | D10: =COUNTIFS('Coded Passages'!$B:$B,$A10,'Coded Passages'!$C:$C,$B10,'Coded Passages'!$H:$H,D$2) | E10: =COUNTIFS('Coded Passages'!$B:$B,$A10,'Coded Passages'!$C:$C,$B10,'Coded Passages'!$H:$H,E$2) | F10: =COUNTIFS('Coded Passages'!$B:$B,$A10,'Coded Passages'!$C:$C,$B10,'Coded Passages'!$H:$H,F$2) | G10: =COUNTIFS('Coded Passages'!$B:$B,$A10,'Coded Passages'!$C:$C,$B10,'Coded Passages'!$H:$H,G$2) | H10: =COUNTIFS('Coded Passages'!$B:$B,$A10,'Coded Passages'!$C:$C,$B10,'Coded Passages'!$H:$H,H$2) | I10: =COUNTIFS('Coded Passages'!$B:$B,$A10,'Coded Passages'!$C:$C,$B10,'Coded Passages'!$H:$H,I$2) | J10: =COUNTIFS('Coded Passages'!$B:$B,$A10,'Coded Passages'!$C:$C,$B10,'Coded Passages'!$H:$H,J$2) | L10: =SUM(C10:K10) | N10: D1.2·Attack on Experts | O10: =L10
A11: D1.2 | B11: =COUNTIFS('Coded Passages'!$B:$B,$A11,'Coded Passages'!$C:$C,$B11,'Coded Passages'!$H:$H,B$2) | C11: =COUNTIFS('Coded Passages'!$B:$B,$A11,'Coded Passages'!$C:$C,$B11,'Coded Passages'!$H:$H,C$2) | D11: =COUNTIFS('Coded Passages'!$B:$B,$A11,'Coded Passages'!$C:$C,$B11,'Coded Passages'!$H:$H,D$2) | E11: =COUNTIFS('Coded Passages'!$B:$B,$A11,'Coded Passages'!$C:$C,$B11,'Coded Passages'!$H:$H,E$2) | F11: =COUNTIFS('Coded Passages'!$B:$B,$A11,'Coded Passages'!$C:$C,$B11,'Coded Passages'!$H:$H,F$2) | G11: =COUNTIFS('Coded Passages'!$B:$B,$A11,'Coded Passages'!$C:$C,$B11,'Coded Passages'!$H:$H,G$2) | H11: =COUNTIFS('Coded Passages'!$B:$B,$A11,'Coded Passages'!$C:$C,$B11,'Coded Passages'!$H:$H,H$2) | I11: =COUNTIFS('Coded Passages'!$B:$B,$A11,'Coded Passages'!$C:$C,$B11,'Coded Passages'!$H:$H,I$2) | J11: =COUNTIFS('Coded Passages'!$B:$B,$A11,'Coded Passages'!$C:$C,$B11,'Coded Passages'!$H:$H,J$2) | L11: =SUM(C11:K11) | N11: D1.2·Selective Empirici | O11: =L11
A12: D1.2 | B12: =COUNTIFS('Coded Passages'!$B:$B,$A12,'Coded Passages'!$C:$C,$B12,'Coded Passages'!$H:$H,B$2) | C12: =COUNTIFS('Coded Passages'!$B:$B,$A12,'Coded Passages'!$C:$C,$B12,'Coded Passages'!$H:$H,C$2) | D12: =COUNTIFS('Coded Passages'!$B:$B,$A12,'Coded Passages'!$C:$C,$B12,'Coded Passages'!$H:$H,D$2) | E12: =COUNTIFS('Coded Passages'!$B:$B,$A12,'Coded Passages'!$C:$C,$B12,'Coded Passages'!$H:$H,E$2) | F12: =COUNTIFS('Coded Passages'!$B:$B,$A12,'Coded Passages'!$C:$C,$B12,'Coded Passages'!$H:$H,F$2) | G12: =COUNTIFS('Coded Passages'!$B:$B,$A12,'Coded Passages'!$C:$C,$B12,'Coded Passages'!$H:$H,G$2) | H12: =COUNTIFS('Coded Passages'!$B:$B,$A12,'Coded Passages'!$C:$C,$B12,'Coded Passages'!$H:$H,H$2) | I12: =COUNTIFS('Coded Passages'!$B:$B,$A12,'Coded Passages'!$C:$C,$B12,'Coded Passages'!$H:$H,I$2) | J12: =COUNTIFS('Coded Passages'!$B:$B,$A12,'Coded Passages'!$C:$C,$B12,'Coded Passages'!$H:$H,J$2) | L12: =SUM(C12:K12) | N12: D1.2·Pseudo-Science / I | O12: =L12
A13: D1.2 | B13: =COUNTIFS('Coded Passages'!$B:$B,$A13,'Coded Passages'!$C:$C,$B13,'Coded Passages'!$H:$H,B$2) | C13: =COUNTIFS('Coded Passages'!$B:$B,$A13,'Coded Passages'!$C:$C,$B13,'Coded Passages'!$H:$H,C$2) | D13: =COUNTIFS('Coded Passages'!$B:$B,$A13,'Coded Passages'!$C:$C,$B13,'Coded Passages'!$H:$H,D$2) | E13: =COUNTIFS('Coded Passages'!$B:$B,$A13,'Coded Passages'!$C:$C,$B13,'Coded Passages'!$H:$H,E$2) | F13: =COUNTIFS('Coded Passages'!$B:$B,$A13,'Coded Passages'!$C:$C,$B13,'Coded Passages'!$H:$H,F$2) | G13: =COUNTIFS('Coded Passages'!$B:$B,$A13,'Coded Passages'!$C:$C,$B13,'Coded Passages'!$H:$H,G$2) | H13: =COUNTIFS('Coded Passages'!$B:$B,$A13,'Coded Passages'!$C:$C,$B13,'Coded Passages'!$H:$H,H$2) | I13: =COUNTIFS('Coded Passages'!$B:$B,$A13,'Coded Passages'!$C:$C,$B13,'Coded Passages'!$H:$H,I$2) | J13: =COUNTIFS('Coded Passages'!$B:$B,$A13,'Coded Passages'!$C:$C,$B13,'Coded Passages'!$H:$H,J$2) | L13: =SUM(C13:K13) | N13: D1.2·Attack on Universi | O13: =L13
A14: D1.3 | B14: =COUNTIFS('Coded Passages'!$B:$B,$A14,'Coded Passages'!$C:$C,$B14,'Coded Passages'!$H:$H,B$2) | C14: =COUNTIFS('Coded Passages'!$B:$B,$A14,'Coded Passages'!$C:$C,$B14,'Coded Passages'!$H:$H,C$2) | D14: =COUNTIFS('Coded Passages'!$B:$B,$A14,'Coded Passages'!$C:$C,$B14,'Coded Passages'!$H:$H,D$2) | E14: =COUNTIFS('Coded Passages'!$B:$B,$A14,'Coded Passages'!$C:$C,$B14,'Coded Passages'!$H:$H,E$2) | F14: =COUNTIFS('Coded Passages'!$B:$B,$A14,'Coded Passages'!$C:$C,$B14,'Coded Passages'!$H:$H,F$2) | G14: =COUNTIFS('Coded Passages'!$B:$B,$A14,'Coded Passages'!$C:$C,$B14,'Coded Passages'!$H:$H,G$2) | H14: =COUNTIFS('Coded Passages'!$B:$B,$A14,'Coded Passages'!$C:$C,$B14,'Coded Passages'!$H:$H,H$2) | I14: =COUNTIFS('Coded Passages'!$B:$B,$A14,'Coded Passages'!$C:$C,$B14,'Coded Passages'!$H:$H,I$2) | J14: =COUNTIFS('Coded Passages'!$B:$B,$A14,'Coded Passages'!$C:$C,$B14,'Coded Passages'!$H:$H,J$2) | L14: =SUM(C14:K14) | N14: D1.3·Civilizational Def | O14: =L14
... A16: D1.3 | B16: =COUNTIFS('Coded Passages'!$B:$B,$A16,'Coded Passages'!$C:$C,$B16,'Coded Passages'!$H:$H,B$2) | C16: =COUNTIFS('Coded Passages'!$B:$B,$A16,'Coded Passages'!$C:$C,$B16,'Coded Passages'!$H:$H,C$2) | D16: =COUNTIFS('Coded Passages'!$B:$B,$A16,'Coded Passages'!$C:$C,$B16,'Coded Passages'!$H:$H,D$2) | E16: =COUNTIFS('Coded Passages'!$B:$B,$A16,'Coded Passages'!$C:$C,$B16,'Coded Passages'!$H:$H,E$2) | F16: =COUNTIFS('Coded Passages'!$B:$B,$A16,'Coded Passages'!$C:$C,$B16,'Coded Passages'!$H:$H,F$2) | G16: =COUNTIFS('Coded Passages'!$B:$B,$A16,'Coded Passages'!$C:$C,$B16,'Coded Passages'!$H:$H,G$2) | H16: =COUNTIFS('Coded Passages'!$B:$B,$A16,'Coded Passages'!$C:$C,$B16,'Coded Passages'!$H:$H,H$2) | I16: =COUNTIFS('Coded Passages'!$B:$B,$A16,'Coded Passages'!$C:$C,$B16,'Coded Passages'!$H:$H,I$2) | J16: =COUNTIFS('Coded Passages'!$B:$B,$A16,'Coded Passages'!$C:$C,$B16,'Coded Passages'!$H:$H,J$2) | L16: =SUM(C16:K16) | N16: D1.3·Anti-Socialism / A | O16: =L16
A17: TOTAL | B17: All Sub-codes | C17: =SUM(C3:C16) | D17: =SUM(D3:D16) | E17: =SUM(E3:E16) | F17: =SUM(F3:F16) | G17: =SUM(G3:G16) | H17: =SUM(H3:H16) | I17: =SUM(I3:I16) | J17: =SUM(J3:J16) | ... L17: =SUM(L3:L16)

Sheet Speech Overview
A1: Speech-Level Overview -- D1 / Inductive counts update automatically from 'Coded Passages' (D2 = 0 in v4)
A2: Speech | B2: Date | C2: Venue | D2: Type | E2: Scope | F2: D1 Codes | G2: D2 Codes | H2: Inductive | I2: Total | J2: Notes
A3: Debate Presidencial 2023 | B3: 2023-10-08 | C3: Buenos Aires | D3: Debate presidencial | E3: National | F3: =COUNTIFS('Coded Passages'!$H:$H,$A3,'Coded Passages'!$B:$B,"D1*") -> 3 | G3: =COUNTIFS('Coded Passages'!$H:$H,$A3,'Coded Passages'!$B:$B,"D2*") -> 0 | H3: =COUNTIFS('Coded Passages'!$H:$H,$A3,'Coded Passages'!$B:$B,"IND") -> 0 | I3: =F3+G3+H3 -> 3 | J3: D2=0 in v4 (speech corpus)
A4: WEF Davos 2024 | B4: 2024-01-17 | C4: Davos, Suiza | D4: Foro económico internacional | E4: International | F4: =COUNTIFS('Coded Passages'!$H:$H,$A4,'Coded Passages'!$B:$B,"D1*") -> 19 | G4: =COUNTIFS('Coded Passages'!$H:$H,$A4,'Coded Passages'!$B:$B,"D2*") -> 0 | H4: =COUNTIFS('Coded Passages'!$H:$H,$A4,'Coded Passages'!$B:$B,"IND") -> 0 | I4: =F4+G4+H4 -> 19 | J4: D2=0 in v4 (speech corpus)
A5: Apertura Sesiones Ordinarias 2024 (142°) | B5: 2024-03-01 | C5: Buenos Aires (Congreso) | D5: Acto institucional | E5: National | F5: =COUNTIFS('Coded Passages'!$H:$H,$A5,'Coded Passages'!$B:$B,"D1*") -> 3 | G5: =COUNTIFS('Coded Passages'!$H:$H,$A5,'Coded Passages'!$B:$B,"D2*") -> 0 | H5: =COUNTIFS('Coded Passages'!$H:$H,$A5,'Coded Passages'!$B:$B,"IND") -> 0 | I5: =F5+G5+H5 -> 3 | J5: D2=0 in v4 (speech corpus)
A6: UN General Assembly 79th | B6: 2024-09-24 | C6: Nueva York, EE.UU. | D6: Cumbre internacional | E6: International | F6: =COUNTIFS('Coded Passages'!$H:$H,$A6,'Coded Passages'!$B:$B,"D1*") -> 13 | G6: =COUNTIFS('Coded Passages'!$H:$H,$A6,'Coded Passages'!$B:$B,"D2*") -> 0 | H6: =COUNTIFS('Coded Passages'!$H:$H,$A6,'Coded Passages'!$B:$B,"IND") -> 0 | I6: =F6+G6+H6 -> 13 | J6: D2=0 in v4 (speech corpus)
A7: WEF Davos 2025 | B7: 2025-01-23 | C7: Davos, Suiza | D7: Foro económico internacional | E7: International | F7: =COUNTIFS('Coded Passages'!$H:$H,$A7,'Coded Passages'!$B:$B,"D1*") -> 19 | G7: =COUNTIFS('Coded Passages'!$H:$H,$A7,'Coded Passages'!$B:$B,"D2*") -> 0 | H7: =COUNTIFS('Coded Passages'!$H:$H,$A7,'Coded Passages'!$B:$B,"IND") -> 0 | I7: =F7+G7+H7 -> 19 | J7: D2=0 in v4 (speech corpus)
A8: Apertura Sesiones Ordinarias 2025 (143°) | B8: 2025-03-01 | C8: Buenos Aires (Congreso) | D8: Acto institucional | E8: National | F8: =COUNTIFS('Coded Passages'!$H:$H,$A8,'Coded Passages'!$B:$B,"D1*") -> 4 | G8: =COUNTIFS('Coded Passages'!$H:$H,$A8,'Coded Passages'!$B:$B,"D2*") -> 0 | H8: =COUNTIFS('Coded Passages'!$H:$H,$A8,'Coded Passages'!$B:$B,"IND") -> 0 | I8: =F8+G8+H8 -> 4 | J8: D2=0 in v4 (speech corpus)
A9: UN General Assembly 80th | B9: 2025-09-24 | C9: Nueva York, EE.UU. | D9: Cumbre internacional | E9: International | F9: =COUNTIFS('Coded Passages'!$H:$H,$A9,'Coded Passages'!$B:$B,"D1*") -> 12 | G9: =COUNTIFS('Coded Passages'!$H:$H,$A9,'Coded Passages'!$B:$B,"D2*") -> 0 | H9: =COUNTIFS('Coded Passages'!$H:$H,$A9,'Coded Passages'!$B:$B,"IND") -> 0 | I9: =F9+G9+H9 -> 12 | J9: D2=0 in v4 (speech corpus)
A10: WEF Davos 2026 | B10: 2026-01-22 | C10: Davos, Suiza | D10: Foro económico internacional | E10: International | F10: =COUNTIFS('Coded Passages'!$H:$H,$A10,'Coded Passages'!$B:$B,"D1*") -> 7 | G10: =COUNTIFS('Coded Passages'!$H:$H,$A10,'Coded Passages'!$B:$B,"D2*") -> 0 | H10: =COUNTIFS('Coded Passages'!$H:$H,$A10,'Coded Passages'!$B:$B,"IND") -> 0 | I10: =F10+G10+H10 -> 7 | J10: D2=0 in v4 (speech corpus)
A11: Apertura Sesiones Ordinarias 2026 (144°) | B11: 2026-03-01 | C11: Buenos Aires (Congreso) | D11: Acto institucional | E11: National | F11: =COUNTIFS('Coded Passages'!$H:$H,$A11,'Coded Passages'!$B:$B,"D1*") -> 8 | G11: =COUNTIFS('Coded Passages'!$H:$H,$A11,'Coded Passages'!$B:$B,"D2*") -> 0 | H11: =COUNTIFS('Coded Passages'!$H:$H,$A11,'Coded Passages'!$B:$B,"IND") -> 0 | I11: =F11+G11+H11 -> 8 | J11: D2=0 in v4 (speech corpus)
A12: TOTAL | F12: =SUM(F3:F11) -> 88 | G12: =SUM(G3:G11) -> 0 | H12: =SUM(H3:H11) -> 0 | I12: =SUM(I3:I11) -> 88

Sheet Freq — By Scope
A1: Code Frequency by Scope — values update automatically from 'Coded Passages'
A2: Dimension | B2: Dimension (Full) | C2: National | D2: International | E2: TOTAL | G2: Scope | H2: Total
A3: D1.1 | B3: D1.1 — State Intervention & Governance | C3: =COUNTIFS('Coded Passages'!$B:$B,$A3,'Coded Passages'!$L:$L,"National") -> 13 | D3: =COUNTIFS('Coded Passages'!$B:$B,$A3,'Coded Passages'!$L:$L,"International") -> 42 | E3: =SUM(C3:D3) -> 55 | G3: D1.1 | H3: =E3 -> 55
A4: D1.2 | B4: D1.2 — Public Science & Expertise | C4: =COUNTIFS('Coded Passages'!$B:$B,$A4,'Coded Passages'!$L:$L,"National") -> 3 | D4: =COUNTIFS('Coded Passages'!$B:$B,$A4,'Coded Passages'!$L:$L,"International") -> 13 | E4: =SUM(C4:D4) -> 16 | G4: D1.2 | H4: =E4 -> 16
A5: D1.3 | B5: D1.3 — Cultural Backlash | C5: =COUNTIFS('Coded Passages'!$B:$B,$A5,'Coded Passages'!$L:$L,"National") -> 2 | D5: =COUNTIFS('Coded Passages'!$B:$B,$A5,'Coded Passages'!$L:$L,"International") -> 15 | E5: =SUM(C5:D5) -> 17 | G5: D1.3 | H5: =E5 -> 17
A6: IND | B6: Inductive | C6: =COUNTIFS('Coded Passages'!$B:$B,$A6,'Coded Passages'!$L:$L,"National") -> 0 | D6: =COUNTIFS('Coded Passages'!$B:$B,$A6,'Coded Passages'!$L:$L,"International") -> 0 | E6: =SUM(C6:D6) -> 0 | G6: IND | H6: =E6 -> 0
A7: TOTAL | B7: All Dimensions | C7: =SUM(C3:C6) -> 18 | D7: =SUM(D3:D6) -> 70 | E7: =SUM(E3:E6) -> 88
A29: Sub-code Detail × Scope
A30: Dim | B30: Sub-code | C30: National | D30: International | E30: TOTAL
A31: D1.1 | B31: Anti-Casta (Elite Frame) | C31: =COUNTIFS('Coded Passages'!$B:$B,$A31,'Coded Passages'!$C:$C,$B31,'Coded Passages'!$L:$L,"National") -> 2 | D31: =COUNTIFS('Coded Passages'!$B:$B,$A31,'Coded Passages'!$C:$C,$B31,'Coded Passages'!$L:$L,"International") -> 2 | E31: =SUM(C31:D31) -> 4
A32: D1.1 | B32: Anti-State / Anti-Bureaucratic | C32: =COUNTIFS('Coded Passages'!$B:$B,$A32,'Coded Passages'!$C:$C,$B32,'Coded Passages'!$L:$L,"National") -> 1 | D32: =COUNTIFS('Coded Passages'!$B:$B,$A32,'Coded Passages'!$C:$C,$B32,'Coded Passages'!$L:$L,"International") -> 4 | E32: =SUM(C32:D32) -> 5
A33: D1.1 | B33: Delegitimization of Regulation | C33: =COUNTIFS('Coded Passages'!$B:$B,$A33,'Coded Passages'!$C:$C,$B33,'Coded Passages'!$L:$L,"National") -> 5 | D33: =COUNTIFS('Coded Passages'!$B:$B,$A33,'Coded Passages'!$C:$C,$B33,'Coded Passages'!$L:$L,"International") -> 13 | E33: =SUM(C33:D33) -> 18
A34: D1.1 | B34: Market Primacy | C34: =COUNTIFS('Coded Passages'!$B:$B,$A34,'Coded Passages'!$C:$C,$B34,'Coded Passages'!$L:$L,"National") -> 1 | D34: =COUNTIFS('Coded Passages'!$B:$B,$A34,'Coded Passages'!$C:$C,$B34,'Coded Passages'!$L:$L,"International") -> 5 | E34: =SUM(C34:D34) -> 6
A35: D1.1 | B35: Rejection of Multilateral Governance | C35: =COUNTIFS('Coded Passages'!$B:$B,$A35,'Coded Passages'!$C:$C,$B35,'Coded Passages'!$L:$L,"National") -> 2 | D35: =COUNTIFS('Coded Passages'!$B:$B,$A35,'Coded Passages'!$C:$C,$B35,'Coded Passages'!$L:$L,"International") -> 13 | E35: =SUM(C35:D35) -> 15
A36: D1.1 | B36: Sustainability as Ideological or Harmful | C36: =COUNTIFS('Coded Passages'!$B:$B,$A36,'Coded Passages'!$C:$C,$B36,'Coded Passages'!$L:$L,"National") -> 2 | D36: =COUNTIFS('Coded Passages'!$B:$B,$A36,'Coded Passages'!$C:$C,$B36,'Coded Passages'!$L:$L,"International") -> 5 | E36: =SUM(C36:D36) -> 7
A37: D1.2 | B37: Attack on Universities & Research Institutions | C37: =COUNTIFS('Coded Passages'!$B:$B,$A37,'Coded Passages'!$C:$C,$B37,'Coded Passages'!$L:$L,"National") -> 1 | D37: =COUNTIFS('Coded Passages'!$B:$B,$A37,'Coded Passages'!$C:$C,$B37,'Coded Passages'!$L:$L,"International") -> 2 | E37: =SUM(C37:D37) -> 3
A38: D1.2 | B38: Attack on Experts & Technocrats | C38: =COUNTIFS('Coded Passages'!$B:$B,$A38,'Coded Passages'!$C:$C,$B38,'Coded Passages'!$L:$L,"National") -> 1 | D38: =COUNTIFS('Coded Passages'!$B:$B,$A38,'Coded Passages'!$C:$C,$B38,'Coded Passages'!$L:$L,"International") -> 5 | E38: =SUM(C38:D38) -> 6
A39: D1.2 | B39: Climate Skepticism or Dismissal | C39: =COUNTIFS('Coded Passages'!$B:$B,$A39,'Coded Passages'!$C:$C,$B39,'Coded Passages'!$L:$L,"National") -> 1 | D39: =COUNTIFS('Coded Passages'!$B:$B,$A39,'Coded Passages'!$C:$C,$B39,'Coded Passages'!$L:$L,"International") -> 1 | E39: =SUM(C39:D39) -> 2
A40: D1.2 | B40: Pseudo-Science / Ideological Science | C40: =COUNTIFS('Coded Passages'!$B:$B,$A40,'Coded Passages'!$C:$C,$B40,'Coded Passages'!$L:$L,"National") -> 0 | D40: =COUNTIFS('Coded Passages'!$B:$B,$A40,'Coded Passages'!$C:$C,$B40,'Coded Passages'!$L:$L,"International") -> 3 | E40: =SUM(C40:D40) -> 3
A41: D1.2 | B41: Selective Empiricism | C41: =COUNTIFS('Coded Passages'!$B:$B,$A41,'Coded Passages'!$C:$C,$B41,'Coded Passages'!$L:$L,"National") -> 0 | D41: =COUNTIFS('Coded Passages'!$B:$B,$A41,'Coded Passages'!$C:$C,$B41,'Coded Passages'!$L:$L,"International") -> 2 | E41: =SUM(C41:D41) -> 2
A42: D1.3 | B42: Civilizational Defense | C42: =COUNTIFS('Coded Passages'!$B:$B,$A42,'Coded Passages'!$C:$C,$B42,'Coded Passages'!$L:$L,"National") -> 1 | D42: =COUNTIFS('Coded Passages'!$B:$B,$A42,'Coded Passages'!$C:$C,$B42,'Coded Passages'!$L:$L,"International") -> 7 | E42: =SUM(C42:D42) -> 8
... A44: D1.3 | B44: Woke Bundling | C44: =COUNTIFS('Coded Passages'!$B:$B,$A44,'Coded Passages'!$C:$C,$B44,'Coded Passages'!$L:$L,"National") -> 0 | D44: =COUNTIFS('Coded Passages'!$B:$B,$A44,'Coded Passages'!$C:$C,$B44,'Coded Passages'!$L:$L,"International") -> 5 | E44: =SUM(C44:D44) -> 5
A45: TOTAL | B45: All Sub-codes | C45: =SUM(C31:C44) -> 18 | D45: =SUM(D31:D44) -> 70 | E45: =SUM(E31:E44) -> 88

Sheet Freq — By Venue Type
A1: Code Frequency by Venue Type — values update automatically from 'Coded Passages'
A2: Dimension | B2: Dimension (Full) | C2: Debate presidencial | D2: Foro económico internacional | E2: Acto institucional | F2: Cumbre internacional | G2: TOTAL | I2: Venue Type | J2: Total
A3: D1.1 | B3: D1.1 — State Intervention & Governance | C3: =COUNTIFS('Coded Passages'!$B:$B,$A3,'Coded Passages'!$K:$K,"Debate presidencial") -> 1 | D3: =COUNTIFS('Coded Passages'!$B:$B,$A3,'Coded Passages'!$K:$K,"Foro económico internacional") -> 25 | E3: =COUNTIFS('Coded Passages'!$B:$B,$A3,'Coded Passages'!$K:$K,"Acto institucional") -> 12 | F3: =COUNTIFS('Coded Passages'!$B:$B,$A3,'Coded Passages'!$K:$K,"Cumbre internacional") -> 17 | G3: =SUM(C3:F3) -> 55 | I3: D1.1 | J3: =G3 -> 55
A4: D1.2 | B4: D1.2 — Public Science & Expertise | C4: =COUNTIFS('Coded Passages'!$B:$B,$A4,'Coded Passages'!$K:$K,"Debate presidencial") -> 2 | D4: =COUNTIFS('Coded Passages'!$B:$B,$A4,'Coded Passages'!$K:$K,"Foro económico internacional") -> 10 | E4: =COUNTIFS('Coded Passages'!$B:$B,$A4,'Coded Passages'!$K:$K,"Acto institucional") -> 1 | F4: =COUNTIFS('Coded Passages'!$B:$B,$A4,'Coded Passages'!$K:$K,"Cumbre internacional") -> 3 | G4: =SUM(C4:F4) -> 16 | I4: D1.2 | J4: =G4 -> 16
A5: D1.3 | B5: D1.3 — Cultural Backlash | C5: =COUNTIFS('Coded Passages'!$B:$B,$A5,'Coded Passages'!$K:$K,"Debate presidencial") -> 0 | D5: =COUNTIFS('Coded Passages'!$B:$B,$A5,'Coded Passages'!$K:$K,"Foro económico internacional") -> 10 | E5: =COUNTIFS('Coded Passages'!$B:$B,$A5,'Coded Passages'!$K:$K,"Acto institucional") -> 2 | F5: =COUNTIFS('Coded Passages'!$B:$B,$A5,'Coded Passages'!$K:$K,"Cumbre internacional") -> 5 | G5: =SUM(C5:F5) -> 17 | I5: D1.3 | J5: =G5 -> 17
A6: IND | B6: Inductive | C6: =COUNTIFS('Coded Passages'!$B:$B,$A6,'Coded Passages'!$K:$K,"Debate presidencial") -> 0 | D6: =COUNTIFS('Coded Passages'!$B:$B,$A6,'Coded Passages'!$K:$K,"Foro económico internacional") -> 0 | E6: =COUNTIFS('Coded Passages'!$B:$B,$A6,'Coded Passages'!$K:$K,"Acto institucional") -> 0 | F6: =COUNTIFS('Coded Passages'!$B:$B,$A6,'Coded Passages'!$K:$K,"Cumbre internacional") -> 0 | G6: =SUM(C6:F6) -> 0 | I6: IND | J6: =G6 -> 0
A7: TOTAL | B7: All Dimensions | C7: =SUM(C3:C6) -> 3 | D7: =SUM(D3:D6) -> 45 | E7: =SUM(E3:E6) -> 15 | F7: =SUM(F3:F6) -> 25 | G7: =SUM(G3:G6) -> 88
A29: Sub-code Detail × Venue Type
A30: Dim | B30: Sub-code | C30: Debate presidencial | D30: Foro económico internacional | E30: Acto institucional | F30: Cumbre internacional | G30: TOTAL
A31: D1.1 | B31: Anti-Casta (Elite Frame) | C31: =COUNTIFS('Coded Passages'!$B:$B,$A31,'Coded Passages'!$C:$C,$B31,'Coded Passages'!$K:$K,"Debate presidencial") -> 0 | D31: =COUNTIFS('Coded Passages'!$B:$B,$A31,'Coded Passages'!$C:$C,$B31,'Coded Passages'!$K:$K,"Foro económico internacional") -> 2 | E31: =COUNTIFS('Coded Passages'!$B:$B,$A31,'Coded Passages'!$C:$C,$B31,'Coded Passages'!$K:$K,"Acto institucional") -> 2 | F31: =COUNTIFS('Coded Passages'!$B:$B,$A31,'Coded Passages'!$C:$C,$B31,'Coded Passages'!$K:$K,"Cumbre internacional") -> 0 | G31: =SUM(C31:F31) -> 4
A32: D1.1 | B32: Anti-State / Anti-Bureaucratic | C32: =COUNTIFS('Coded Passages'!$B:$B,$A32,'Coded Passages'!$C:$C,$B32,'Coded Passages'!$K:$K,"Debate presidencial") -> 0 | D32: =COUNTIFS('Coded Passages'!$B:$B,$A32,'Coded Passages'!$C:$C,$B32,'Coded Passages'!$K:$K,"Foro económico internacional") -> 1 | E32: =COUNTIFS('Coded Passages'!$B:$B,$A32,'Coded Passages'!$C:$C,$B32,'Coded Passages'!$K:$K,"Acto institucional") -> 1 | F32: =COUNTIFS('Coded Passages'!$B:$B,$A32,'Coded Passages'!$C:$C,$B32,'Coded Passages'!$K:$K,"Cumbre internacional") -> 3 | G32: =SUM(C32:F32) -> 5
A33: D1.1 | B33: Delegitimization of Regulation | C33: =COUNTIFS('Coded Passages'!$B:$B,$A33,'Coded Passages'!$C:$C,$B33,'Coded Passages'!$K:$K,"Debate presidencial") -> 0 | D33: =COUNTIFS('Coded Passages'!$B:$B,$A33,'Coded Passages'!$C:$C,$B33,'Coded Passages'!$K:$K,"Foro económico internacional") -> 12 | E33: =COUNTIFS('Coded Passages'!$B:$B,$A33,'Coded Passages'!$C:$C,$B33,'Coded Passages'!$K:$K,"Acto institucional") -> 5 | F33: =COUNTIFS('Coded Passages'!$B:$B,$A33,'Coded Passages'!$C:$C,$B33,'Coded Passages'!$K:$K,"Cumbre internacional") -> 1 | G33: =SUM(C33:F33) -> 18
A34: D1.1 | B34: Market Primacy | C34: =COUNTIFS('Coded Passages'!$B:$B,$A34,'Coded Passages'!$C:$C,$B34,'Coded Passages'!$K:$K,"Debate presidencial") -> 0 | D34: =COUNTIFS('Coded Passages'!$B:$B,$A34,'Coded Passages'!$C:$C,$B34,'Coded Passages'!$K:$K,"Foro económico internacional") -> 5 | E34: =COUNTIFS('Coded Passages'!$B:$B,$A34,'Coded Passages'!$C:$C,$B34,'Coded Passages'!$K:$K,"Acto institucional") -> 1 | F34: =COUNTIFS('Coded Passages'!$B:$B,$A34,'Coded Passages'!$C:$C,$B34,'Coded Passages'!$K:$K,"Cumbre internacional") -> 0 | G34: =SUM(C34:F34) -> 6
A35: D1.1 | B35: Rejection of Multilateral Governance | C35: =COUNTIFS('Coded Passages'!$B:$B,$A35,'Coded Passages'!$C:$C,$B35,'Coded Passages'!$K:$K,"Debate presidencial") -> 0 | D35: =COUNTIFS('Coded Passages'!$B:$B,$A35,'Coded Passages'!$C:$C,$B35,'Coded Passages'!$K:$K,"Foro económico internacional") -> 4 | E35: =COUNTIFS('Coded Passages'!$B:$B,$A35,'Coded Passages'!$C:$C,$B35,'Coded Passages'!$K:$K,"Acto institucional") -> 2 | F35: =COUNTIFS('Coded Passages'!$B:$B,$A35,'Coded Passages'!$C:$C,$B35,'Coded Passages'!$K:$K,"Cumbre internacional") -> 9 | G35: =SUM(C35:F35) -> 15
A36: D1.1 | B36: Sustainability as Ideological or Harmful | C36: =COUNTIFS('Coded Passages'!$B:$B,$A36,'Coded Passages'!$C:$C,$B36,'Coded Passages'!$K:$K,"Debate presidencial") -> 1 | D36: =COUNTIFS('Coded Passages'!$B:$B,$A36,'Coded Passages'!$C:$C,$B36,'Coded Passages'!$K:$K,"Foro económico internacional") -> 1 | E36: =COUNTIFS('Coded Passages'!$B:$B,$A36,'Coded Passages'!$C:$C,$B36,'Coded Passages'!$K:$K,"Acto institucional") -> 1 | F36: =COUNTIFS('Coded Passages'!$B:$B,$A36,'Coded Passages'!$C:$C,$B36,'Coded Passages'!$K:$K,"Cumbre internacional") -> 4 | G36: =SUM(C36:F36) -> 7
A37: D1.2 | B37: Attack on Universities & Research Institutions | C37: =COUNTIFS('Coded Passages'!$B:$B,$A37,'Coded Passages'!$C:$C,$B37,'Coded Passages'!$K:$K,"Debate presidencial") -> 0 | D37: =COUNTIFS('Coded Passages'!$B:$B,$A37,'Coded Passages'!$C:$C,$B37,'Coded Passages'!$K:$K,"Foro económico internacional") -> 2 | E37: =COUNTIFS('Coded Passages'!$B:$B,$A37,'Coded Passages'!$C:$C,$B37,'Coded Passages'!$K:$K,"Acto institucional") -> 1 | F37: =COUNTIFS('Coded Passages'!$B:$B,$A37,'Coded Passages'!$C:$C,$B37,'Coded Passages'!$K:$K,"Cumbre internacional") -> 0 | G37: =SUM(C37:F37) -> 3
A38: D1.2 | B38: Attack on Experts & Technocrats | C38: =COUNTIFS('Coded Passages'!$B:$B,$A38,'Coded Passages'!$C:$C,$B38,'Coded Passages'!$K:$K,"Debate presidencial") -> 1 | D38: =COUNTIFS('Coded Passages'!$B:$B,$A38,'Coded Passages'!$C:$C,$B38,'Coded Passages'!$K:$K,"Foro económico internacional") -> 2 | E38: =COUNTIFS('Coded Passages'!$B:$B,$A38,'Coded Passages'!$C:$C,$B38,'Coded Passages'!$K:$K,"Acto institucional") -> 0 | F38: =COUNTIFS('Coded Passages'!$B:$B,$A38,'Coded Passages'!$C:$C,$B38,'Coded Passages'!$K:$K,"Cumbre internacional") -> 3 | G38: =SUM(C38:F38) -> 6
A39: D1.2 | B39: Climate Skepticism or Dismissal | C39: =COUNTIFS('Coded Passages'!$B:$B,$A39,'Coded Passages'!$C:$C,$B39,'Coded Passages'!$K:$K,"Debate presidencial") -> 1 | D39: =COUNTIFS('Coded Passages'!$B:$B,$A39,'Coded Passages'!$C:$C,$B39,'Coded Passages'!$K:$K,"Foro económico internacional") -> 1 | E39: =COUNTIFS('Coded Passages'!$B:$B,$A39,'Coded Passages'!$C:$C,$B39,'Coded Passages'!$K:$K,"Acto institucional") -> 0 | F39: =COUNTIFS('Coded Passages'!$B:$B,$A39,'Coded Passages'!$C:$C,$B39,'Coded Passages'!$K:$K,"Cumbre internacional") -> 0 | G39: =SUM(C39:F39) -> 2
A40: D1.2 | B40: Pseudo-Science / Ideological Science | C40: =COUNTIFS('Coded Passages'!$B:$B,$A40,'Coded Passages'!$C:$C,$B40,'Coded Passages'!$K:$K,"Debate presidencial") -> 0 | D40: =COUNTIFS('Coded Passages'!$B:$B,$A40,'Coded Passages'!$C:$C,$B40,'Coded Passages'!$K:$K,"Foro económico internacional") -> 3 | E40: =COUNTIFS('Coded Passages'!$B:$B,$A40,'Coded Passages'!$C:$C,$B40,'Coded Passages'!$K:$K,"Acto institucional") -> 0 | F40: =COUNTIFS('Coded Passages'!$B:$B,$A40,'Coded Passages'!$C:$C,$B40,'Coded Passages'!$K:$K,"Cumbre internacional") -> 0 | G40: =SUM(C40:F40) -> 3
A41: D1.2 | B41: Selective Empiricism | C41: =COUNTIFS('Coded Passages'!$B:$B,$A41,'Coded Passages'!$C:$C,$B41,'Coded Passages'!$K:$K,"Debate presidencial") -> 0 | D41: =COUNTIFS('Coded Passages'!$B:$B,$A41,'Coded Passages'!$C:$C,$B41,'Coded Passages'!$K:$K,"Foro económico internacional") -> 2 | E41: =COUNTIFS('Coded Passages'!$B:$B,$A41,'Coded Passages'!$C:$C,$B41,'Coded Passages'!$K:$K,"Acto institucional") -> 0 | F41: =COUNTIFS('Coded Passages'!$B:$B,$A41,'Coded Passages'!$C:$C,$B41,'Coded Passages'!$K:$K,"Cumbre internacional") -> 0 | G41: =SUM(C41:F41) -> 2
A42: D1.3 | B42: Civilizational Defense | C42: =COUNTIFS('Coded Passages'!$B:$B,$A42,'Coded Passages'!$C:$C,$B42,'Coded Passages'!$K:$K,"Debate presidencial") -> 0 | D42: =COUNTIFS('Coded Passages'!$B:$B,$A42,'Coded Passages'!$C:$C,$B42,'Coded Passages'!$K:$K,"Foro económico internacional") -> 4 | E42: =COUNTIFS('Coded Passages'!$B:$B,$A42,'Coded Passages'!$C:$C,$B42,'Coded Passages'!$K:$K,"Acto institucional") -> 1 | F42: =COUNTIFS('Coded Passages'!$B:$B,$A42,'Coded Passages'!$C:$C,$B42,'Coded Passages'!$K:$K,"Cumbre internacional") -> 3 | G42: =SUM(C42:F42) -> 8
... A44: D1.3 | B44: Woke Bundling | C44: =COUNTIFS('Coded Passages'!$B:$B,$A44,'Coded Passages'!$C:$C,$B44,'Coded Passages'!$K:$K,"Debate presidencial") -> 0 | D44: =COUNTIFS('Coded Passages'!$B:$B,$A44,'Coded Passages'!$C:$C,$B44,'Coded Passages'!$K:$K,"Foro económico internacional") -> 3 | E44: =COUNTIFS('Coded Passages'!$B:$B,$A44,'Coded Passages'!$C:$C,$B44,'Coded Passages'!$K:$K,"Acto institucional") -> 0 | F44: =COUNTIFS('Coded Passages'!$B:$B,$A44,'Coded Passages'!$C:$C,$B44,'Coded Passages'!$K:$K,"Cumbre internacional") -> 2 | G44: =SUM(C44:F44) -> 5
A45: TOTAL | B45: All Sub-codes | C45: =SUM(C31:C44) -> 3 | D45: =SUM(D31:D44) -> 45 | E45: =SUM(E31:E44) -> 15 | F45: =SUM(F31:F44) -> 25 | G45: =SUM(G31:G44) -> 88
